Workbook
Name FEFCO_plot: Plot!$B$136:$J$161
Name FEFCOGEENPRIJS: Mastersheet!$A$64:$B$78
Name Kwaliteit_plot: Plot!$B$99:$E$131
Name Snelheid_plot: Plot!$C$71:$E$74
Name Tape_aantal_plot: Plot!$B$78:$B$92
Name Tape_prijs_plot: Plot!$C$78:$C$92
Name Tapen_plot: Plot!$B$78:$C$92

Sheet BLO
A1: Input | E1: Output | K1: LEVERTIJD
A2: FEFCO | B2: 0201 | C2: 500 | E2: per_price | F2: =Mastersheet!K43 -> 0.85 | K2: Pakketmaten
A3: Lengte | B3: 300 | E3: staffel2_qty | F3: =Mastersheet!L44 -> 1800 | K3: 200 stuks nog niet optimaal
A4: Breedte | B4: 250 | E4: staffel2_price | F4: =Mastersheet!K44 -> 0 | K4: grote dozen te goedkoop
A5: Hoogte | B5: 100 | E5: staffel3_qty | F5: =Mastersheet!L45 -> 1800 | K5: meerdere naar elkaar stapelen pakketmaat
A6: Kwaliteit | B6: 10010 | E6: staffel3_price | F6: =Mastersheet!K45 -> 0.42 | K6: Dozenlaten maken machine 2,5m breed
A7: Bedrukking | B7: onbedrukt | E7: staffel4_qty | F7: =Mastersheet!L46 -> 490
A8: Handgrepen | B8: geen handgrepen / stansbewerking | E8: staffel4_price | F8: =Mastersheet!K46 -> 0.7 | K8: Opmerking nog aanpassen
A9: Aantal | B9: 400 | E9: pallet_qty | F9: =Mastersheet!C88 -> 1800 | K9: Klein 427 bij doosopmaat in E golf te duur
E10: status | F10: =Mastersheet!M53 -> RegularPrice
E11: remark | F11: =Mastersheet!M58
A12: Rekenen bedrukking | B12: =IF(B7="Full color (CMYK)","onbedrukt",B7) -> onbedrukt | E12: deliverytime_from | F12: =Mastersheet!B100 -> 8
E13: deliverytime_to | F13: =Mastersheet!B101 -> 12
E17: Inkoop Fris | F17: =Input!B23 -> 0.72166405
E18: Inkoop Faes | F18: =Plot!D55 -> 1.2092969

Sheet Mastersheet
A1: Aantal gevraagd | D1: =Input!B17 -> 400 | M1: Code actief voor staffel 1 | N1: Code | O1: Tekst
A3: Stansdoos | D3: =VLOOKUP(Input!B6,Plot!FEFCO_plot,9,0) -> 0 | L3: Alleen prijzen van van Plotter gebruiken
A4: Bedrukte doos | D4: =IF(Input!B11="onbedrukt",0,1) -> 0 | L4: Alleen prijzen van van Boxmaker gebruiken | O4: Voor dozen met flexo bedrukking is de prijs exclusief eenmalige cliche kosten, vanaf 300 euro per drukkleur, afhankelijk van het ontwerp. SUPERTIP: Selecteer Full Color voor bedrukking ZONDER opstartkosten
A5: Digitale druk | D5: =IF(BLO!B7="Full color (CMYK)",1,0) -> 0
A6: m2 per verpakking | D6: =Rekenblad!H108 -> 0.402154
A7: 200 m2 is x dozen | D7: =CEILING(200/D6, 10) -> 500
A8: Snelle check | L8: Opmerking
A9: Doostype zonder prijs | D9: =VLOOKUP(Input!B6,A65:B78,2,0) -> 0 | L9: Direct code terug geven en geen berekening | M9: =D9 -> 0 | N9: MustRequestQuote | O9: Vraag een offerte aan voor snel een aanbod, deze samenstelling kunnen we helaas nog niet uitrekenen
A10: Bedrukte stansdoos | D10: =IF(AND(D4=1, D3=1), 1, 0) -> 0 | L10: Direct code terug geven en geen berekening | M10: =D10 -> 0 | N10: MustRequestQuote | O10: Selecteer de optie Full color voor direct een prijs. Bij aantallen boven 3000 stuks vraag een speciale prijs op
A11: Niet-stansdoos en niet maakbaar | D11: =IF(D3=1, 0, IF(Rekenblad!J1075=1, 0, 1)) -> 0 | L11: Direct code terug geven en geen berekening | M11: =D11 -> 0 | N11: MustRequestQuote | O11: Vraag een offerte aan voor snel een aanbod, deze samenstelling kunnen we helaas nog niet uitrekenen
A13: Welk staffels mogen aangeboden worden? | L13: Opmerking
A14: Staffel check | D14: Variabele 1 | F14: Variabele 2 | G14: Staffel 1 | H14: Staffel 2 | I14: Staffel 3 | J14: Staffel 4
A15: Aantal | G15: =VLOOKUP(1,B85:C91,2,0) -> 400 | H15: =VLOOKUP(2,B85:C91,2,0) -> 1800 | I15: =VLOOKUP(3,B85:C91,2,0) -> 1800 | J15: =VLOOKUP(4,B85:C91,2,0) -> 490
A16: Aantal m2 | G16: =G15*D6 -> 160.8616 | H16: =H15*D6 -> 723.8772 | I16: =I15*D6 -> 723.8772 | J16: =D6*J15 -> 197.05546 | L16: Meer m2 dan X voor altijd offerte | M16: =M22 -> 0 | N16: =N22 -> MustRequestQuote | O16: =O22 -> Voor dit aantal maken we graag een speciale aanbieding, vraag een offerte aan en ontvang snel een mooi aanbod.
A17: Meer m2 dan X voor vanaf prijs | B17: M2 | D17: 3500 | G17: =IF(G16>$D$17,1,0) -> 0 | H17: =IF(H16>$D$17,1,0) -> 0 | I17: =IF(I16>$D$17,1,0) -> 0 | J17: =IF(J16>$D$17,1,0) -> 0 | L17: Vanaf prijs | M17: =G17 -> 0 | N17: CanRequestBetterQuote | O17: Dit is een vanaf prijs, deze aantallen kunnen we vaak nóg voordeliger aanbieden. Vraag een offerte aan voor een scherp aanbod.
L19: Wel een prijs bij andere staffel | M19: =IF(AND(J43=0, J47>0), 1, 0) -> 0 | N19: OtherQtyHasPrice | O19: Het gevraagde aantal kunnen we niet aanbieden. SUPERTIP: Selecteer de optie Full color voor direct een prijs in klein oplage. Of kijk hieronder voor het minimale bestelaantal voor deze bedrukte doos.
A20: Meer m2 dan X en stansdoos | B20: M2 | D20: 1000 | E20: Stansdoos | F20: =D3 -> 0 | G20: =IF(G16>$D$20,1,0)*F20 -> 0 | H20: =IF(H16>$D$20,1,0)*F20 -> 0 | I20: =IF(I16>$D$20,1,0)*F20 -> 0 | J20: =IF(J16>$D$20,1,0)*F20 -> 0 | L20: Vanaf prijs | M20: =G20 -> 0 | N20: CanRequestBetterQuote | O20: Dit is een vanaf prijs, deze aantallen kunnen we voordeliger aanbieden met een andere productietechniek. Vraag een offerte aan voor een scherp aanbod.
A21: Minder dan X stuks | B21: Stuks | D21: 10 | G21: =IF(G15<$D$21,1,0) -> 0 | H21: =IF(H15<$D$21,1,0) -> 0 | I21: =IF(I15<$D$21,1,0) -> 0 | J21: =IF(J15<$D$21,1,0) -> 0 | L21: Geen prijs | M21: =G21 -> 0 | N21: NoPricePossible
A22: Meer m2 dan X voor altijd offerte | B22: M2 | D22: 8000 | G22: =IF(G16>$D$22,1,0) -> 0 | H22: =IF(H16>$D$22,1,0) -> 0 | I22: =IF(I16>$D$22,1,0) -> 0 | J22: =IF(J16>$D$22,1,0) -> 0 | L22: Geen prijs, alleen offerte | M22: =G22 -> 0 | N22: MustRequestQuote | O22: Voor dit aantal maken we graag een speciale aanbieding, vraag een offerte aan en ontvang snel een mooi aanbod.
A23: Minder dan X m2 bedrukt | B23: M2 | D23: 300 | E23: Bedrukt | F23: =D4 -> 0 | G23: =IF(G16<$D$23,1,0)*F23 -> 0 | H23: =IF(H16<$D$23,1,0)*F23 -> 0 | I23: =IF(I16<$D$23,1,0)*F23 -> 0 | J23: =IF(J16<$D$23,1,0)*F23 -> 0 | L23: Geen prijs | M23: =G23 -> 0 | N23: NoPricePossible
A24: Staffel staat er dubbel in | H24: =IF(OR(H15=G15, H15=I15, H15=J15), 1, 0) -> 1
A25: Staffel verbergen | G25: =IF(SUM(G21:G24) >= 1, 1, 0) -> 0 | H25: =IF(SUM(H20:H24) >= 1, 1, 0) -> 1 | I25: =IF(SUM(I20:I24) >= 1, 1, 0) -> 0 | J25: =IF(SUM(J20:J24) >= 1, 1, 0) -> 0
A27: Welk leveranciers mogen aangeboden worden?
E28: Diskwalificator
A29: Plotter prijzen gebruiken | B29: Stansdoos | D29: =D3 -> 0 | E29: 1
B30: Bedrukt | D30: =D4 -> 0 | E30: =IF(D30=1,0,1) -> 1
B31: Digitaal bedrukt en te groot | D31: =Digitaaldruk!J3 -> 0 | E31: =IF(AND(D5=1,D31=1),"0",1) -> 1
E32: =E30*E29*E31 -> 1 | F32: =IF(E32=0,"niet gebruiken","prijs gebruiken") -> prijs gebruiken
A34: Boxmaker prijzen gebruiken | B34: Stansdoos | D34: =D3 -> 0 | E34: =IF(D34=1,0,1) -> 1
B35: Bedrukt | D35: =D4 -> 0 | E35: 1
B36: Digitaal bedrukt en te groot | D36: =Digitaaldruk!J3 -> 0 | E36: =IF(AND(D5=1,D36=1),"0",1) -> 1
E37: =E35*E34*E36 -> 1 | F37: =IF(E37=0,"niet gebruiken","prijs gebruiken") -> prijs gebruiken
B38: Marge | E38: =IF(D4=1,E41,IF(D5=1,E40,E39)) -> 1.18
B39: Basismarge | E39: 1.18
B40: Digtale druk marge | E40: 1.35
B41: Flexo marge | E41: 1.22
B42: Staffel tonen | C42: Niet maakbaar | D42: Plotter | E42: Prijs | F42: Te gebruiken | G42: Boxmaker | H42: Prijs | I42: Te gebruiken | J42: Laagste prijs | K42: Afgerond | L42: Staffel hoeveelheid
A43: Staffel 1 | B43: =IF(G25=1,0,1) -> 1 | C43: =IF(D11=1,0,1) -> 1 | D43: =E32 -> 1 | E43: =IFERROR(Plot!F1, 0) -> 1.5720859 | F43: =E43*D43*B43*C43 -> 1.5720859 | G43: =E37 -> 1 | H43: =IFERROR(Input!B23*E38, 0) -> 0.85156357 | I43: =H43*G43*B43*C43 -> 0.85156357 | J43: =IF(AND(F43=0,I43=0),0,IF(F43=0,I43,IF(I43=0,F43,MIN(F43,I43)))) -> 0.85156357 | K43: =ROUND(J43,2) -> 0.85 | L43: =G15 -> 400
A44: Staffel 2 | B44: =IF(H25=1,0,1) -> 0 | C44: =IF(D11=1,0,1) -> 1 | D44: =E32 -> 1 | E44: =IFERROR(Plot!R1, 0) -> 1.2568627 | F44: =E44*D44*B44*C44 -> 0 | G44: =E37 -> 1 | H44: =IFERROR('Input (2)'!B23*E38, 0) -> 0.42205112 | I44: =H44*G44*B44*C44 -> 0 | J44: =IF(AND(F44=0,I44=0),0,IF(F44=0,I44,IF(I44=0,F44,MIN(F44,I44)))) -> 0 | K44: =ROUND(J44,2) -> 0 | L44: =H15 -> 1800
A45: Staffel 3 | B45: =IF(I25=1,0,1) -> 1 | C45: =IF(D11=1,0,1) -> 1 | D45: =E32 -> 1 | E45: =IFERROR(Plot!AB1, 0) -> 1.2568627 | F45: =E45*D45*B45*C45 -> 1.2568627 | G45: =E37 -> 1 | H45: =IFERROR('Input (3)'!B23*E38, 0) -> 0.42205112 | I45: =H45*G45*B45*C45 -> 0.42205112 | J45: =IF(AND(F45=0,I45=0),0,IF(F45=0,I45,IF(I45=0,F45,MIN(F45,I45)))) -> 0.42205112 | K45: =ROUND(J45,2) -> 0.42 | L45: =I15 -> 1800
A46: Staffel 4 | B46: =IF(J25=1,0,1) -> 1 | C46: =IF(D11=1,0,1) -> 1 | D46: =E32 -> 1 | E46: =IFERROR(Plot!AL1, 0) -> 1.5092759 | F46: =E46*D46*B46*C46 -> 1.5092759 | G46: =E37 -> 1 | H46: =IFERROR('Input (4)'!B23*E38, 0) -> 0.69956716 | I46: =H46*G46*B46*C46 -> 0.69956716 | J46: =IF(AND(F46=0,I46=0),0,IF(F46=0,I46,IF(I46=0,F46,MIN(F46,I46)))) -> 0.69956716 | K46: =ROUND(J46,2) -> 0.7 | L46: =J15 -> 490
J47: =SUM(J43:J46) -> 1.9731819 | L47: Alle prijzen 0 | M47: =IF(J47=0,1,0) -> 0 | N47: MustRequestQuote
M49: 1 | N49: RegularPrice
A51: Remarks en code
A53: Remark 2 bedrukking weergeven | B53: Voor dozen met flexo bedrukking is de prijs exclusief eenmalige cliche kosten, vanaf 300 euro per drukkleur, afhankelijk van het ontwerp. Selecteer Full Color voor bedrukking ZONDER opstartkosten | L53: Eerste code beschikbaar | M53: =VLOOKUP(1,M9:O51,2,0) -> RegularPrice
A54: Som snelle check | B54: =SUM(M9:M11) -> 0 | L54: Remark 1 | M54: =VLOOKUP(1,M9:O52,3,0)
A55: Stafel verborgen | B55: =G25 -> 0 | L55: Remark 2 bedrukking | M55: =IF(B57>0,"", B53)
A56: Onbedrukte doos | B56: =IF(D4=1,0,1) -> 1
B57: =SUM(B54:B56) -> 1
L58: Gecombineerde remark | M58: =M54
A63: Doostype wel/niet prijs
A64: FEFCO | B64: Geen prijs
A65: 0427 | B65: 0
A66: 0409 | B66: 0
A67: 0200 | B67: 0
A68: 0452 | B68: 0
A69: 0422 | B69: 0
A70: 0201 | B70: 0
A71: 0203 | B71: 0
A72: 0110 | B72: 0
A73: 0401 | B73: 1
A74: 0421 | B74: 0
A75: 0471 | B75: 0
A76: 0401 | B76: 0
... A78: 0933 | B78: 1
A83: Staffels
B84: Staffel | D84: Variabele | E84: Waarde
A85: Gevraagd aantal | B85: 1 | C85: =Input!B17 -> 400
A86: Aantal x2 (bij grote aantallen afgerond op pallet) | B86: 2 | C86: =IF(C85 < E86 * C87, C85 * 2, CEILING(C85 * 2, C88)) -> 1800 | D86: Percentage van minimale afname | E86: 0.4
A87: Aantal minimale afname | B87: =IF(OR(C85>C87, B91=4), 0, 4) -> 4 | C87: =IF(AND(ISNUMBER(Input!C21)), Input!C21, D7) -> 490
A88: Aantal per pallet | C88: =IF(OR(Input!B31="", ISNUMBER(Input!B31)=FALSE), 0, Input!B31) -> 1800
A89: Afgerond op volle pallet | B89: 3 | C89: =IF(C85<C88,C88,MROUND(C85,C88)) -> 1800
A90: Volgende pallet | B90: =IF(OR(C85<=C87, B91=4), 0, 4) -> 0 | C90: =C89+C88 -> 3600
A91: Minimaal hoeveelheid bedrukt | B91: =IF(AND(C85<C91, D4=1), 4, 0) -> 0 | C91: =CEILING(D23/D6, 5) -> 750
A99: Levertijd
A100: van | B100: 8 | C100: werkdagen
A101: tot | B101: =IF(OR(D4=1,D5=1),B103,B102) -> 12 | C101: werkdagen
A102: Onbedrukt | B102: 12
A103: Bedrukt | B103: 16
A107: Bedrukking
A108: Rekenen met onbedrukt en bedrukking apart | B108: Full color (CMYK)
A110: onbedrukt
A111: zwart
A112: 1 kleur naar keuze
A113: 2 kleuren naar keuze
A114: Full color (CMYK)

Sheet Digitaaldruk
A2: Aanschaf | B2: 200000
A3: Afschrijving | B3: 60 | C3: maanden | D3: Doos | E3: =BLO!B3 -> 300 | F3: =BLO!B4 -> 250 | G3: =BLO!B5 -> 100 | I3: Te groot | J3: =IF(AND(E46>2500,E47>2500),1,0) -> 0
B4: 80 | C4: uren per maand
A5: Afschijving per maand | B5: =B2/B3 -> 3333.3333
A6: Onderhoud per maand | B6: =(B2*0.1)/12 -> 1666.6667 | D6: Plano | E6: Plano
A7: Kosten afschrijving plus onderhoud | B7: =B5+B6 -> 5000 | D7: Breedte | E7: Lengte | F7: M2
A8: Kosten afschrijving plus onderhoud / uur | B8: =B7/B4 -> 62.5 | D8: =Plot!G9 -> 361 | E8: =Plot!G10 -> 1114 | F8: =D8*E8 -> 402154
D10: 600 | E10: m2/uur
A11: Inkt per maand | B11: 300 | C11: (28 euro per liter)
A12: Prints per maand | B12: 20000 | E12: DPI
A13: Kost inkt per print | B13: =B11/B12 -> 0.015 | D13: Low | E13: 200x600 | G13: =E8/F13/1000 -> #DIV/0! | H13: seconde per product
D14: Middle | E14: 300x600 | G14: =E8/F14/1000 -> #DIV/0! | H14: seconde per product
A15: Instel machine | B15: 20 | C15: minuten | D15: High | E15: 600x600 | F15: 1 | G15: =E8/F15/1000 -> 1.114 | H15: seconde per product
A16: Per order kartoor | B16: 25 | C16: euro
A17: Extra handling | B17: 10 | D17: Tijd totale run | F17: Seconde | G17: =G15*G21 -> 445.6 | H17: =G15*H21 -> 2005.2 | I17: =G15*I21 -> 2005.2 | J17: =G15*J21 -> 545.86
B18: =SUM(B16:B17) -> 35 | F18: Minuten | G18: =G17/60 -> 7.4266667 | H18: =H17/60 -> 33.42 | I18: =I17/60 -> 33.42 | J18: =J17/60 -> 9.0976667
A19: Operator cost per dag | F19: Uren | G19: =G18/60 -> 0.12377778 | H19: =H18/60 -> 0.557 | I19: =I18/60 -> 0.557 | J19: =J18/60 -> 0.15162778
A20: Bruto loon | B20: 4000
A21: Bruto naar kosten | B21: 0.63 | D21: Prijsopbouw | F21: Aantal | G21: =BLO!B9 -> 400 | H21: =Mastersheet!L44 -> 1800 | I21: =Mastersheet!L45 -> 1800 | J21: =Mastersheet!L46 -> 490
B22: =B21*B20 -> 2520 | G22: Per stuk
A23: Totaal kosten | B23: =B20+B22 -> 6520 | D23: Order kosten | E23: =B44 -> 91.336616 | F23: per order | G23: =$E$23/G21 -> 0.22834154 | H23: =$E$23/H21 -> 0.050742565 | I23: =$E$23/I21 -> 0.050742565 | J23: =$E$23/J21 -> 0.18640126
A24: Uren per maand | B24: 165 | D24: Uur kosten | E24: =B57 -> 169.00985 | F24: per uur | G24: =G19*$E$24/G21 -> 0.052299159 | H24: =H19*$E$24/H21 -> 0.052299159 | I24: =I19*$E$24/I21 -> 0.052299159 | J24: =J19*$E$24/J21 -> 0.052299159
A25: Tarief per uur | B25: =B23/165 -> 39.515152 | D25: Inkt kosten | G25: =$B$59 -> 0.015 | H25: =$B$59 -> 0.015 | I25: =$B$59 -> 0.015 | J25: =$B$59 -> 0.015
A26: Marge op tarief | B26: 0.15 | D26: Extra marge | E26: 0.2 | G26: =SUM(G23:G25)*$E$26 -> 0.05912814 | H26: =SUM(H23:H25)*$E$26 -> 0.023608345 | I26: =SUM(I23:I25)*$E$26 -> 0.023608345 | J26: =SUM(J23:J25)*$E$26 -> 0.050740083
A27: Kosten 1* operator / uur | B27: =B25+B25*B26 -> 45.442424
A28: Kosten 2* Operator / uur | B28: =B27*2 -> 90.884848 | D28: Totale extra kosten per stuk | G28: =SUM(G23:G26) -> 0.35476884 | H28: =SUM(H23:H26) -> 0.14165007 | I28: =SUM(I23:I26) -> 0.14165007 | J28: =SUM(J23:J26) -> 0.3044405
F29: afgerond | G29: =ROUND(G28,2) -> 0.35 | H29: =ROUND(H28,2) -> 0.14 | I29: =ROUND(I28,2) -> 0.14 | J29: =ROUND(J28,2) -> 0.3
A30: Huisvesting m2 | B30: 300 | C30: per m2 | E30: Prijs per m2 | G30: =(G28-G23)/F8*1000000 -> 0.31437534 | H30: =(H28-H23)/F8*1000000 -> 0.22605147 | I30: =(I28-I23)/F8*1000000 -> 0.22605147 | J30: =(J28-J23)/F8*1000000 -> 0.29351751
A31: Kosten Huisvesting per uur | B31: =((B30*50)/(B4*12)) -> 15.625
A33: Stroom | B33: 3
D34: Prijs digitaaldruk | G34: =Digitaaldruk!G28 -> 0.35476884 | H34: =Digitaaldruk!H28 -> 0.14165007 | I34: =Digitaaldruk!I28 -> 0.14165007 | J34: =Digitaaldruk!J28 -> 0.3044405
A36: Kosten overzicht per order
A37: Order kosten | B37: =B18 -> 35
A38: Machine instellen | B38: =B15*B57/60 -> 56.336616
D39: Totaalprijs | G39: =SUM(G34) -> 0.35476884 | H39: =SUM(H34) -> 0.14165007 | I39: =SUM(I34) -> 0.14165007 | J39: =SUM(J34) -> 0.3044405
D40: Te gebruiken prijs | G40: =Mastersheet!$D$5*Digitaaldruk!G39 -> 0 | H40: =Mastersheet!$D$5*Digitaaldruk!H39 -> 0 | I40: =Mastersheet!$D$5*Digitaaldruk!I39 -> 0 | J40: =Mastersheet!$D$5*Digitaaldruk!J39 -> 0
D42: Extra marge | E42: Waarde | F42: Voorwaarde | G42: Marge | H42: Toevoegen
D43: Doostype | E43: =BLO!B2 -> 0201 | F43: 0201 | G43: 0.04 | H43: =IF(E43=F43,G43,0) -> 0.04
A44: Totaal | B44: =SUM(B37:B43) -> 91.336616 | D44: Formaat | E44: =BLO!B3*BLO!B4*BLO!B5 -> 7500000 | F44: 100000000 | G44: 0.05 | H44: =IF(E44>F44,G44,0) -> 0
A45: Kosten per uur | D45: Formaat | E45: =BLO!B3*BLO!B4*BLO!B5 -> 7500000 | F45: 200000000 | G45: 0 | H45: =IF(E45>F45,G45,0) -> 0
A46: Afschrijving / onderhoud | B46: =B8 -> 62.5 | D46: Plano formaat | E46: =Plot!G9 -> 361
A47: Operator | B47: =B28 -> 90.884848 | D47: Plano formaat | E47: =Plot!G10 -> 1114 | F47: 2550 | G47: 0.1 | H47: =IF(E47>F47,G47,0) -> 0
A48: Huisvesting | B48: =B31 -> 15.625
H51: =SUM(H43:H50) -> 0.04
A57: Totaal | B57: =SUM(B46:B53) -> 169.00985
A58: Kosten overzicht per print
A59: Inkt | B59: =B13 -> 0.015
A65: Totaal | B65: =SUM(B58:B64) -> 0.015

Sheet Plot
A1: Input | B1: FEFCO | C1: =Input!B6 -> 0201 | E1: Verkoopprijs | F1: =D59+Digitaaldruk!G40 -> 1.5720859 | M1: Input | N1: FEFCO | O1: =$C$1 -> 0201 | Q1: Verkoopprijs | R1: =P59+Digitaaldruk!H40 -> 1.2568627 | W1: Input | X1: FEFCO | Y1: =$C$1 -> 0201 | AA1: Verkoopprijs | AB1: =Z59+Digitaaldruk!I40 -> 1.2568627 | AG1: Input | AH1: FEFCO | AI1: =$C$1 -> 0201 | AK1: Verkoopprijs | AL1: =AJ59+Digitaaldruk!J40 -> 1.5092759
B2: Lengte | C2: =Input!B7 -> 300 | N2: Lengte | O2: =$C$2 -> 300 | X2: Lengte | Y2: =$C$2 -> 300 | AH2: Lengte | AI2: =$C$2 -> 300
B3: Breedte | C3: =Input!B8 -> 250 | N3: Breedte | O3: =$C$3 -> 250 | X3: Breedte | Y3: =$C$3 -> 250 | AH3: Breedte | AI3: =$C$3 -> 250
B4: Hoogte | C4: =Input!B9 -> 100 | N4: Hoogte | O4: =$C$4 -> 100 | X4: Hoogte | Y4: =$C$4 -> 100 | AH4: Hoogte | AI4: =$C$4 -> 100
B5: Karton | C5: =Input!B2 -> 10010 | N5: Karton | O5: =$C$5 -> 10010 | X5: Karton | Y5: =$C$5 -> 10010 | AH5: Karton | AI5: =$C$5 -> 10010
B6: Aantal | C6: =Input!B17 -> 400 | N6: Aantal | O6: =Mastersheet!H15 -> 1800 | X6: Aantal | Y6: =Mastersheet!I15 -> 1800 | AH6: Aantal | AI6: =Mastersheet!J15 -> 490
A8: Berekening | C8: Lengte | D8: Breedte | E8: Hoogte | F8: Extra | G8: Totaal | I8: Productformaat | M8: Berekening | O8: Lengte | P8: Breedte | Q8: Hoogte | R8: Extra | S8: Totaal | U8: Productformaat | W8: Berekening | Y8: Lengte | Z8: Breedte | AA8: Hoogte | AB8: Extra | AC8: Totaal | AE8: Productformaat | AG8: Berekening | AI8: Lengte | AJ8: Breedte | AK8: Hoogte | AL8: Extra | AM8: Totaal | AO8: Productformaat
B9: Planobreedte (golfrichting) | G9: =VLOOKUP($C$1,Rekenblad!B74:G107,2,0) -> 361 | I9: =VLOOKUP($C$1,Rekenblad!B74:G107,5,0) -> 361 | S9: =G9 -> 361 | U9: =I9 -> 361 | X9: Planobreedte | AC9: =S9 -> 361 | AE9: =U9 -> 361 | AH9: Planobreedte | AM9: =AC9 -> 361 | AO9: =AE9 -> 361
B10: Planolengte | G10: =VLOOKUP($C$1,Rekenblad!B74:G107,3,0) -> 1114 | I10: =VLOOKUP($C$1,Rekenblad!B74:G107,6,0) -> 557 | S10: =G10 -> 1114 | U10: =I10 -> 557 | X10: Planolengte | AC10: =S10 -> 1114 | AE10: =U10 -> 557 | AH10: Planolengte | AM10: =AC10 -> 1114 | AO10: =AE10 -> 557
B11: M2 | C11: =G9*G10/1000000 -> 0.402154 | N11: M2 | O11: =S9*S10/1000000 -> 0.402154 | X11: M2 | Y11: =AC9*AC10/1000000 -> 0.402154 | AH11: M2 | AI11: =AM9*AM10/1000000 -> 0.402154
B12: M2 totaal | C12: =C11*C6 -> 160.8616 | N12: M2 totaal | O12: =O11*O6 -> 723.8772 | X12: M2 totaal | Y12: =Y11*Y6 -> 723.8772 | AH12: M2 totaal | AI12: =AI11*AI6 -> 197.05546
C14: Lengte | D14: Breedte | E14: Hoogte | F14: Totaal | G14: Snelheid | O14: Lengte | P14: Breedte | Q14: Hoogte | R14: Totaal | S14: Snelheid | Y14: Lengte | Z14: Breedte | AA14: Hoogte | AB14: Totaal | AC14: Snelheid | AI14: Lengte | AJ14: Breedte | AK14: Hoogte | AL14: Totaal | AM14: Snelheid
B15: Snijlengte | C15: =VLOOKUP($C$1,FEFCO_plot,3,0) -> 4 | D15: =VLOOKUP($C$1,FEFCO_plot,4,0) -> 12 | E15: =VLOOKUP($C$1,FEFCO_plot,5,0) -> 2 | F15: =C15*C2+D15*C3+E15*C4 -> 4400 | G15: =VLOOKUP(C11,Snelheid_plot,3,1) -> 300 | N15: Snijlengte | O15: =VLOOKUP($C$1,FEFCO_plot,3,0) -> 4 | P15: =VLOOKUP($C$1,FEFCO_plot,4,0) -> 12 | Q15: =VLOOKUP($C$1,FEFCO_plot,5,0) -> 2 | R15: =O15*O2+P15*O3+Q15*O4 -> 4400 | S15: =VLOOKUP(O11,Snelheid_plot,3,1) -> 300 | X15: Snijlengte | Y15: =VLOOKUP($C$1,FEFCO_plot,3,0) -> 4 | Z15: =VLOOKUP($C$1,FEFCO_plot,4,0) -> 12 | AA15: =VLOOKUP($C$1,FEFCO_plot,5,0) -> 2 | AB15: =Y15*Y2+Z15*Y3+AA15*Y4 -> 4400 | AC15: =VLOOKUP(Y11,Snelheid_plot,3,1) -> 300 | AH15: Snijlengte | AI15: =VLOOKUP($C$1,FEFCO_plot,3,0) -> 4 | AJ15: =VLOOKUP($C$1,FEFCO_plot,4,0) -> 12 | AK15: =VLOOKUP($C$1,FEFCO_plot,5,0) -> 2 | AL15: =AI15*AI2+AJ15*AI3+AK15*AI4 -> 4400 | AM15: =VLOOKUP(AI11,Snelheid_plot,3,1) -> 300
B16: Rillengte | C16: =VLOOKUP($C$1,FEFCO_plot,6,0) -> 4 | D16: =VLOOKUP($C$1,FEFCO_plot,7,0) -> 4 | E16: =VLOOKUP($C$1,FEFCO_plot,8,0) -> 4 | F16: =C16*C2+D16*C3+E16*C4 -> 2600 | G16: =VLOOKUP(C11,Snelheid_plot,2,1) -> 700 | N16: Rillengte | O16: =VLOOKUP($C$1,FEFCO_plot,6,0) -> 4 | P16: =VLOOKUP($C$1,FEFCO_plot,7,0) -> 4 | Q16: =VLOOKUP($C$1,FEFCO_plot,8,0) -> 4 | R16: =O16*O2+P16*O3+Q16*O4 -> 2600 | S16: =VLOOKUP(O11,Snelheid_plot,2,1) -> 700 | X16: Rillengte | Y16: =VLOOKUP($C$1,FEFCO_plot,6,0) -> 4 | Z16: =VLOOKUP($C$1,FEFCO_plot,7,0) -> 4 | AA16: =VLOOKUP($C$1,FEFCO_plot,8,0) -> 4 | AB16: =Y16*Y2+Z16*Y3+AA16*Y4 -> 2600 | AC16: =VLOOKUP(Y11,Snelheid_plot,2,1) -> 700 | AH16: Rillengte | AI16: =VLOOKUP($C$1,FEFCO_plot,6,0) -> 4 | AJ16: =VLOOKUP($C$1,FEFCO_plot,7,0) -> 4 | AK16: =VLOOKUP($C$1,FEFCO_plot,8,0) -> 4 | AL16: =AI16*AI2+AJ16*AI3+AK16*AI4 -> 2600 | AM16: =VLOOKUP(AI11,Snelheid_plot,2,1) -> 700
B18: Seconden per verpakking | D18: =F15/G15+F16/G16 -> 18.380952 | N18: Seconden per verpakking | P18: =R15/S15+R16/S16 -> 18.380952 | X18: Seconden per verpakking | Z18: =AB15/AC15+AB16/AC16 -> 18.380952 | AH18: Seconden per verpakking | AJ18: =AL15/AM15+AL16/AM16 -> 18.380952
B19: Uurtarief | D19: =Plot!C64 -> 65 | N19: Uurtarief | P19: =Plot!$C$64 -> 65 | X19: Uurtarief | Z19: =Plot!$C$64 -> 65 | AH19: Uurtarief | AJ19: =Plot!$C$64 -> 65
B20: Secondetarief | D20: =D19/3600 -> 0.018055556 | N20: Secondetarief | P20: =P19/3600 -> 0.018055556 | X20: Secondetarief | Z20: =Z19/3600 -> 0.018055556 | AH20: Secondetarief | AJ20: =AJ19/3600 -> 0.018055556
B21: Machinetarief | D21: =D20*D18 -> 0.33187831 | N21: Machinetarief | P21: =P20*P18 -> 0.33187831 | X21: Machinetarief | Z21: =Z20*Z18 -> 0.33187831 | AH21: Machinetarief | AJ21: =AJ20*AJ18 -> 0.33187831
B23: Formaat plaat | D23: 3000 | E23: 2200 | N23: Formaat plaat | P23: =$D$23 -> 3000 | Q23: =$E$23 -> 2200 | X23: Formaat plaat | Z23: =$D$23 -> 3000 | AA23: =$E$23 -> 2200 | AH23: Formaat plaat | AJ23: =$D$23 -> 3000 | AK23: =$E$23 -> 2200
B24: Aantal lengte | D24: =D23/G10 -> 2.6929982 | N24: Aantal lengte | P24: =P23/S10 -> 2.6929982 | X24: Aantal lengte | Z24: =Z23/AC10 -> 2.6929982 | AH24: Aantal lengte | AJ24: =AJ23/AM10 -> 2.6929982
B25: Aantal breedte | E25: =E23/G9 -> 6.0941828 | N25: Aantal breedte | Q25: =Q23/S9 -> 6.0941828 | X25: Aantal breedte | AA25: =AA23/AC9 -> 6.0941828 | AH25: Aantal breedte | AK25: =AK23/AM9 -> 6.0941828
B27: Aantal per moederplaat | D27: =INT(D24) -> 2 | E27: =INT(E25) -> 6 | F27: =E27*D27 -> 12 | N27: Aantal per moederplaat | P27: =INT(P24) -> 2 | Q27: =INT(Q25) -> 6 | R27: =Q27*P27 -> 12 | X27: Aantal per moederplaat | Z27: =INT(Z24) -> 2 | AA27: =INT(AA25) -> 6 | AB27: =AA27*Z27 -> 12 | AH27: Aantal per moederplaat | AJ27: =INT(AJ24) -> 2 | AK27: =INT(AK25) -> 6 | AL27: =AK27*AJ27 -> 12
B29: Prijs per moederplaat | D29: =VLOOKUP(C5,B100:E130,4,0) -> 0.50976 | E29: m2 | F29: =D23*E23/1000000*D29 -> 3.364416 | N29: Prijs per moederplaat | P29: =VLOOKUP(C5,B100:E130,4,0) -> 0.50976 | Q29: m2 | R29: =P23*Q23/1000000*P29 -> 3.364416 | X29: Prijs per moederplaat | Z29: =VLOOKUP(C5,B100:E130,4,0) -> 0.50976 | AA29: m2 | AB29: =Z23*AA23/1000000*Z29 -> 3.364416 | AH29: Prijs per moederplaat | AJ29: =VLOOKUP(C5,B100:E130,4,0) -> 0.50976 | AK29: m2 | AL29: =AJ23*AK23/1000000*AJ29 -> 3.364416
D31: Voorraad | E31: Op maat | P31: Voorraad | Q31: Op maat | Z31: Voorraad | AA31: Op maat | AJ31: Voorraad | AK31: Op maat
B32: Materiaal per product | D32: =F29/F27 -> 0.280368 | E32: =C11*D29 -> 0.20500202 | N32: Materiaal per product | P32: =R29/R27 -> 0.280368 | Q32: =O11*P29 -> 0.20500202 | X32: Materiaal per product | Z32: =AB29/AB27 -> 0.280368 | AA32: =Y11*Z29 -> 0.20500202 | AH32: Materiaal per product | AJ32: =AL29/AL27 -> 0.280368 | AK32: =AI11*AJ29 -> 0.20500202
B33: Materiaalprijs | D33: =IF(AND(C12>300, C6>=250), E32, D32) -> 0.280368 | N33: Materiaalprijs | P33: =IF(AND(O12>300, O6>=250), Q32, P32) -> 0.20500202 | X33: Materiaalprijs | Z33: =IF(AND(Y12>300, Y6>=250), AA32, Z32) -> 0.20500202 | AH33: Materiaalprijs | AJ33: =IF(AND(AI12>300, AI6>=250), AK32, AJ32) -> 0.280368
B34: Pallethoogte | D34: 2100 | N34: Pallethoogte | P34: 2100 | X34: Pallethoogte | Z34: 2100 | AH34: Pallethoogte | AJ34: 2100
B35: Product lijmen/tapen | D35: =VLOOKUP(C1,FEFCO_plot,2,0) -> Ja | N35: Product lijmen/tapen | P35: =VLOOKUP(O1,FEFCO_plot,2,0) -> Ja | X35: Product lijmen/tapen | Z35: =VLOOKUP(Y1,FEFCO_plot,2,0) -> Ja | AH35: Product lijmen/tapen | AJ35: =VLOOKUP(AI1,FEFCO_plot,2,0) -> Ja
B36: Kosten lijmen/tapen vast | D36: =IF(D35="Nee",0,E36) -> 0.27333333 | E36: {=IF(COUNTIF(Tape_aantal_plot,">="&C6)>0, VLOOKUP(C6,Tapen_plot,2,TRUE) + (C6 - VLOOKUP(C6,Tape_aantal_plot,1,TRUE)) * (INDEX(Tape_prijs_plot, MATCH(TRUE, Tape_aantal_plot > C6, 0)) - VLOOKUP(C6,Tapen_plot,2,TRUE)) / (INDEX(Tape_aantal_plot, MATCH(TRUE, Tape_aantal_plot > C6, 0)) - VLOOKUP(C6,Tape_aantal_plot,1,TRUE)), VLOOKUP(C6,Tapen_plot,2,TRUE) )} -> 0.27333333 | N36: Kosten lijmen/tapen vast | P36: =IF(P35="Nee",0,Q36) -> 0.26 | Q36: {=IF(COUNTIF(Tape_aantal_plot,">="&O6)>0, VLOOKUP(O6,Tapen_plot,2,TRUE) + (O6 - VLOOKUP(O6,Tape_aantal_plot,1,TRUE)) * (INDEX(Tape_prijs_plot, MATCH(TRUE, Tape_aantal_plot > O6, 0)) - VLOOKUP(O6,Tapen_plot,2,TRUE)) / (INDEX(Tape_aantal_plot, MATCH(TRUE, Tape_aantal_plot > O6, 0)) - VLOOKUP(O6,Tape_aantal_plot,1,TRUE)), VLOOKUP(O6,Tapen_plot,2,TRUE) )} -> 0.26 | X36: Kosten lijmen/tapen vast | Z36: =IF(Z35="Nee",0,AA36) -> 0.26 | AA36: {=IF(COUNTIF(Tape_aantal_plot,">="&Y6)>0, VLOOKUP(Y6,Tapen_plot,2,TRUE) + (Y6 - VLOOKUP(Y6,Tape_aantal_plot,1,TRUE)) * (INDEX(Tape_prijs_plot, MATCH(TRUE, Tape_aantal_plot > Y6, 0)) - VLOOKUP(Y6,Tapen_plot,2,TRUE)) / (INDEX(Tape_aantal_plot, MATCH(TRUE, Tape_aantal_plot > Y6, 0)) - VLOOKUP(Y6,Tape_aantal_plot,1,TRUE)), VLOOKUP(Y6,Tapen_plot,2,TRUE) )} -> 0.26 | AH36: Kosten lijmen/tapen vast | AJ36: =IF(AJ35="Nee",0,AK36) -> 0.26133333 | AK36: {=IF(COUNTIF(Tape_aantal_plot,">="&AI6)>0, VLOOKUP(AI6,Tapen_plot,2,TRUE) + (AI6 - VLOOKUP(AI6,Tape_aantal_plot,1,TRUE)) * (INDEX(Tape_prijs_plot, MATCH(TRUE, Tape_aantal_plot > AI6, 0)) - VLOOKUP(AI6,Tapen_plot,2,TRUE)) / (INDEX(Tape_aantal_plot, MATCH(TRUE, Tape_aantal_plot > AI6, 0)) - VLOOKUP(AI6,Tape_aantal_plot,1,TRUE)), VLOOKUP(AI6,Tapen_plot,2,TRUE) )} -> 0.26133333
B37: Kosten lijmen/tapen variabel | D37: =IF(D35="Ja",C4*Plot!C67,0) -> 0.026 | N37: Kosten lijmen/tapen variabel | P37: =IF(P35="Ja",O4*Plot!C67,0) -> 0.026 | X37: Kosten lijmen/tapen variabel | Z37: =IF(Z35="Ja",Y4*Plot!C67,0) -> 0.026 | AH37: Kosten lijmen/tapen variabel | AJ37: =IF(AJ35="Ja",AI4*Plot!C67,0) -> 0.026
B39: Aantal per pallet | D39: =Input!B31 -> 1800 | N39: Aantal per pallet | P39: =D39 -> 1800 | X39: Aantal per pallet | Z39: =P39 -> 1800 | AH39: Aantal per pallet | AJ39: =Z39 -> 1800
B42: M2 prijs transport | D42: =Plot!C63 -> 50 | N42: M2 prijs transport | P42: =Plot!$C$63 -> 50 | X42: M2 prijs transport | Z42: =Plot!$C$63 -> 50 | AH42: M2 prijs transport | AJ42: =Plot!$C$63 -> 50
B43: Aantal m2 transport | D43: =('Pallet en transport'!D151*'Pallet en transport'!E151)/1000000 -> 1.2996 | N43: Aantal m2 transport | P43: =D43 -> 1.2996 | X43: Aantal m2 transport | Z43: =P43 -> 1.2996 | AH43: Aantal m2 transport | AJ43: =Z43 -> 1.2996
B44: Transport per stuk | D44: =IF(D45=0, 'Pallet en transport'!E196*E44, C68/C6) -> 0.19771723 | E44: 1.05 | N44: Transport per stuk | P44: =IF(P45=0, 'Pallet en transport (2)'!E196*Q44, C68/O6) -> 0.043937163 | Q44: =E44 -> 1.05 | X44: Transport per stuk | Z44: =IF(Z45=0, 'Pallet en transport (3)'!E196*AA44, C68/Y6) -> 0.043937163 | AA44: =Q44 -> 1.05 | AH44: Transport per stuk | AJ44: =IF(AJ45=0, 'Pallet en transport (4)'!E196*AK44, C68/AI6) -> 0.16140182 | AK44: =AA44 -> 1.05
B45: Pakketpost | D45: =I162 -> 0 | N45: Pakketpost | P45: =K162 -> 0 | X45: Pakketpost | Z45: =M162 -> 0 | AH45: Pakketpost | AJ45: =O162 -> 0
B46: Orderkosten | D46: =Plot!C66 -> 0 | N46: Orderkosten | P46: =Plot!$C$66 -> 0 | X46: Orderkosten | Z46: =Plot!$C$66 -> 0 | AH46: Orderkosten | AJ46: =Plot!$C$66 -> 0
B48: Totaalprijs | N48: Totaalprijs | X48: Totaalprijs | AH48: Totaalprijs
B49: Uitbreken | D49: =Plot!C65 -> 0.1 | N49: Uitbreken | P49: =Plot!$C$65 -> 0.1 | X49: Uitbreken | Z49: =Plot!$C$65 -> 0.1 | AH49: Uitbreken | AJ49: =Plot!$C$65 -> 0.1
B50: Machine | D50: =D21 -> 0.33187831 | N50: Machine | P50: =P21 -> 0.33187831 | X50: Machine | Z50: =Z21 -> 0.33187831 | AH50: Machine | AJ50: =AJ21 -> 0.33187831
B51: Lijmen/tapen | D51: =D37+D36 -> 0.29933333 | N51: Lijmen/tapen | P51: =P37+P36 -> 0.286 | X51: Lijmen/tapen | Z51: =Z37+Z36 -> 0.286 | AH51: Lijmen/tapen | AJ51: =AJ37+AJ36 -> 0.28733333
B52: Materiaal | D52: =D33 -> 0.280368 | N52: Materiaal | P52: =P33 -> 0.20500202 | X52: Materiaal | Z52: =Z33 -> 0.20500202 | AH52: Materiaal | AJ52: =AJ33 -> 0.280368
B53: Transport | D53: =D44 -> 0.19771723 | N53: Transport | P53: =P44 -> 0.043937163 | X53: Transport | Z53: =Z44 -> 0.043937163 | AH53: Transport | AJ53: =AJ44 -> 0.16140182
B54: Order kosten | D54: =D46/C6 -> 0 | N54: Order kosten | P54: =P46/O6 -> 0 | X54: Order kosten | Z54: =Z46/Y6 -> 0 | AH54: Order kosten | AJ54: =AJ46/AI6 -> 0
B55: Inkoop | D55: =SUM(D49:D54) -> 1.2092969 | N55: Inkoop | P55: =SUM(P49:P54) -> 0.96681749 | X55: Inkoop | Z55: =SUM(Z49:Z54) -> 0.96681749 | AH55: Inkoop | AJ55: =SUM(AJ49:AJ54) -> 1.1609815
B57: Marge Superdoos | C57: =VLOOKUP(C1,B136:K150,10,0) -> 0.3 | D57: =IF(F57<$C$69, G57, E57) -> 0.36278906 | E57: =SUM(D49:D54)*C57 -> 0.36278906 | F57: =E57*C6 -> 145.11562 | G57: =$C$69/C6 -> 0.075 | N57: Marge Superdoos | O57: =$C$57 -> 0.3 | P57: =IF(R57<$C$69, S57, Q57) -> 0.29004525 | Q57: =SUM(P49:P54)*O57 -> 0.29004525 | R57: =Q57*O6 -> 522.08145 | S57: =$C$69/O6 -> 0.016666667 | X57: Marge Superdoos | Y57: =$C$57 -> 0.3 | Z57: =IF(AB57<$C$69, AC57, AA57) -> 0.29004525 | AA57: =SUM(Z49:Z54)*Y57 -> 0.29004525 | AB57: =AA57*Y6 -> 522.08145 | AC57: =$C$69/Y6 -> 0.016666667 | AH57: Marge Superdoos | AI57: =$C$57 -> 0.3 | AJ57: =IF(AL57<$C$69, AM57, AK57) -> 0.34829444 | AK57: =SUM(AJ49:AJ54)*AI57 -> 0.34829444 | AL57: =AK57*AI6 -> 170.66427 | AM57: =$C$69/AI6 -> 0.06122449
B58: Onbedrukt | D58: =IF(Input!$B$11="onbedrukt",1,0) -> 1 | N58: Onbedrukt | P58: =IF(Input!$B$11="onbedrukt",1,0) -> 1 | X58: Onbedrukt | Z58: =IF(Input!$B$11="onbedrukt",1,0) -> 1 | AH58: Onbedrukt | AJ58: =IF(Input!$B$11="onbedrukt",1,0) -> 1
B59: Verkoop | D59: =D55+D57 -> 1.5720859 | N59: Verkoop | P59: =P55+P57 -> 1.2568627 | X59: Verkoop | Z59: =Z55+Z57 -> 1.2568627 | AH59: Verkoop | AJ59: =AJ55+AJ57 -> 1.5092759
A62: Variabelen
B63: Transport per m2 | C63: 50
B64: Machine uur tarief | C64: 65
B65: Uitbreken per stuk | C65: 0.1
B66: Order kosten | C66: 0
B67: Lijmen tapen per mm | C67: =0.26/1000 -> 0.00026
B68: Pakketpost | C68: 40
B69: Marge bedrag minimaal | C69: 30
B71: Snelheidtabel | C71: m2 | D71: rillen | E71: snijden
B72: Tarief klein | C72: 0 | D72: 700 | E72: 300
B73: Tarief middel | C73: 1.2 | D73: 875 | E73: 425
B74: Tarief groot | C74: 1.8 | D74: 1000 | E74: 500
B77: Tapen vaste kosten
B78: 1 | C78: 25
B79: 3 | C79: 8
B80: 10 | C80: 2.5
B81: 20 | C81: 1.5
B82: 50 | C82: 0.8
B83: 60 | C83: 0.75
B84: 70 | C84: 0.65
B85: 80 | C85: 0.6
B86: 90 | C86: 0.5
B87: 100 | C87: 0.45
B88: 150 | C88: 0.4
B89: 200 | C89: 0.32
... B92: 100000 | C92: 0.26
B99: Kwaliteit | C99: Golf | D99: Dikte | E99: Prijs per m2
A100: ET12 | B100: 10095 | C100: E | D100: 1.5 | E100: =VLOOKUP(A100,('Prijs karton'!C:G),5,0)/100*1.08 -> 0.28728
A101: ET13/12 | B101: 10097 | C101: E | D101: 1.5 | E101: =VLOOKUP(A101,('Prijs karton'!C:G),5,0)/100*1.08 -> 0.33912
A102: EK13 | B102: 10134 | C102: E | D102: 1.5 | E102: =VLOOKUP(A102,('Prijs karton'!C:G),5,0)/100*1.08 -> 0.47304
A103: ETWT14 | B103: 10099 | C103: E | D103: 1.5 | E103: =VLOOKUP(A103,('Prijs karton'!C:G),5,0)/100*1.08 -> 0.36612
A104: ETWT14 W2 | B104: 10131 | C104: E | D104: 1.5 | E104: =VLOOKUP(A104,('Prijs karton'!C:G),5,0)/100*1.08 -> 0.37908
A105: BT13 | B105: 10326 | C105: B | D105: 3 | E105: =VLOOKUP(A105,('Prijs karton'!C:G),5,0)/100*1.08 -> 0.36612
A106: BKT14 | B106: 10005 | C106: B | D106: 3 | E106: =VLOOKUP(A106,('Prijs karton'!C:G),5,0)/100*1.08 -> 0.42552
A107: BKT19 | B107: 10017 | C107: B | D107: 3 | E107: =VLOOKUP(A107,('Prijs karton'!C:G),5,0)/100*1.08 -> 0.567
A108: BDUWT14 | B108: 10002 | C108: B | D108: 3 | E108: =VLOOKUP(A108,('Prijs karton'!C:G),5,0)/100*1.08 -> 0.42444
A109: BKT14WS | B109: 10010 | C109: B | D109: 3 | E109: =VLOOKUP(A109,('Prijs karton'!C:G),5,0)/100*1.08 -> 0.50976
A110: CT14 | B110: 10053 | C110: C | D110: 4 | E110: =VLOOKUP(A110,('Prijs karton'!C:G),5,0)/100*1.08 -> 0.36072
A111: CKT15 W6 | B111: 10193 | C111: C | D111: 4 | E111: =VLOOKUP(A111,('Prijs karton'!C:G),5,0)/100*1.08 -> 0.5076
... A130: AACKK40/40 | B130: 10220 | C130: AAC | D130: 9 | E130: =VLOOKUP(A130,('Prijs karton'!C:G),5,0)/100*1.08 -> 2.32956
C135: Lijmen/Tapen | D135: Snijmeters | G135: Rilmeters
B136: FEFCO | D136: Lengte | E136: Breedte | F136: Hoogte | G136: Lengte | H136: Breedte | I136: Hoogte | J136: Stansdoos | K136: Marge
B137: 0427 | C137: Nee | D137: 2 | E137: 8 | F137: 20 | G137: 4 | H137: 8 | I137: 6 | J137: 1 | K137: 0.3
B138: 0409 | C138: Nee | D138: 2 | E138: 4 | F138: 26 | G138: 4 | H138: 4 | I138: 6 | J138: 0 | K138: 0.3
B139: 0200 | C139: Ja | D139: 4 | E139: 8 | F139: 2 | G139: 2 | H139: 2 | I139: 4 | J139: 0 | K139: 0.3
B140: 0452 | C140: Nee | D140: 2 | E140: 2 | F140: 16 | G140: 2 | H140: 2 | I140: 4 | J140: 0 | K140: 0.3
B141: 0422 | C141: Nee | D141: 2 | E141: 2 | F141: 28 | G141: 2 | H141: 6 | I141: 4 | J141: 1 | K141: 0.3
B142: 0201 | C142: Ja | D142: 4 | E142: 12 | F142: 2 | G142: 4 | H142: 4 | I142: 4 | J142: 0 | K142: 0.3
B143: 0203 | C143: Ja | D143: 4 | E143: 20 | F143: 2 | G143: 4 | H143: 4 | I143: 4 | J143: 0 | K143: 0.3
B144: 0110 | C144: Nee | D144: 2 | E144: 2 | F144: 0 | G144: 0 | H144: 0 | I144: 0 | J144: 0 | K144: 0.3
B145: 0401 | C145: Nee | D145: 2 | E145: 6 | F145: 8 | G145: 4 | H145: 4 | I145: 0 | J145: 0 | K145: 0.3
B146: 0421 | C146: Nee | D146: 3 | E146: 5 | F146: 17 | G146: 4 | H146: 6 | I146: 4 | J146: 1 | K146: 0.3
B147: 0471 | C147: Nee | D147: 3 | E147: 13 | F147: 10 | G147: 4 | H147: 6 | I147: 6 | J147: 1 | K147: 0.3
...

Sheet Input
A2: Kwaliteitscode | B2: =BLO!B6 -> 10010 | I2: To do:
A3: Golf | B3: ='Kwaliteit conversie'!B4 -> B | I3: Palletaantallen alsof het een Emba doos is. Check of het een Emba doos is.
A4: Kwaliteit | B4: ='Kwaliteit conversie'!C4 -> Wit extra sterk | I4: Kleine stansdozen gaan snel naar 2 uit een plaat. Verschil met verkoopprijsmodel in berekening.
A6: Fefco | B6: =BLO!B2 -> 0201
A7: Lengte | B7: =BLO!B3 -> 300 | C7: mm
A8: Breedte | B8: =BLO!B4 -> 250 | C8: mm
A9: Hoogte | B9: =BLO!B5 -> 100 | C9: mm
A11: Aantal kleuren | B11: =BLO!B12 -> onbedrukt
A12: Bedrukkingspercentage | B12: Onbedrukt / minder dan 10%
A13: Handgrepen | B13: =BLO!B8 -> geen handgrepen / stansbewerking
A14: Extra rillen | B14: Nee
A15: Pallethoogte (max. 2100 mm), niet verplicht vullen. | C15: mm
A17: Aantal | B17: =BLO!B9 -> 400 | C17: Stuks | I17: Alleen voor prijsvergelijking, niet gebruiken (wordt later weer verwijderd):
I18: Materiaal | L18: =Rekenblad!E1081 -> 0.24320434
I19: Totale productiekosten | L19: =Rekenblad!E1083 -> 0.175 | M19: =L19+L20 -> 0.185 | N19: Totaal productie
I20: Overige kosten (inkt/ tape/pallets) | L20: =Rekenblad!E1082 -> 0.01
A21: Minimale afname | C21: =IF(Rekenblad!I445=0," ",CEILING(Rekenblad!I445,10)) -> 490 | D21: Stuks | I21: Orderkosten | L21: =Rekenblad!E1084 -> 0.05
I22: Transport | L22: =Rekenblad!E1091 -> 0.18830213
A23: Prijs per stuk, bij afname | B23: =Rekenblad!C1094 -> 0.72166405 | C23: =B17 -> 400 | D23: stuks
I24: Totaal marge (marge + variatie inkoop) | L24: =Rekenblad!E1089 -> 0.055157585
I26: Kosten per verpakking | L26: =Rekenblad!E1093 -> 0.72166405
A27: Palletstapeling indicatief:
A28: Formaat colli | B28: =IF(Rekenblad!AV46=1,'Pallet en transport'!D151& " x "&'Pallet en transport'!E151," ") -> 1083 x 1200 | C28: mm
A29: Aantal per bundel | B29: =IF(Rekenblad!AV46=1,IF('Pallet en transport'!D165=0,0,'Pallet en transport'!D166)," ") -> 25 | C29: stuks
A30: Aantal stapels per colli | B30: =IF(Rekenblad!AV46=1,'Pallet en transport'!D170," ") -> 6 | C30: stuks | I30: Hoofdbewerking gekozen:
A31: Aantal per colli | B31: =IF(Rekenblad!AV46=1,'Pallet en transport'!D171," ") -> 1800 | C31: stuks | I31: =Rekenblad!C362 -> 0 | J31: =Rekenblad!D362 -> 0 | K31: =Rekenblad!E362 -> 1 | L31: =Rekenblad!F362 -> 0 | M31: =Rekenblad!G362 -> 0 | N31: =Rekenblad!H362 -> 0 | O31: =Rekenblad!I362 -> 0
A32: Hoogte bij benadering | B32: =IF(Rekenblad!AV46=1,'Pallet en transport'!D160," ") -> 1950 | C32: mm | I32: Mini | J32: Maxi | K32: Emba 170 | L32: Emba 295 | M32: Vlakstans | N32: Roda | O32: Plaat op maat
A33: Aantal colli | B33: =IF(Rekenblad!AV46=1,'Pallet en transport'!D174," ") -> 1 | C33: stuks

Sheet Rekenblad
B2: Fefco geselecteerd | C2: =Input!B6 -> 0201
B3: Aantal | C3: =Input!B17 -> 400
B4: Golfsoort | C4: ='Kwaliteit conversie'!B4 -> B
B6: Lengte | C6: =Input!B7 -> 300
B7: breedte | C7: =Input!B8 -> 250
B8: hoogte | C8: =Input!B9 -> 100
B9: Formaat mogelijk | C9: =IF(SUM(D1072:D1074)=3,1,0) -> 1
B10: L >= B akkoord | C10: =IF(AND(E1071=1,C6>=C7),1,IF(E1071=0,1,0)) -> 1
B12: Toeslag materiaal | C12: =E145 -> 2
B13: Dikte | C13: =F145 -> 3
B14: Bedrukking | C14: =Input!B11 -> onbedrukt
B15: Percentage bedrukking | C15: =Input!B12 -> Onbedrukt / minder dan 10%
B16: Stansbewerking | C16: =Input!B13 -> geen handgrepen / stansbewerking
B17: Pallethoogte | C17: =IF(AND(Input!B15>0,Input!B15<2100),Input!B15,2100) -> 2100 | D17: mm
B19: Minimale breedte F02.. op basis van lengte:
B20: =IF(AND($C$6>B21,$C$6<=B22),1,0) -> 0 | C20: =IF(AND($C$6>C21,$C$6<=C22),1,0) -> 0 | D20: =IF(AND($C$6>D21,$C$6<=D22),1,0) -> 1 | E20: =IF(AND($C$6>E21,$C$6<=E22),1,0) -> 0 | F20: =IF(AND($C$6>F21,$C$6<=F22),1,0) -> 0 | G20: =IF(AND($C$6>G21,$C$6<=G22),1,0) -> 0 | H20: =IF(AND($C$6>H21,$C$6<=H22),1,0) -> 0 | I20: =IF(AND($C$6>I21,$C$6<=I22),1,0) -> 0 | ... L20: =IF(AND($C$6>L21,$C$6<=L22),1,0) -> 0
B21: 0 | C21: 200 | D21: 250 | E21: 300 | F21: 350 | G21: 400 | H21: 500 | I21: 600 | J21: 750 | K21: 1000 | L21: 1250
B22: 200 | C22: 250 | D22: 300 | E22: 350 | F22: 400 | G22: 500 | H22: 600 | I22: 750 | J22: 1000 | K22: 1250 | L22: 99999
A23: Stotende klep | B23: 60 | C23: 65 | D23: 70 | E23: 75 | F23: 80 | G23: 85 | H23: 90 | I23: 95 | J23: 100 | K23: 105 | L23: 110 | M23: =HLOOKUP(1,B20:L24,4,FALSE) -> 70
A24: Overslaande klep | B24: 40 | C24: 40 | D24: 40 | E24: 40 | F24: 40 | G24: 40 | H24: 40 | I24: 40 | J24: 50 | K24: 50 | L24: 60 | M24: =HLOOKUP(1,B20:L24,5,FALSE) -> 40
B26: Lengte / hoogte verhouding:
C27: Lengte tussen | E27: Hoogte minimaal
B28: =IF(AND($C$6>C28,$C$6<=D28),1,0) -> 1 | C28: 0 | D28: 400 | E28: 37
B29: =IF(AND($C$6>C29,$C$6<=D29),1,0) -> 0 | C29: 400 | D29: 450 | E29: 40
B30: =IF(AND($C$6>C30,$C$6<=D30),1,0) -> 0 | C30: 450 | D30: 500 | E30: 43
B31: =IF(AND($C$6>C31,$C$6<=D31),1,0) -> 0 | C31: 500 | D31: 550 | E31: 47
B32: =IF(AND($C$6>C32,$C$6<=D32),1,0) -> 0 | C32: 550 | D32: 600 | E32: 50
B33: =IF(AND($C$6>C33,$C$6<=D33),1,0) -> 0 | C33: 600 | D33: 650 | E33: 54
B34: =IF(AND($C$6>C34,$C$6<=D34),1,0) -> 0 | C34: 650 | D34: 700 | E34: 57
B35: =IF(AND($C$6>C35,$C$6<=D35),1,0) -> 0 | C35: 700 | D35: 850 | E35: 60
B36: =IF(AND($C$6>C36,$C$6<=D36),1,0) -> 0 | C36: 850 | D36: 1000 | E36: 70
B37: =IF(AND($C$6>C37,$C$6<=D37),1,0) -> 0 | C37: 1000 | D37: 1200 | E37: 80
B38: =IF(AND($C$6>C38,$C$6<=D38),1,0) -> 0 | C38: 1200 | D38: 2000 | E38: 95
B39: =IF(AND($C$6>C39,$C$6<=D39),1,0) -> 0 | C39: 2000 | D39: 9999 | E39: 110
B41: Minimale hoogte | E41: =VLOOKUP(1,B28:E39,4,FALSE) -> 37
AG44: Beveiliging | AO44: Beveiliging
B45: 2 | C45: 3 | D45: 4 | E45: 5 | F45: 6 | G45: 7 | H45: 8 | I45: 9 | J45: 10 | K45: 11 | L45: 12 | M45: 13 | N45: 14 | O45: 15 | P45: 16 | Q45: 17 | R45: 18 | S45: 19 | T45: 20 | U45: 21 | V45: 22 | W45: 23 | X45: 24 | Y45: 25 | Z45: 26 | AA45: 27 | AB45: 28 | AC45: 29 | AD45: 30 | AE45: 31 | AF45: 32 | AG45: 33 | AH45: 34 | AI45: 35 | AJ45: 36 | AK45: 37 | AL45: 38 | AM45: 39 | AN45: 40 | AO45: 41 | AP45: 42 | AQ45: 43 | AR45: 44 | AS45: 45 | AT45: 46 | AU45: 47 | AV45: 48 | AW45: 49 | AX45: 50 | AY45: 51 | AZ45: 52
C46: =C6 -> 300 | D46: =C7 -> 250 | E46: =C8 -> 100 | F46: =C13 -> 3 | I46: =C12 -> 2 | K46: =C6 -> 300 | L46: =C7 -> 250 | M46: =C8 -> 100 | N46: =C13 -> 3 | Q46: =C12 -> 2 | T46: =VLOOKUP(1,50:70,T45,FALSE) -> 1 | U46: =VLOOKUP(1,50:70,U45,FALSE) -> 1 | V46: =VLOOKUP(1,50:70,V45,FALSE) -> 0 | W46: =VLOOKUP(1,50:70,W45,FALSE) -> 0 | X46: =VLOOKUP(1,50:70,X45,FALSE) -> 0 | AA46: =VLOOKUP(1,50:70,AA45,FALSE) -> 1 | AB46: =VLOOKUP(1,50:70,AB45,FALSE) -> 1 | AC46: =VLOOKUP(1,50:70,AC45,FALSE) -> 0 | AD46: =VLOOKUP(1,50:70,AD45,FALSE) -> 127 | AE46: =VLOOKUP(1,50:70,AE45,FALSE) -> 127 | AF46: =VLOOKUP(1,50:70,AF45,FALSE) -> 107 | AG46: =VLOOKUP(1,50:70,AG45,FALSE) -> 100 | AH46: =VLOOKUP(1,50:70,AH45,FALSE) -> 2000 | ... AZ46: =VLOOKUP(1,50:70,AZ45,FALSE) -> 1
C47: Breedte plaat | K47: Lengte plaat | S47: Bewerkingen | T47: Machinegroep mogelijk | AA47: Sluiting | AB47: Lijmlip | AC47: Zijafval mini | AD47: Slitmaten | AF47: Ongeslit Emba | AG47: Lengte | AI47: Breedte | AK47: Hoogte | AM47: Lengte > Breedte | AN47: Max. boven elkaar | AO47: H < L | AP47: L > 2xB | AQ47: Handgreep | AR47: Stapel/bundel | AS47: Factoren | AT47: Stanssuport | AU47: Extra marge | AX47: H min 10% van L
B48: Fefco | C48: Lengte | D48: Breedte | E48: Hoogte | F48: Wanddikte | G48: Extra | H48: Extra waarde | I48: Toeslag | J48: Totaal (golfrichting) | K48: Lengte | L48: Breedte | M48: Hoogte | N48: Wanddikte | O48: Extra | P48: Extra waarde | Q48: Toeslag | R48: Totaal (lengte) | T48: Boxmaker | U48: Emba | V48: Stans | W48: Roda | X48: Plaat op maat | Y48: m2 / st | Z48: m2 tot | AA48: Nodig | AB48: Nodig | AC48: Nodig | AD48: Onder | AE48: Boven | AG48: minimaal | AH48: maximaal | AI48: Minimaal | AJ48: Maximaal | AK48: Minimaal | AL48: Maximaal | AM48: verplicht | AN48: Mini | AQ48: Mogelijk | AR48: Berekenen | AS48: Emba | AT48: Boxmaker | AU48: Fefco | AV48: Pallet berekenen | AW48: Afval boxm / product | AY48: Efficientie/ fefco | AZ48: Bedrukking mogelijk
A50: =IF($C$2=B50,1," ") | B50: 0110 | C50: 1 | J50: =(C50*$C$46)+(D50*$D$46)+(E50*$E$46)+(F50*$F$46)+(I50*$I$46)+(G50*H50) -> 300 | L50: 1 | R50: =(K50*$K$46)+(L50*$L$46)+(M50*$M$46)+(N50*$N$46)+(Q50*$Q$46)+(O50*P50) -> 250 | S50: 1 | T50: 1 | U50: 1 | W50: 1 | X50: 1 | Y50: =(J50/1000)*(R50/1000) -> 0.075 | Z50: =Y50*$C$3 -> 30 | AA50: 0 | AB50: 0 | AC50: 0 | AG50: 65 | AH50: 2000 | AI50: 65 | AJ50: 5000 | AK50: 0 | AL50: 0 | AM50: 0 | AN50: 4 | AO50: 0 | AP50: 0 | AQ50: 0 | AR50: 0 | AS50: 0 | AT50: 0 | AU50: 0 | AV50: 1 | AW50: 0,2 | AX50: 0 | AY50: 0.9 | AZ50: 0 | BD50: 0110
A51: =IF($C$2=B51,1," ") | B51: 0200 | D51: 0.5 | E51: 1 | F51: 1 | I51: 2 | J51: =(C51*$C$46)+(D51*$D$46)+(E51*$E$46)+(F51*$F$46)+(I51*$I$46)+(G51*H51) -> 232 | K51: 2 | L51: 2 | Q51: 7 | R51: =(K51*$K$46)+(L51*$L$46)+(M51*$M$46)+(N51*$N$46)+(Q51*$Q$46)+(O51*P51) -> 1114 | S51: 3 | T51: 1 | U51: 1 | Y51: =(J51/1000)*(R51/1000) -> 0.258448 | Z51: =Y51*$C$3 -> 103.3792 | AA51: 1 | AB51: 1 | AC51: 0 | AD51: =(0.5*D46)+I46 -> 127 | AE51: 0 | AF51: =J51-AD51-AE51 -> 105 | AG51: 100 | AH51: 2000 | AI51: =M23 -> 70 | AJ51: 1000 | AK51: =E41 -> 37 | AL51: 1200 | AM51: 1 | AN51: 4 | AO51: 0 | AP51: 0 | AQ51: 1 | AR51: 1 | AS51: 1 | AT51: 0 | AU51: 0 | AV51: 1 | AW51: 0,2 | AX51: 1 | AY51: 0.9 | AZ51: 1 | BD51: 0200
A52: =IF($C$2=B52,1," ") -> 1 | B52: 0201 | D52: 1 | E52: 1 | F52: 1 | I52: 4 | J52: =(C52*$C$46)+(D52*$D$46)+(E52*$E$46)+(F52*$F$46)+(I52*$I$46)+(G52*H52) -> 361 | K52: 2 | L52: 2 | Q52: 7 | R52: =(K52*$K$46)+(L52*$L$46)+(M52*$M$46)+(N52*$N$46)+(Q52*$Q$46)+(O52*P52) -> 1114 | S52: 3 | T52: 1 | U52: 1 | Y52: =(J52/1000)*(R52/1000) -> 0.402154 | Z52: =Y52*$C$3 -> 160.8616 | AA52: 1 | AB52: 1 | AC52: 0 | AD52: =(0.5*D46)+I46 -> 127 | AE52: =(0.5*D46)+I46 -> 127 | AF52: =J52-AD52-AE52 -> 107 | AG52: 100 | AH52: 2000 | AI52: =M23 -> 70 | AJ52: 1000 | AK52: =E41 -> 37 | AL52: 1200 | AM52: 1 | AN52: 4 | AO52: 0 | AP52: 0 | AQ52: 1 | AR52: 1 | AS52: 1 | AT52: 0 | AU52: 0 | AV52: 1 | AW52: 0,2 | AX52: 1 | AY52: 0.9 | AZ52: 1 | BD52: 0201
A53: =IF($C$2=B53,1," ") | B53: 0203 | D53: 2 | E53: 1 | F53: 2 | I53: 4 | J53: =(C53*$C$46)+(D53*$D$46)+(E53*$E$46)+(F53*$F$46)+(I53*$I$46)+(G53*H53) -> 614 | K53: 2 | L53: 2 | Q53: 7 | R53: =(K53*$K$46)+(L53*$L$46)+(M53*$M$46)+(N53*$N$46)+(Q53*$Q$46)+(O53*P53) -> 1114 | S53: 3 | T53: 1 | U53: 1 | Y53: =(J53/1000)*(R53/1000) -> 0.683996 | Z53: =Y53*$C$3 -> 273.5984 | AA53: 1 | AB53: 1 | AC53: 0 | AD53: =D46+I46 -> 252 | AE53: =D46+I46 -> 252 | AF53: =J53-AD53-AE53 -> 110 | AG53: 100 | AH53: 2000 | AI53: =M24 -> 40 | AJ53: 1000 | AK53: =E41 -> 37 | AL53: 1200 | AM53: 1 | AN53: 4 | AO53: 0 | AP53: 1 | AQ53: 1 | AR53: 1 | AS53: 1 | AT53: 0 | AU53: 0 | AV53: 1 | AW53: 0,2 | AX53: 1 | AY53: 0.9 | AZ53: 1 | BD53: 0203
A54: =IF($C$2=B54,1," ") | B54: 0409 | C54: 1 | E54: 2 | F54: 2 | I54: 4 | J54: =(C54*$C$46)+(D54*$D$46)+(E54*$E$46)+(F54*$F$46)+(I54*$I$46)+(G54*H54) -> 514 | L54: 2 | M54: 3 | N54: 1 | Q54: 8 | R54: =(K54*$K$46)+(L54*$L$46)+(M54*$M$46)+(N54*$N$46)+(Q54*$Q$46)+(O54*P54) -> 819 | S54: 4 | T54: 1 | Y54: =(J54/1000)*(R54/1000) -> 0.420966 | Z54: =Y54*$C$3 -> 168.3864 | AA54: 0 | AB54: 0 | AC54: 0 | AD54: =E46+I46 -> 102 | AE54: =E46+I46 -> 102 | AG54: 200 | AH54: 2000 | AI54: 100 | AJ54: 1200 | AK54: 40 | AL54: 200 | AM54: 1 | AN54: 4 | AO54: 0 | AP54: 0 | AQ54: 0 | AR54: 0 | AS54: 0 | AT54: 0 | AU54: 0 | AV54: 1 | AW54: 0,2 | AX54: 0 | AY54: 0.9 | AZ54: 0 | BD54: 0409
A55: =IF($C$2=B55,1," ") | B55: 0410 | C55: 1 | E55: 2 | F55: 2 | I55: 4 | J55: =(C55*$C$46)+(D55*$D$46)+(E55*$E$46)+(F55*$F$46)+(I55*$I$46)+(G55*H55) -> 514 | L55: 2 | M55: 3 | N55: 1 | Q55: 8 | R55: =(K55*$K$46)+(L55*$L$46)+(M55*$M$46)+(N55*$N$46)+(Q55*$Q$46)+(O55*P55) -> 819 | S55: 4 | T55: 1 | Y55: =(J55/1000)*(R55/1000) -> 0.420966 | Z55: =Y55*$C$3 -> 168.3864 | AA55: 0 | AB55: 0 | AC55: 0 | AD55: =E46+I46 -> 102 | AE55: =E46+I46 -> 102 | AG55: 200 | AH55: 2000 | AI55: 100 | AJ55: 1200 | AK55: 40 | AL55: 200 | AM55: 1 | AN55: 4 | AO55: 0 | AP55: 0 | AQ55: 0 | AR55: 0 | AS55: 0 | AT55: =C8+C12 -> 102 | AU55: 0.04 | AV55: 1 | AW55: 0,5 | AX55: 0 | AY55: 0.85 | AZ55: 0 | BD55: 0410
A56: =IF($C$2=B56,1," ") | B56: 0412 | D56: 3 | E56: 2 | F56: 4 | I56: 8 | J56: =(C56*$C$46)+(D56*$D$46)+(E56*$E$46)+(F56*$F$46)+(I56*$I$46)+(G56*H56) -> 978 | K56: 1 | M56: 2 | O56: 2 | P56: 50 | Q56: 8 | R56: =(K56*$K$46)+(L56*$L$46)+(M56*$M$46)+(N56*$N$46)+(Q56*$Q$46)+(O56*P56) -> 616 | S56: 4 | T56: 1 | Y56: =(J56/1000)*(R56/1000) -> 0.602448 | Z56: =Y56*$C$3 -> 240.9792 | AA56: 0 | AB56: 0 | AC56: 1 | AG56: 300 | AH56: 2000 | AI56: 100 | AJ56: 500 | AK56: 80 | AL56: 200 | AM56: 1 | AN56: 2 | AO56: 0 | AP56: 0 | AQ56: 0 | AR56: 0 | AS56: 0 | AT56: =(P56+C12) -> 52 | AU56: 0.04 | AV56: 1 | AW56: 0,4 | AX56: 0 | AY56: 0.82 | AZ56: 0 | BD56: 0412
A57: =IF($C$2=B57,1," ") | B57: 0427 | C57: 1 | E57: 4 | F57: 12 | I57: 12 | J57: =(C57*$C$46)+(D57*$D$46)+(E57*$E$46)+(F57*$F$46)+(I57*$I$46)+(G57*H57) -> 760 | L57: 2 | M57: 3 | N57: 1 | Q57: 8 | R57: =(K57*$K$46)+(L57*$L$46)+(M57*$M$46)+(N57*$N$46)+(Q57*$Q$46)+(O57*P57) -> 819 | V57: 0 | Y57: =(J57/1000)*(R57/1000) -> 0.62244 | Z57: =Y57*$C$3 -> 248.976 | AA57: 0 | AB57: 0 | AC57: 0 | AG57: 80 | AH57: 1400 | AI57: 50 | AJ57: 550 | AK57: 23 | AL57: 200 | AM57: 0 | AN57: 0 | AO57: 1 | AP57: 0 | AQ57: 0 | AR57: 0 | AS57: 0 | AT57: 0 | AU57: 0.02 | AV57: 1 | AW57: 0 | AX57: 0 | AY57: 0.9 | BD57: 0427
A58: =IF($C$2=B58,1," ") | B58: 0421 | C58: 1 | E58: 4 | F58: 8 | I58: 12 | J58: =(C58*$C$46)+(D58*$D$46)+(E58*$E$46)+(F58*$F$46)+(I58*$I$46)+(G58*H58) -> 748 | L58: 2 | M58: 2 | N58: 1 | O58: 1 | P58: 30 | Q58: 4 | R58: =(K58*$K$46)+(L58*$L$46)+(M58*$M$46)+(N58*$N$46)+(Q58*$Q$46)+(O58*P58) -> 741 | V58: 0 | Y58: =(J58/1000)*(R58/1000) -> 0.554268 | Z58: =Y58*$C$3 -> 221.7072 | AA58: 0 | AB58: 0 | AC58: 0 | AG58: 80 | AH58: 1400 | AI58: 50 | AJ58: 550 | AK58: 23 | AL58: 200 | AM58: 0 | AN58: 0 | AO58: 1 | AP58: 0 | AQ58: 0 | AR58: 0 | AS58: 0 | AT58: 0 | AU58: 0.02 | AV58: 1 | AW58: 0 | AX58: 0 | AY58: 0.9 | BD58: 0421
A59: =IF($C$2=B59,1," ") | B59: 0422 | C59: 1 | E59: 4 | F59: 8 | I59: 12 | J59: =(C59*$C$46)+(D59*$D$46)+(E59*$E$46)+(F59*$F$46)+(I59*$I$46)+(G59*H59) -> 748 | L59: 1 | M59: 2 | Q59: 4 | R59: =(K59*$K$46)+(L59*$L$46)+(M59*$M$46)+(N59*$N$46)+(Q59*$Q$46)+(O59*P59) -> 458 | V59: 0 | Y59: =(J59/1000)*(R59/1000) -> 0.342584 | Z59: =Y59*$C$3 -> 137.0336 | AA59: 0 | AB59: 0 | AC59: 0 | AG59: 100 | AH59: 1400 | AI59: 50 | AJ59: 800 | AK59: 30 | AL59: 200 | AM59: 0 | AN59: 0 | AO59: 1 | AP59: 0 | AQ59: 0 | AR59: 0 | AS59: 0 | AT59: 0 | AU59: 0.02 | AV59: 1 | AW59: 0 | AX59: 0 | AY59: 0.9 | BD59: 0422
A60: =IF($C$2=B60,1," ") | B60: 0452 | D60: 1 | E60: 2 | F60: 2 | I60: 4 | J60: =(C60*$C$46)+(D60*$D$46)+(E60*$E$46)+(F60*$F$46)+(I60*$I$46)+(G60*H60) -> 464 | K60: 1 | M60: 2 | Q60: 4 | R60: =(K60*$K$46)+(L60*$L$46)+(M60*$M$46)+(N60*$N$46)+(Q60*$Q$46)+(O60*P60) -> 508 | S60: 2 | T60: 1 | Y60: =(J60/1000)*(R60/1000) -> 0.235712 | Z60: =Y60*$C$3 -> 94.2848 | AA60: 0 | AB60: 0 | AC60: 0 | AD60: =E46+I46 -> 102 | AE60: =E46+I46 -> 102 | AG60: 150 | AH60: 2000 | AI60: 100 | AJ60: 1200 | AK60: 45 | AL60: 400 | AM60: 1 | AN60: 4 | AO60: 0 | AP60: 0 | AQ60: 0 | AR60: 0 | AS60: 0 | AT60: 0 | AU60: 0 | AV60: 1 | AW60: 0,2 | AX60: 0 | AY60: 0.9 | BD60: 0452
A61: =IF($C$2=B61,1," ") | B61: 0501 | E61: 1 | I61: 0 | J61: =(C61*$C$46)+(D61*$D$46)+(E61*$E$46)+(F61*$F$46)+(I61*$I$46)+(G61*H61) -> 100 | K61: 2 | L61: 2 | Q61: 7 | R61: =(K61*$K$46)+(L61*$L$46)+(M61*$M$46)+(N61*$N$46)+(Q61*$Q$46)+(O61*P61) -> 1114 | S61: 4 | T61: 1 | U61: 1 | Y61: =(J61/1000)*(R61/1000) -> 0.1114 | Z61: =Y61*$C$3 -> 44.56 | AA61: 1 | AB61: 1 | AC61: 0 | AG61: 100 | AH61: 2000 | AI61: =M24 -> 40 | AJ61: 1000 | AK61: 100 | AL61: 1200 | AM61: 1 | AN61: 4 | AO61: 0 | AP61: 0 | AQ61: 1 | AR61: 1 | AS61: 1 | AT61: 0 | AU61: 0 | AV61: 1 | AW61: 0 | AX61: 1 | AY61: 0.9 | AZ61: 1 | BD61: 0501
A62: =IF($C$2=B62,1," ") | B62: 0401 | D62: 2 | E62: 2 | F62: 2 | I62: 8 | J62: =(C62*$C$46)+(D62*$D$46)+(E62*$E$46)+(F62*$F$46)+(I62*$I$46)+(G62*H62) -> 722 | K62: 1 | M62: 2 | O62: 2 | P62: 50 | Q62: 8 | R62: =(K62*$K$46)+(L62*$L$46)+(M62*$M$46)+(N62*$N$46)+(Q62*$Q$46)+(O62*P62) -> 616 | S62: 4 | T62: 1 | Y62: =(J62/1000)*(R62/1000) -> 0.444752 | Z62: =Y62*$C$3 -> 177.9008 | AA62: 0 | AB62: 0 | AC62: 1 | AD62: =(0.5*D46)+E46+(3*I46)+F46 -> 234 | AE62: =(0.5*D46)+E46+(3*I46)+F46 -> 234 | AG62: 200 | AH62: 2000 | AI62: 100 | AJ62: 800 | AK62: 20 | AL62: 80 | AM62: 1 | AN62: =IF(J62+C166>=I183,1,2) -> 1 | AO62: 0 | AP62: 0 | AQ62: 0 | AR62: 0 | AS62: 0 | AT62: =(P62+(C12*3)+C8) -> 156 | AU62: 0.04 | AV62: 1 | AW62: 2 | AX62: 0 | AY62: 0.82 | BD62: 0401
A63: =IF($C$2=B63,1," ") | B63: 0471 | D63: 2 | E63: 3 | F63: 2 | I63: 8 | J63: =(C63*$C$46)+(D63*$D$46)+(E63*$E$46)+(F63*$F$46)+(I63*$I$46)+(G63*H63) -> 822 | K63: 1 | L63: 2 | N63: 6 | Q63: 4 | R63: =(K63*$K$46)+(L63*$L$46)+(M63*$M$46)+(N63*$N$46)+(Q63*$Q$46)+(O63*P63) -> 826 | V63: 0 | Y63: =(J63/1000)*(R63/1000) -> 0.678972 | Z63: =Y63*$C$3 -> 271.5888 | AA63: 0 | AB63: 0 | AC63: 0 | AG63: 180 | AH63: 1400 | AI63: 80 | AJ63: 600 | AK63: 60 | AL63: 400 | AM63: 1 | AN63: 0 | AO63: 1 | AP63: 0 | AQ63: 0 | AR63: 0 | AS63: 0 | AT63: 0 | AU63: 0.02 | AV63: 1 | AW63: 0 | AX63: 0 | AY63: 0.9 | BD63: 0471
A64: =IF($C$2=B64,1," ") | B64: 0933 | C64: 1 | D64: 1 | E64: 1 | F64: 1 | J64: =(C64*$C$46)+(D64*$D$46)+(E64*$E$46)+(F64*$F$46)+(I64*$I$46)+(G64*H64) -> 653 | K64: 1 | L64: 1 | M64: 1 | N64: 1 | O64: 1 | R64: =(K64*$K$46)+(L64*$L$46)+(M64*$M$46)+(N64*$N$46)+(Q64*$Q$46)+(O64*P64) -> 653 | T64: 0 | U64: 0 | V64: 0 | W64: 0 | X64: 0 | Y64: =(J64/1000)*(R64/1000) -> 0.426409 | Z64: =Y64*$C$3 -> 170.5636 | AA64: 0 | AB64: 0 | AC64: 0 | AG64: 99 | AH64: 9999 | AI64: 99 | AJ64: 9999 | AK64: 99 | AL64: 9999 | AM64: 0 | AN64: 0 | AO64: 0 | AP64: 0 | AQ64: 0 | AR64: 0 | AS64: 0 | AT64: 0 | AU64: 0 | AV64: 0 | AW64: 0 | AX64: 0 | AY64: 0.9 | BA64: Wordt niet berekend | BD64: 0933
A65: =IF($C$2=B65,1," ") | B65: 0701 | C65: 1 | D65: 1 | E65: 1 | F65: 1 | J65: =(C65*$C$46)+(D65*$D$46)+(E65*$E$46)+(F65*$F$46)+(I65*$I$46)+(G65*H65) -> 653 | K65: 1 | L65: 1 | M65: 1 | N65: 1 | O65: 1 | R65: =(K65*$K$46)+(L65*$L$46)+(M65*$M$46)+(N65*$N$46)+(Q65*$Q$46)+(O65*P65) -> 653 | T65: 0 | U65: 0 | V65: 0 | W65: 0 | X65: 0 | Y65: =(J65/1000)*(R65/1000) -> 0.426409 | Z65: =Y65*$C$3 -> 170.5636 | AA65: 0 | AB65: 0 | AC65: 0 | AG65: 99 | AH65: 9999 | AI65: 99 | AJ65: 9999 | AK65: 99 | AL65: 9999 | AM65: 0 | AN65: 0 | AO65: 0 | AP65: 0 | AQ65: 0 | AR65: 0 | AS65: 0 | AT65: 0 | AU65: 0 | AV65: 0 | AW65: 0 | AX65: 0 | AY65: 0.9 | BA65: Wordt niet berekend | BD65: 0711
A66: =IF($C$2=B66,1," ") | J66: =(C66*$C$46)+(D66*$D$46)+(E66*$E$46)+(F66*$F$46)+(I66*$I$46)+(G66*H66) -> 0 | R66: =(K66*$K$46)+(L66*$L$46)+(M66*$M$46)+(N66*$N$46)+(Q66*$Q$46)+(O66*P66) -> 0 | Y66: =(J66/1000)*(R66/1000) -> 0 | Z66: =Y66*$C$3 -> 0
A67: =IF($C$2=B67,1," ") | J67: =(C67*$C$46)+(D67*$D$46)+(E67*$E$46)+(F67*$F$46)+(I67*$I$46)+(G67*H67) -> 0 | R67: =(K67*$K$46)+(L67*$L$46)+(M67*$M$46)+(N67*$N$46)+(Q67*$Q$46)+(O67*P67) -> 0 | Y67: =(J67/1000)*(R67/1000) -> 0 | Z67: =Y67*$C$3 -> 0
A68: =IF($C$2=B68,1," ") | J68: =(C68*$C$46)+(D68*$D$46)+(E68*$E$46)+(F68*$F$46)+(I68*$I$46)+(G68*H68) -> 0 | R68: =(K68*$K$46)+(L68*$L$46)+(M68*$M$46)+(N68*$N$46)+(Q68*$Q$46)+(O68*P68) -> 0 | Y68: =(J68/1000)*(R68/1000) -> 0 | Z68: =Y68*$C$3 -> 0
A69: =IF($C$2=B69,1," ") | J69: =(C69*$C$46)+(D69*$D$46)+(E69*$E$46)+(F69*$F$46)+(I69*$I$46)+(G69*H69) -> 0 | R69: =(K69*$K$46)+(L69*$L$46)+(M69*$M$46)+(N69*$N$46)+(Q69*$Q$46)+(O69*P69) -> 0 | Y69: =(J69/1000)*(R69/1000) -> 0 | Z69: =Y69*$C$3 -> 0
A70: =IF($C$2=B70,1," ") | J70: =(C70*$C$46)+(D70*$D$46)+(E70*$E$46)+(F70*$F$46)+(I70*$I$46)+(G70*H70) -> 0 | R70: =(K70*$K$46)+(L70*$L$46)+(M70*$M$46)+(N70*$N$46)+(Q70*$Q$46)+(O70*P70) -> 0 | Y70: =(J70/1000)*(R70/1000) -> 0 | Z70: =Y70*$C$3 -> 0
B73: Maatvoering check:
E75: Lengte | G75: Breedte | I75: Hoogte | K75: Overige voorwaarde | Q75: Maatvoering
B76: L | C76: B | D76: H | E76: Min | F76: Max | G76: Min | H76: Max | I76: Min | J76: Max | K76: H < L | L76: L > 2xB | M76: H min 10% van L | Q76: geschikt
E77: =AG46 -> 100 | F77: =AH46 -> 2000 | G77: =AI46 -> 70 | H77: =AJ46 -> 1000 | I77: =AK46 -> 37 | J77: =AL46 -> 1200 | K77: =AO46 -> 0 | L77: =AP46 -> 0 | M77: =AX46 -> 1 | Q77: 9
B78: =C6 -> 300 | C78: =C7 -> 250 | D78: =C8 -> 100 | E78: =IF(B78>=E77,1,0) -> 1 | F78: =IF(B78<=F77,1,0) -> 1 | G78: =IF(C78>=G77,1,0) -> 1 | H78: =IF(C78<=H77,1,0) -> 1 | I78: =IF(D78>=I77,1,0) -> 1 | J78: =IF(D78<=J77,1,0) -> 1 | K78: =IF(K77=0,1,IF(AND(K77=1,C8<=C6),1,0)) -> 1 | L78: =IF(L77=0,1,IF(AND(L77=1,C6>=(C7*2)),1,0)) -> 1 | M78: =IF(M77=0,1,IF(AND(M77=1,C8>=(C6*0.1)),1,0)) -> 1 | Q78: =IF(SUM(E78:P78)=Q77,1,0) -> 1
B84: Plano formaat (ex lijmlip / afval rondom)
B85: Fefco | C85: Totaal (golfrichting) | D85: Totaal (lengte) | E85: Factor stapelen | F85: Breedte transport | G85: Lengte transport
A87: =A50 | B87: =B50 -> 0110 | C87: =J50 -> 300 | D87: =R50 -> 250 | E87: 1 | F87: =C87 -> 300 | G87: =D87 -> 250
A88: =A51 | B88: =B51 -> 0200 | C88: =J51 -> 232 | D88: =R51 -> 1114 | E88: 2 | F88: =C88 -> 232 | G88: =D88/E88 -> 557
A89: =A52 -> 1 | B89: =B52 -> 0201 | C89: =J52 -> 361 | D89: =R52 -> 1114 | E89: 2 | F89: =C89 -> 361 | G89: =D89/E89 -> 557
A90: =A53 | B90: =B53 -> 0203 | C90: =J53 -> 614 | D90: =R53 -> 1114 | E90: 2 | F90: =C90 -> 614 | G90: =D90/E90 -> 557
A91: =A54 | B91: =B54 -> 0409 | C91: =J54 -> 514 | D91: =R54 -> 819 | E91: 1 | F91: =C91 -> 514 | G91: =D91 -> 819
A92: =A55 | B92: =B55 -> 0410 | C92: =J55 -> 514 | D92: =R55 -> 819 | E92: 1 | F92: =C92 -> 514 | G92: =D92 -> 819
A93: =A56 | B93: =B56 -> 0412 | C93: =J56 -> 978 | D93: =R56 -> 616 | E93: 1 | F93: =C93 -> 978 | G93: =D93 -> 616
A94: =A57 | B94: =B57 -> 0427 | C94: =J57 -> 760 | D94: =R57 -> 819 | E94: 1 | F94: =C94 -> 760 | G94: =D94 -> 819
A95: =A58 | B95: =B58 -> 0421 | C95: =J58 -> 748 | D95: =R58 -> 741 | E95: 1 | F95: =C95 -> 748 | G95: =D95 -> 741
A96: =A59 | B96: =B59 -> 0422 | C96: =J59 -> 748 | D96: =R59 -> 458 | E96: 1 | F96: =C96 -> 748 | G96: =D96 -> 458
A97: =A60 | B97: =B60 -> 0452 | C97: =J60 -> 464 | D97: =R60 -> 508 | E97: 1 | F97: =C97 -> 464 | G97: =D97 -> 508
A98: =A61 | B98: =B61 -> 0501 | C98: =J61 -> 100 | D98: =R61 -> 1114 | E98: 2 | F98: =C98 -> 100 | G98: =D98/E98 -> 557
A99: =A62 | B99: =B62 -> 0401 | C99: =J62 -> 722 | D99: =R62 -> 616 | E99: 1 | F99: =C99 -> 722 | G99: =D99 -> 616
A100: =A63 | B100: =B63 -> 0471 | C100: =J63 -> 822 | D100: =R63 -> 826 | E100: 1 | F100: =C100 -> 822 | G100: =D100 -> 826
A101: =A64 | B101: =B64 -> 0933 | C101: =J64 -> 653 | D101: =R64 -> 653 | E101: 1 | F101: =C101 -> 653 | G101: =D101 -> 653
A102: =A65 | B102: =B65 -> 0701 | C102: =J65 -> 653 | D102: =R65 -> 653 | E102: 1 | F102: =C102 -> 653 | G102: =D102 -> 653
A103: =A66 | B103: =B66 -> 0 | C103: =J66 -> 0 | D103: =R66 -> 0 | F103: =C103 -> 0 | G103: =D103 -> 0
A104: =A67 | B104: =B67 -> 0 | C104: =J67 -> 0 | D104: =R67 -> 0 | F104: =C104 -> 0 | G104: =D104 -> 0
A105: =A68 | B105: =B68 -> 0 | C105: =J68 -> 0 | D105: =R68 -> 0 | F105: =C105 -> 0 | G105: =D105 -> 0
A106: =A69 | B106: =B69 -> 0 | C106: =J69 -> 0 | D106: =R69 -> 0 | F106: =C106 -> 0 | G106: =D106 -> 0 | H106: m2 | I106: m2
A107: =A70 | B107: =B70 -> 0 | C107: =J70 -> 0 | D107: =R70 -> 0 | F107: =C107 -> 0 | G107: =D107 -> 0 | H107: per product | I107: Totaal gewenst
B108: Plano formaat (exl lijmlip) | C108: =VLOOKUP(1,A87:G107,3,FALSE) -> 361 | D108: =VLOOKUP(1,A87:G107,4,FALSE) -> 1114 | E108: =VLOOKUP(1,A87:G107,5,FALSE) -> 2 | F108: =VLOOKUP(1,A87:G107,6,FALSE) -> 361 | G108: =VLOOKUP(1,A87:G107,7,FALSE) -> 557 | H108: =(C108/1000)*(D108/1000) -> 0.402154 | I108: =H108*C3 -> 160.8616
B111: Bedrukking: | C111: =VLOOKUP(1,A113:C116,3,FALSE) -> 0 | D111: =VLOOKUP(1,A113:D116,4,FALSE) -> 0
B112: Keuze | C112: Aantal keuren | D112: Minimaal inkt
A113: =IF($C$14=B113,1," ") -> 1 | B113: onbedrukt | C113: 0 | D113: 0
A114: =IF($C$14=B114,1," ") | B114: zwart | C114: 1 | D114: 30
A115: =IF($C$14=B115,1," ") | B115: 1 kleur naar keuze | C115: 1 | D115: 40
A116: =IF($C$14=B116,1," ") | B116: 2 kleuren naar keuze | C116: 2 | D116: 80
E118: 0.06
C119: =VLOOKUP(1,A121:C128,3,FALSE) -> 0.05 | D119: =VLOOKUP(1,A121:D128,4,FALSE) -> 0.0201077 | E119: =IF(VLOOKUP(1,A121:E128,5,FALSE)<=D111,D111,VLOOKUP(1,A121:E128,5,FALSE)) -> 0.4825848
B120: Keuze | C120: Percentage | D120: m2 bedr / doos | E120: Kosten inkt
A121: =IF($C$15=B121,1," ") -> 1 | B121: Onbedrukt / minder dan 10% | C121: 0.05 | D121: =C121*$H$108 -> 0.0201077 | E121: =(D121*$C$3)*$E$118 -> 0.4825848
...

Sheet Kwaliteit conversie
B4: =VLOOKUP(BLO!B6,$A$5:$D$70,2,0) -> B | C4: =VLOOKUP(BLO!B6,$A$5:$D$70,3,0) -> Wit extra sterk | D4: =VLOOKUP(BLO!B6,$A$5:$D$70,4,0) -> BKT14WS | G4: Keuze | H4: =IF(H5=Input!$B$3,1,0) -> 0 | I4: =IF(I5=Input!$B$3,1,0) -> 1 | J4: =IF(J5=Input!$B$3,1,0) -> 0 | K4: =IF(K5=Input!$B$3,1,0) -> 0 | L4: =IF(L5=Input!$B$3,1,0) -> 0 | M4: =IF(M5=Input!$B$3,1,0) -> 0 | N4: =IF(N5=Input!$B$3,1,0) -> 0 | O4: =IF(O5=Input!$B$3,1,0) -> 0 | P4: =IF(P5=Input!$B$3,1,0) -> 0
A5: Selectie | B5: Golf | C5: Naam | D5: Code | H5: E | I5: B | J5: C | K5: EE | L5: EB | M5: BE | N5: BC | O5: AC | P5: AAC
A6: 10095 | B6: E | C6: Bruin budget | D6: ET12 | F6: 3 | G6: =HLOOKUP(1,$H$4:$Q$24,F6,FALSE) -> Bruin budget | H6: Bruin budget | I6: Bruin budget | J6: Bruin budget | K6: Bruin standaard | L6: Bruin budget | M6: Bruin budget | N6: Bruin budget | O6: Bruin standaard | P6: Bruin budget
A7: 10097 | B7: E | C7: Bruin standaard | D7: ET13/12 | F7: 4 | G7: =HLOOKUP(1,$H$4:$Q$24,F7,FALSE) -> Bruin standaard | H7: Bruin standaard | I7: Bruin standaard | J7: Bruin standaard | K7: =" " | L7: Bruin standaard | M7: Bruin standaard | N7: Bruin standaard | O7: Bruin extra sterk | P7: Bruin standaard
A8: 10134 | B8: E | C8: Bruin extra sterk | D8: EK13 | F8: 5 | G8: =HLOOKUP(1,$H$4:$Q$24,F8,FALSE) -> bruin extra sterk | H8: bruin extra sterk | I8: bruin extra sterk | J8: bruin extra sterk | K8: =" " | L8: Wit budget | M8: Wit standaard | N8: bruin extra sterk | O8: =" " | P8: bruin extra sterk
A9: 10099 | B9: E | C9: Wit standaard | D9: ETWT14 | F9: 6 | G9: =HLOOKUP(1,$H$4:$Q$24,F9,FALSE) -> Wit standaard | H9: Wit standaard | I9: Wit standaard | J9: Wit standaard | K9: =" " | L9: Wit standaard | M9: =" " | N9: Wit standaard | O9: =" " | P9: =" "
A10: 10131 | B10: E | C10: Wit extra sterk | D10: ETWT14 W2 | F10: 7 | G10: =HLOOKUP(1,$H$4:$Q$24,F10,FALSE) -> Wit extra sterk | H10: Wit extra sterk | I10: Wit extra sterk | J10: =" " | K10: =" " | L10: =" " | M10: =" " | N10: =" " | O10: =" " | P10: =" "
A11: 10326 | B11: B | C11: Bruin budget | D11: BT13 | F11: 8 | G11: =HLOOKUP(1,$H$4:$Q$24,F11,FALSE) | H11: =" " | I11: =" " | J11: =" " | K11: =" " | L11: =" " | M11: =" " | N11: =" " | O11: =" " | P11: =" "
A12: 10005 | B12: B | C12: Bruin standaard | D12: BKT14 | F12: 9 | G12: =HLOOKUP(1,$H$4:$Q$24,F12,FALSE) | H12: =" " | I12: =" " | J12: =" " | K12: =" " | L12: =" " | M12: =" " | N12: =" " | O12: =" " | P12: =" "
A13: 10017 | B13: B | C13: bruin extra sterk | D13: BKT19 | F13: 10 | G13: =HLOOKUP(1,$H$4:$Q$24,F13,FALSE) | H13: =" " | I13: =" " | J13: =" " | K13: =" " | L13: =" " | M13: =" " | N13: =" " | O13: =" " | P13: =" "
A14: 10002 | B14: B | C14: Wit standaard | D14: BDUWT14 | F14: 11 | G14: =HLOOKUP(1,$H$4:$Q$24,F14,FALSE) | H14: =" " | I14: =" " | J14: =" " | K14: =" " | L14: =" " | M14: =" " | N14: =" " | O14: =" " | P14: =" "
A15: 10010 | B15: B | C15: Wit extra sterk | D15: BKT14WS | F15: 12 | G15: =HLOOKUP(1,$H$4:$Q$24,F15,FALSE) | H15: =" " | I15: =" " | J15: =" " | K15: =" " | L15: =" " | M15: =" " | N15: =" " | O15: =" " | P15: =" "
A16: 10053 | B16: C | C16: Bruin budget | D16: CT14 | F16: 13 | G16: =HLOOKUP(1,$H$4:$Q$24,F16,FALSE) | H16: =" " | I16: =" " | J16: =" " | K16: =" " | L16: =" " | M16: =" " | N16: =" " | O16: =" " | P16: =" "
A17: 10193 | B17: C | C17: Bruin standaard | D17: CKT15 W6 | F17: 14 | G17: =HLOOKUP(1,$H$4:$Q$24,F17,FALSE) | H17: =" " | I17: =" " | J17: =" " | K17: =" " | L17: =" " | M17: =" " | N17: =" " | O17: =" " | P17: =" "
A18: 10050 | B18: C | C18: Bruin extra sterk | D18: CKT19 | F18: 15 | G18: =HLOOKUP(1,$H$4:$Q$24,F18,FALSE) | H18: =" " | I18: =" " | J18: =" " | K18: =" " | L18: =" " | M18: =" " | N18: =" " | O18: =" " | P18: =" "
A19: 10221 | B19: C | C19: Wit standaard | D19: CKT14WS | F19: 16 | G19: =HLOOKUP(1,$H$4:$Q$24,F19,FALSE) | H19: =" " | I19: =" " | J19: =" " | K19: =" " | L19: =" " | M19: =" " | N19: =" " | O19: =" " | P19: =" "
A20: 10339 | B20: EE | C20: Bruin standaard | D20: EET13K | F20: 17 | G20: =HLOOKUP(1,$H$4:$Q$24,F20,FALSE) | H20: =" " | I20: =" " | J20: =" " | K20: =" " | L20: =" " | M20: =" " | N20: =" " | O20: =" " | P20: =" "
A21: 10335 | B21: EB | C21: Bruin budget | D21: EBT12 | F21: 18 | G21: =HLOOKUP(1,$H$4:$Q$24,F21,FALSE) | H21: =" " | I21: =" " | J21: =" " | K21: =" " | L21: =" " | M21: =" " | N21: =" " | O21: =" " | P21: =" "
A22: 10368 | B22: EB | C22: Bruin standaard | D22: EBKT15 | F22: 19 | G22: =HLOOKUP(1,$H$4:$Q$24,F22,FALSE) | H22: =" " | I22: =" " | J22: =" " | K22: =" " | L22: =" " | M22: =" " | N22: =" " | O22: =" " | P22: =" "
A23: 10136 | B23: EB | C23: Wit budget | D23: EBT13/10W | F23: 20 | G23: =HLOOKUP(1,$H$4:$Q$24,F23,FALSE) | H23: =" " | I23: =" " | J23: =" " | K23: =" " | L23: =" " | M23: =" " | N23: =" " | O23: =" " | P23: =" "
A24: 10140 | B24: EB | C24: Wit standaard | D24: EBKT13/12W
A25: 10197 | B25: BE | C25: Bruin budget | D25: BET14/12
A26: 10199 | B26: BE | C26: Bruin standaard | D26: BEKT12
A27: 10200 | B27: BE | C27: Wit standaard | D27: BEKT13/12W
A28: 10178 | B28: BC | C28: Bruin budget | D28: DT14 N2
A29: 10158 | B29: BC | C29: Bruin standaard | D29: DKT14 N2
A30: 10183 | B30: BC | C30: bruin extra sterk | D30: DKT19 N2
A31: 10181 | B31: BC | C31: Wit standaard | D31: DKT13/12W N2
A32: 10214 | B32: AC | C32: Bruin standaard | D32: ACK30/30
A33: 10215 | B33: AC | C33: Bruin extra sterk | D33: ACK40
A34: 10216 | B34: AAC | C34: Bruin budget | D34: AACK14
A35: 10218 | B35: AAC | C35: Bruin standaard | D35: AACK30/20
A36: 10220 | B36: AAC | C36: bruin extra sterk | D36: AACKK40/40

Sheet Tarieven
B4: Machine | C4: Geselecteerde prijs
B5: Emba 295 | C5: 550
B6: Emba 170 | C6: 300
B7: Maxi blauw | C7: 190
B8: Mini | C8: 125
B9: Taper (gemiddeld tarief) | C9: 94
B10: Wookil | C10: 150
B11: Roda | C11: 96
B12: Overige | C12: 37
B13: Order kosten | C13: 20
B14: Kosten per pallet | C14: 4
B15: Brandstoftoeslag | C15: 0.195
B16: Tape kosten per meter | C16: 0.0912

Sheet Prijs karton
A1: Prijs Karton | B1: 2 | C1: 3 | D1: 4 | E1: 5 | F1: 6 | G1: 7 | H1: 8 | I1: 9 | J1: 10 | K1: 11 | L1: 12 | M1: 13 | N1: 14 | O1: 15 | P1: 16 | Q1: 17 | R1: 18 | S1: 19 | T1: 20 | U1: 21 | V1: 22 | W1: 23 | X1: 24 | Y1: 25 | Z1: 26 | AA1: 27 | AB1: 28 | AC1: 29
N3: Voorwaarde Pro | T3: Voorwaarde Kappa
C4: Gebruik: | M4: 1 | N4: Plaatlengte korter dan | O4: 600 | P4: 4 | Q4: extra per HQM | S4: 1 | T4: Plaatlengte korter dan | U4: 600 | V4: 4 | W4: extra per HQM
C5: Alle gele cellen vullen door deze te copieren uit verkoopprijsmodel. Altijd plakken "waarde" gebruiken | M5: 2 | N5: Plaatlengte korter dan | O5: 700 | P5: 2 | Q5: extra per HQM | S5: 2 | T5: Plaatlengte korter dan | U5: 750 | V5: 2 | W5: extra per HQM
C6: Cellen kunnen t/m "ECT" in een keer worden gecopieerd. Daarna rij voor rij bekijken. | M6: 3 | N6: Plaatlengte lager dan | O6: 5000 | P6: =VLOOKUP("X",19:254,29,FALSE) -> 0 | Q6: extra per HQM | S6: 3 | T6: Plaatlengte langer dan | U6: 5000 | V6: 5 | W6: extra per HQM
M7: 4 | N7: =" " | O7: =" " | P7: =" " | Q7: =" " | S7: 4 | T7: =" " | U7: =" " | V7: =" " | W7: =" "
M8: 5 | N8: =" " | O8: =" " | P8: =" " | Q8: =" " | S8: 5 | T8: =" "
M9: 6 | N9: =" " | O9: =" " | P9: =" " | Q9: =" " | S9: 6
M10: 7 | N10: =" " | O10: =" " | P10: =" " | Q10: =" " | S10: 7
M11: 8 | N11: =" " | O11: =" " | P11: =" " | Q11: =" " | S11: 8
M12: 9 | N12: =" " | O12: =" " | P12: =" " | Q12: =" " | S12: 9
M13: 10 | N13: =" " | O13: =" " | P13: =" " | Q13: =" " | S13: 10
B15: 2 | C15: 3 | D15: 4 | E15: 5 | F15: 6 | G15: 7 | H15: 8 | I15: 9 | J15: 10 | K15: 11 | L15: 12 | M15: 13 | N15: 14 | O15: 15 | P15: 16 | Q15: 17 | R15: 18 | S15: 19 | T15: 20 | U15: 21 | V15: 22 | W15: 23 | X15: 24 | Y15: 25 | Z15: 26 | AA15: 27 | AB15: 28 | AC15: 29 | AD15: 30 | AE15: 31 | AF15: 32 | AG15: 33 | AH15: 34 | AI15: 35 | AJ15: 36
A16: Keuze | B16: Type golf | C16: Kwaliteitscodering Arifal | D16: kg. per m2 | E16: Dikte (mm) | F16: 0 | G16: 200 | H16: 500 | I16: 1000 | J16: 2000 | K16: 5000 | AC16: Toeslag plaat tussen Pro | AD16: =VLOOKUP("X",19:254,AD15,FALSE) -> 1 | AE16: =VLOOKUP("X",19:254,AE15,FALSE) -> 1 | AF16: =VLOOKUP("X",19:254,AF15,FALSE) -> 1 | AG16: =VLOOKUP("X",19:254,AG15,FALSE) -> 1 | AH16: =VLOOKUP("X",19:254,AH15,FALSE) -> 1 | AI16: =VLOOKUP("X",19:254,AI15,FALSE) -> 1 | AJ16: =VLOOKUP("X",19:254,AJ15,FALSE) -> 1
F17: 200 | G17: 500 | H17: 1000 | I17: 2000 | J17: 5000 | K17: 999999 | T17: LEVERANCIER | AC17: 5000 | AD17: Mini | AE17: Maxi | AF17: Emba 170 | AG17: Emba 295 | AH17: Stans | AI17: Roda | AJ17: Plaat op maat
F18: 0-199 | G18: 200-499 | H18: 500-999 | I18: 1000-1999 | J18: 2000-4999 | K18: >5000 | L18: Code | M18: Buiten | N18: Golf | O18: Tussen | P18: Golf | Q18: Tussen | R18: Golf | S18: Binnen | U18: min plano breedte | V18: max plano breedte | W18: min plano lengte | X18: max plano lengte | Y18: min platen < 550 br | Z18: min platen | AA18: min m2 | AB18: Ect | AC18: 6200 | AD18: mogelijk | AE18: mogelijk | AF18: mogelijk | AG18: mogelijk | AH18: mogelijk | AI18: mogelijk | AJ18: mogelijk
A19: =IF('Kwaliteit conversie'!$D$4='Prijs karton'!C19,"X"," ") | B19: B | C19: BT10 K | D19: 0.351 | E19: 2.84 | F19: 0 | G19: 40.5 | H19: 37.5 | I19: 37.5 | J19: 35.5 | K19: 35.5 | L19: B 70301 | M19: TL 100 | N19: WS 100 | O19: - | P19: - | Q19: - | R19: - | S19: TL 100 | T19: Kappa | U19: 240 | V19: 2450 | W19: 500 | X19: 6000 | Y19: 125 | Z19: 125 | AA19: 200 | AB19: 4.02 | AC19: 0 | AD19: 1 | AE19: 1 | AF19: 1 | AG19: 1 | AH19: 1 | AI19: 1 | AJ19: 1
A20: =IF('Kwaliteit conversie'!$D$4='Prijs karton'!C20,"X"," ") | B20: B | C20: BTS12/11 | D20: 0.305 | E20: 2.7 | F20: 0 | G20: 27.7 | H20: 24.7 | I20: 24.2 | J20: 24.2 | K20: 23.7 | L20: 1.01 B | M20: TL 90 | N20: WS 90 | O20: - | P20: - | Q20: - | R20: - | S20: WS 90 | T20: Pro | U20: 250 | V20: 2450 | W20: 500 | X20: 6200 | Y20: 480 | Z20: 240 | AA20: 200 | AB20: 3 | AC20: 0 | AD20: 1 | AE20: 1 | AF20: 1 | AG20: 1 | AH20: 1 | AI20: 1 | AJ20: 1
A21: =IF('Kwaliteit conversie'!$D$4='Prijs karton'!C21,"X"," ") | B21: B | C21: BT12 | D21: 0.365 | E21: 2.8 | F21: 0 | G21: 31 | H21: 28 | I21: 27.5 | J21: 27.5 | K21: 27 | L21: 1.02 B W1 | M21: TL115 | N21: WS 100 | O21: - | P21: - | Q21: - | R21: - | S21: TL 115 | T21: Pro | U21: 250 | V21: 2450 | W21: 500 | X21: 6200 | Y21: 480 | Z21: 240 | AA21: 200 | AB21: 4 | AC21: 0 | AD21: 1 | AE21: 1 | AF21: 1 | AG21: 1 | AH21: 1 | AI21: 1 | AJ21: 1
A22: =IF('Kwaliteit conversie'!$D$4='Prijs karton'!C22,"X"," ") | B22: B | C22: BT11 | D22: 0.355 | E22: 2.8 | F22: 0 | G22: 28.8 | H22: 25.8 | I22: 25.3 | J22: 25.3 | K22: 24.8 | L22: 1.02 B | M22: TL 115 | N22: WS 90 | O22: - | P22: - | Q22: - | R22: - | S22: TL 115 | T22: Pro | U22: 250 | V22: 2450 | W22: 500 | X22: 6200 | Y22: 480 | Z22: 240 | AA22: 200 | AB22: 3.6 | AC22: 10 | AD22: 1 | AE22: 1 | AF22: 1 | AG22: 1 | AH22: 1 | AI22: 1 | AJ22: 1
A23: =IF('Kwaliteit conversie'!$D$4='Prijs karton'!C23,"X"," ") | B23: B | C23: BT11 K | D23: 0.365 | E23: 2.84 | F23: 0 | G23: 41.1 | H23: 38.1 | I23: 38.1 | J23: 36.1 | K23: 36.1 | L23: B 70303 | M23: TL 110 | N23: WS 100 | O23: - | P23: - | Q23: - | R23: - | S23: TL 110 | T23: Kappa | U23: 240 | V23: 2450 | W23: 500 | X23: 6000 | Y23: 125 | Z23: 125 | AA23: 200 | AB23: 4 | AC23: 0 | AD23: 1 | AE23: 1 | AF23: 1 | AG23: 1 | AH23: 1 | AI23: 1 | AJ23: 1
A24: =IF('Kwaliteit conversie'!$D$4='Prijs karton'!C24,"X"," ") | B24: B
A25: =IF('Kwaliteit conversie'!$D$4='Prijs karton'!C25,"X"," ") | B25: B | C25: BT14 | D25: 0.375 | E25: 2.8 | F25: 0 | G25: 29.8 | H25: 26.8 | I25: 26.3 | J25: 26.3 | K25: 25.8 | L25: 1.03 B | M25: TL 135 | N25: WS 90 | O25: - | P25: - | Q25: - | R25: - | S25: TL 115 | T25: Pro | U25: 250 | V25: 2450 | W25: 500 | X25: 6200 | Y25: 480 | Z25: 240 | AA25: 200 | AB25: 3.9 | AC25: 10 | AD25: 1 | AE25: 1 | AF25: 1 | AG25: 1 | AH25: 1 | AI25: 1 | AJ25: 1
A26: =IF('Kwaliteit conversie'!$D$4='Prijs karton'!C26,"X"," ") | B26: B
A27: =IF('Kwaliteit conversie'!$D$4='Prijs karton'!C27,"X"," ") | B27: B | C27: BT14S K | D27: 0.381 | E27: 2.88 | F27: 0 | G27: 44.9 | H27: 41.9 | I27: 41.9 | J27: 39.9 | K27: 39.9 | L27: B 720 | M27: THP 125 | N27: WS 100 | O27: - | P27: - | Q27: - | R27: - | S27: THP 125 | T27: Kappa | U27: 240 | V27: 2450 | W27: 500 | X27: 6000 | Y27: 125 | Z27: 125 | AA27: 200 | AB27: 4.87 | AC27: 0 | AD27: 1 | AE27: 1 | AF27: 1 | AG27: 1 | AH27: 1 | AI27: 1 | AJ27: 1
A28: =IF('Kwaliteit conversie'!$D$4='Prijs karton'!C28,"X"," ") | B28: B | C28: BT14 N2 | D28: 0.36 | E28: 2.3 | F28: 0 | G28: 29.6 | H28: 26.6 | I28: 26.1 | J28: 26.1 | K28: 25.6 | L28: 1.03 B N2 | M28: TL 135 | N28: WS 80 | O28: - | P28: - | Q28: - | R28: - | S28: TL 115 | T28: Pro | U28: 250 | V28: 2450 | W28: 500 | X28: 6200 | Y28: 480 | Z28: 240 | AA28: 200 | AB28: 4.1 | AC28: 0 | AD28: 1 | AE28: 1 | AF28: 1 | AG28: 1 | AH28: 1 | AI28: 1 | AJ28: 1
A29: =IF('Kwaliteit conversie'!$D$4='Prijs karton'!C29,"X"," ") | B29: B | C29: BT13/14 | D29: 0.43 | E29: 2.8 | F29: 0 | G29: 37.5 | H29: 34.5 | I29: 34 | J29: 34 | K29: 33.5 | L29: 1.03 B W6 | M29: TL 135 | N29: WS 135 | O29: - | P29: - | Q29: - | R29: - | S29: TL 115 | T29: Pro | U29: 250 | V29: 2450 | W29: 500 | X29: 6200 | Y29: 480 | Z29: 240 | AA29: 200 | AB29: 5 | AC29: 0 | AD29: 1 | AE29: 1 | AF29: 1 | AG29: 1 | AH29: 1 | AI29: 1 | AJ29: 1
A30: =IF('Kwaliteit conversie'!$D$4='Prijs karton'!C30,"X"," ") | B30: B | C30: BT14/15 | D30: 0.45 | E30: 2.8 | F30: 0 | G30: 38.5 | H30: 35.5 | I30: 35 | J30: 35 | K30: 34.5 | L30: 1.04 B W6 | M30: TL 135 | N30: WS 135 | O30: - | P30: - | Q30: - | R30: - | S30: TL 135 | T30: Pro | U30: 250 | V30: 2450 | W30: 500 | X30: 6200 | Y30: 480 | Z30: 240 | AA30: 200 | AB30: 5.2 | AC30: 0 | AD30: 1 | AE30: 1 | AF30: 1 | AG30: 1 | AH30: 1 | AI30: 1 | AJ30: 1
A31: =IF('Kwaliteit conversie'!$D$4='Prijs karton'!C31,"X"," ") | B31: B | C31: BDUWT14 | D31: 0.395 | E31: 2.8 | F31: 0 | G31: 39.3 | H31: 36.3 | I31: 35.8 | J31: 35.8 | K31: 35.3 | L31: 1.25 B | M31: TLW 135 | N31: WS 90 | O31: - | P31: - | Q31: - | R31: - | S31: TL 135 | T31: Pro | U31: 250 | V31: 2450 | W31: 500 | X31: 6200 | Y31: 480 | Z31: 240 | AA31: 200 | AB31: 3.9 | AC31: 0 | AD31: 1 | AE31: 1 | AF31: 1 | AG31: 1 | AH31: 1 | AI31: 1 | AJ31: 1
A32: =IF('Kwaliteit conversie'!$D$4='Prijs karton'!C32,"X"," ") | B32: B | C32: BDUWT14 K | D32: 0.391 | E32: 2.85 | F32: 0 | G32: - | H32: 47.3 | I32: 47.3 | J32: 45.3 | K32: 45.3 | L32: B 742 | M32: TLW 135 | N32: WS 100 | O32: - | P32: - | Q32: - | R32: - | S32: THP 125 | T32: Kappa | U32: 240 | V32: 2450 | W32: 500 | X32: 6000 | Y32: 125 | Z32: 125 | AA32: 500 | AB32: 4.55 | AC32: 0 | AD32: 1 | AE32: 1 | AF32: 1 | AG32: 1 | AH32: 1 | AI32: 1 | AJ32: 1
A33: =IF('Kwaliteit conversie'!$D$4='Prijs karton'!C33,"X"," ") | B33: B
A34: =IF('Kwaliteit conversie'!$D$4='Prijs karton'!C34,"X"," ") | B34: B
A35: =IF('Kwaliteit conversie'!$D$4='Prijs karton'!C35,"X"," ") | B35: B | C35: BKT13 | D35: 0.4 | E35: 2.8 | F35: 0 | G35: 38.7 | H35: 35.7 | I35: 35.2 | J35: 35.2 | K35: 34.7 | L35: 1.30 B | M35: PLK 140 | N35: WS 90 | O35: - | P35: - | Q35: - | R35: - | S35: TL 135 | T35: Pro | U35: 250 | V35: 2450 | W35: 500 | X35: 6200 | Y35: 480 | Z35: 240 | AA35: 200 | AB35: 4.6 | AC35: 0 | AD35: 1 | AE35: 1 | AF35: 1 | AG35: 1 | AH35: 1 | AI35: 1 | AJ35: 1
A36: =IF('Kwaliteit conversie'!$D$4='Prijs karton'!C36,"X"," ") | B36: B | C36: BKT13 K | D36: 0.391 | E36: 2.87 | F36: 0 | G36: 50.6 | H36: 47.6 | I36: 47.6 | J36: 45.6 | K36: 45.6 | L36: B 725 | M36: KL 135 | N36: WS 100 | O36: - | P36: - | Q36: - | R36: - | S36: THP 125 | T36: Kappa | U36: 240 | V36: 2450 | W36: 500 | X36: 6000 | Y36: 125 | Z36: 125 | AA36: 200 | AB36: 5.07 | AC36: 0 | AD36: 1 | AE36: 1 | AF36: 1 | AG36: 1 | AH36: 1 | AI36: 1 | AJ36: 1
A37: =IF('Kwaliteit conversie'!$D$4='Prijs karton'!C37,"X"," ") | B37: B
A38: =IF('Kwaliteit conversie'!$D$4='Prijs karton'!C38,"X"," ") | B38: B
A39: =IF('Kwaliteit conversie'!$D$4='Prijs karton'!C39,"X"," ") | B39: B | C39: BT13 | D39: 0.385 | E39: 2.8 | F39: 0 | G39: 33.9 | H39: 30.9 | I39: 30.4 | J39: 30.4 | K39: 29.9 | L39: 1.03 B W1 | M39: TL 135 | N39: WS 100 | O39: - | P39: - | Q39: - | R39: - | S39: TL 115 | T39: Pro | U39: 250 | V39: 2450 | W39: 500 | X39: 6200 | Y39: 480 | Z39: 240 | AA39: 200 | AB39: 4.4 | AC39: 0 | AD39: 1 | AE39: 1 | AF39: 1 | AG39: 1 | AH39: 1 | AI39: 1 | AJ39: 1
A40: =IF('Kwaliteit conversie'!$D$4='Prijs karton'!C40,"X"," ") | B40: B | C40: BKT14 | D40: 0.455 | E40: 2.8 | F40: 0 | G40: 39.4 | H40: 36.4 | I40: 35.9 | J40: 35.9 | K40: 35.4 | L40: 1.30 B W6 | M40: PLK 140 | N40: WS 135 | O40: - | P40: - | Q40: - | R40: - | S40: TL 135 | T40: Pro | U40: 250 | V40: 2450 | W40: 500 | X40: 6200 | Y40: 480 | Z40: 240 | AA40: 200 | AB40: 5.6 | AC40: 10 | AD40: 1 | AE40: 1 | AF40: 1 | AG40: 1 | AH40: 1 | AI40: 1 | AJ40: 1
A41: =IF('Kwaliteit conversie'!$D$4='Prijs karton'!C41,"X"," ") | B41: B | C41: BKT14K | D41: 0.45 | E41: 2.8 | F41: 0 | G41: 44 | H41: 41 | I41: 40.5 | J41: 40.5 | K41: 40 | L41: 1.31 B | M41: KL 135 | N41: WS 135 | O41: - | P41: - | Q41: - | R41: - | S41: TL 135 | T41: Pro | U41: 250 | V41: 2450 | W41: 500 | X41: 6200 | Y41: 480 | Z41: 240 | AA41: 200 | AB41: 5.4 | AC41: 0 | AD41: 1 | AE41: 1 | AF41: 1 | AG41: 1 | AH41: 1 | AI41: 1 | AJ41: 1
A42: =IF('Kwaliteit conversie'!$D$4='Prijs karton'!C42,"X"," ") | B42: B | C42: BT13 N7 | D42: 0.425 | E42: 2.3 | F42: 0 | G42: 36.2 | H42: 33.2 | I42: 32.7 | J42: 32.7 | K42: 32.2 | L42: 1.04 B N7 | M42: TL 135 | N42: WS 115 | O42: - | P42: - | Q42: - | R42: - | S42: TL 135 | T42: Pro | U42: 250 | V42: 2450 | W42: 500 | X42: 6200 | Y42: 480 | Z42: 240 | AA42: 200 | AB42: 5 | AC42: 0 | AD42: 1 | AE42: 1 | AF42: 1 | AG42: 1 | AH42: 1 | AI42: 1 | AJ42: 1
A43: =IF('Kwaliteit conversie'!$D$4='Prijs karton'!C43,"X"," ") | B43: B | C43: BKT13/14 | D43: 0.43 | E43: 2.8 | F43: 0 | G43: 38.7 | H43: 35.7 | I43: 35.2 | J43: 35.2 | K43: 34.7 | L43: 1.30 B W7 | M43: PLK 140 | N43: WS 115 | O43: - | P43: - | Q43: - | R43: - | S43: TL 135 | T43: Pro | U43: 250 | V43: 2450 | W43: 500 | X43: 6200 | Y43: 480 | Z43: 240 | AA43: 200 | AB43: 5.3 | AC43: 0 | AD43: 1 | AE43: 1 | AF43: 1 | AG43: 1 | AH43: 1 | AI43: 1 | AJ43: 1
A44: =IF('Kwaliteit conversie'!$D$4='Prijs karton'!C44,"X"," ") -> X | B44: B | C44: BKT14WS | D44: 0.45 | E44: 2.8 | F44: 0 | G44: 47.2 | H44: 44.2 | I44: 43.7 | J44: 43.7 | K44: 43.2 | L44: 1.37 B W6 | M44: KLW 135 | N44: WS 135 | O44: - | P44: - | Q44: - | R44: - | S44: TL 135 | T44: Pro | U44: 250 | V44: 2450 | W44: 500 | X44: 6000 | Y44: 480 | Z44: 240 | AA44: 200 | AB44: 5.3 | AC44: 0 | AD44: 1 | AE44: 1 | AF44: 1 | AG44: 1 | AH44: 1 | AI44: 1 | AJ44: 1
A45: =IF('Kwaliteit conversie'!$D$4='Prijs karton'!C45,"X"," ") | B45: B
A46: =IF('Kwaliteit conversie'!$D$4='Prijs karton'!C46,"X"," ") | B46: B | C46: BT17 W6 | D46: 0.52 | E46: 2.9 | F46: 0 | G46: 43.4 | H46: 40.4 | I46: 39.9 | J46: 39.9 | K46: 39.4 | L46: 1.05 B W6 | M46: TL 170 | N46: WS 135 | O46: - | P46: - | Q46: - | R46: - | S46: TL 170 | T46: Pro | U46: 250 | V46: 2450 | W46: 500 | X46: 6000 | Y46: 480 | Z46: 240 | AA46: 200 | AB46: 6.3 | AC46: 0 | AD46: 1 | AE46: 1 | AF46: 1 | AG46: 1 | AH46: 1 | AI46: 1 | AJ46: 1
A47: =IF('Kwaliteit conversie'!$D$4='Prijs karton'!C47,"X"," ") | B47: B | C47: BKT19 | D47: 0.495 | E47: 2.9 | F47: 0 | G47: 52.5 | H47: 49.5 | I47: 49 | J47: 49 | K47: 48.5 | L47: 1.41 B | M47: KL 175 | N47: WS 135 | O47: - | P47: - | Q47: - | R47: - | S47: PLK 140 | T47: Pro | U47: 250 | V47: 2450 | W47: 500 | X47: 6200 | Y47: 480 | Z47: 240 | AA47: 200 | AB47: 6.2 | AC47: 0 | AD47: 1 | AE47: 1 | AF47: 1 | AG47: 1 | AH47: 1 | AI47: 1 | AJ47: 1
A48: =IF('Kwaliteit conversie'!$D$4='Prijs karton'!C48,"X"," ") | B48: B | C48: BKT19 X6 | D48: 0.495 | E48: 2.9 | F48: 0 | G48: 50 | H48: 47 | I48: 46.5 | J48: 46.5 | K48: 46 | L48: 1.40 B X6 | M48: PLK 175 | N48: WS 135 | O48: - | P48: - | Q48: - | R48: - | S48: PLK 140 | T48: Pro | U48: 250 | V48: 2450 | W48: 500 | X48: 6200 | Y48: 480 | Z48: 240 | AA48: 200 | AB48: 6.5 | AC48: 0 | AD48: 1 | AE48: 1 | AF48: 1 | AG48: 1 | AH48: 1 | AI48: 1 | AJ48: 1
A49: =IF('Kwaliteit conversie'!$D$4='Prijs karton'!C49,"X"," ") | B49: B | C49: BKT19 K | D49: 0.471 | E49: 3 | F49: 0 | G49: 56.5 | H49: 53.5 | I49: 53.5 | J49: 51.5 | K49: 51.5 | L49: B 730 | M49: KL 170 | N49: WS 100 | O49: - | P49: - | Q49: - | R49: - | S49: THP 150 | T49: Kappa | U49: 240 | V49: 2450 | W49: 500 | X49: 6000 | Y49: 125 | Z49: 125 | AA49: 200 | AB49: 5.74 | AC49: 0 | AD49: 1 | AE49: 1 | AF49: 1 | AG49: 1 | AH49: 1 | AI49: 1 | AJ49: 1
A50: =IF('Kwaliteit conversie'!$D$4='Prijs karton'!C50,"X"," ") | B50: B | O50: - | P50: - | Q50: - | R50: -
A51: =IF('Kwaliteit conversie'!$D$4='Prijs karton'!C51,"X"," ") | B51: B | O51: - | P51: - | Q51: - | R51: -
A52: =IF('Kwaliteit conversie'!$D$4='Prijs karton'!C52,"X"," ") | B52: B | C52: BKT14W | D52: 0.395 | E52: 2.8 | F52: 0 | G52: 43.2 | H52: 40.2 | I52: 39.7 | J52: 39.7 | K52: 39.2 | L52: 1.37 B | M52: KLW 135 | N52: WS 90 | O52: - | P52: - | Q52: - | R52: - | S52: TL 135 | T52: Pro | U52: 250 | V52: 2450 | W52: 500 | X52: 6200 | Y52: 480 | Z52: 240 | AA52: 200 | AB52: 4.4 | AC52: 0 | AD52: 1 | AE52: 1 | AF52: 1 | AG52: 1 | AH52: 1 | AI52: 1 | AJ52: 1
A53: =IF('Kwaliteit conversie'!$D$4='Prijs karton'!C53,"X"," ") | B53: B | C53: BDUWT14 W6 | D53: 0.45 | E53: 2.8 | F53: 0 | G53: 43.5 | H53: 40.5 | I53: 40 | J53: 40 | K53: 39.5 | L53: 1.25 B W6 | M53: TLW 135 | N53: WS 135 | O53: - | P53: - | Q53: - | R53: - | S53: TL135 | T53: Pro | U53: 250 | V53: 2450 | W53: 500 | X53: 6200 | Y53: 480 | Z53: 240 | AA53: 200 | AB53: 4.8 | AC53: 0 | AD53: 1 | AE53: 1 | AF53: 1 | AG53: 1 | AH53: 1 | AI53: 1 | AJ53: 1
A54: =IF('Kwaliteit conversie'!$D$4='Prijs karton'!C54,"X"," ") | B54: B | C54: BDUWT15 | D54: 0.405 | E54: 2.8 | F54: 0 | G54: 40.5 | H54: 37.5 | I54: 37 | J54: 37 | K54: 36.5 | L54: 1.25 B W1 | M54: TLW 135 | N54: WS 100 | O54: - | P54: - | Q54: - | R54: - | S54: TL135 | T54: Pro | U54: 250 | V54: 2450 | W54: 500 | X54: 6200 | Y54: 480 | Z54: 240 | AA54: 200 | AB54: 4.3 | AC54: 0 | AD54: 1 | AE54: 1 | AF54: 1 | AG54: 1 | AH54: 1 | AI54: 1 | AJ54: 1
A55: =IF('Kwaliteit conversie'!$D$4='Prijs karton'!C55,"X"," ") | B55: B | C55: BKT13W K | D55: 0.376 | E55: 2.83 | F55: 0 | G55: 53.6 | H55: 50.6 | I55: 50.6 | J55: 48.6 | K55: 48.6 | L55: B 748 | M55: KLW 135 | N55: WS 100 | O55: - | P55: - | Q55: - | R55: - | S55: TL110 | T55: Kappa | U55: 240 | V55: 2450 | W55: 500 | X55: 6000 | Y55: 125 | Z55: 125 | AA55: 200 | AB55: 4.77 | AC55: 0 | AD55: 1 | AE55: 1 | AF55: 1 | AG55: 1 | AH55: 1 | AI55: 1 | AJ55: 1
A56: =IF('Kwaliteit conversie'!$D$4='Prijs karton'!C56,"X"," ") | B56: B | C56: BK14WW K | D56: 0.401 | E56: 2.82 | F56: 0 | G56: - | H56: 57.4 | I56: 57.4 | J56: 55.4 | K56: 55.4 | L56: B 74814 | M56: KLW 135 | N56: WS 100 | O56: - | P56: - | Q56: - | R56: - | S56: KLW 135 | T56: Kappa | U56: 240 | V56: 2450 | W56: 500 | X56: 6000 | Y56: 125 | Z56: 125 | AA56: 500 | AB56: 5.51 | AC56: 0 | AD56: 1 | AE56: 1 | AF56: 1 | AG56: 1 | AH56: 1 | AI56: 1 | AJ56: 1
A57: =IF('Kwaliteit conversie'!$D$4='Prijs karton'!C57,"X"," ") | B57: B
A58: =IF('Kwaliteit conversie'!$D$4='Prijs karton'!C58,"X"," ") | B58: B | C58: BKT13 M | D58: 0.385 | E58: 2.75 | F58: 0 | G58: 35.9 | H58: 34.5 | I58: 34.3 | J58: 34.1 | K58: 34.1 | L58: B 20 | M58: PLK 135 | N58: WS 100 | O58: - | P58: - | Q58: - | R58: - | S58: TL 120 | T58: Model | U58: 250 | V58: 2450 | W58: 600 | X58: 6000 | Y58: 290 | Z58: 145 | AA58: 200 | AB58: 5 | AC58: 0 | AD58: 1 | AE58: 1 | AF58: 1 | AG58: 1 | AH58: 1 | AI58: 1 | AJ58: 1
A59: =IF('Kwaliteit conversie'!$D$4='Prijs karton'!C59,"X"," ") | B59: B | C59: BKT14 M | D59: 0.44 | E59: 2.8 | F59: 0 | G59: 39.3 | H59: 38 | I59: 37.8 | J59: 37.5 | K59: 37.5 | L59: B 31 | M59: KL 135 | N59: WS 100 | O59: - | P59: - | Q59: - | R59: - | S59: TL 160 | T59: Model | U59: 250 | V59: 2450 | W59: 600 | X59: 6000 | Y59: 290 | Z59: 145 | AA59: 200 | AB59: 5.3 | AC59: 0 | AD59: 1 | AE59: 1 | AF59: 1 | AG59: 1 | AH59: 1 | AI59: 1 | AJ59: 1
A60: =IF('Kwaliteit conversie'!$D$4='Prijs karton'!C60,"X"," ") | B60: B | C60: BKT14WS M | D60: 0.425 | E60: 2.74 | F60: 0 | G60: 46.5 | H60: 45 | I60: 44.8 | J60: 44.5 | K60: 44.5 | L60: B 65 | M60: KLW 135 | N60: WS 100 | O60: - | P60: - | Q60: - | R60: - | S60: TL 160 | T60: Model | U60: 250 | V60: 2450 | W60: 600 | X60: 6000 | Y60: 290 | Z60: 145 | AA60: 200 | AB60: 5.21 | AC60: 0 | AD60: 1 | AE60: 1 | AF60: 1 | AG60: 1 | AH60: 1 | AI60: 1 | AJ60: 1
A61: =IF('Kwaliteit conversie'!$D$4='Prijs karton'!C61,"X"," ") | B61: B | C61: BKT19 M | D61: 0.482 | E61: 2.82 | F61: 0 | G61: 49.9 | H61: 48.4 | I61: 48.1 | J61: 47.8 | K61: 47.8 | L61: B 34 | M61: KL 186 | N61: WS 135 | O61: - | P61: - | Q61: - | R61: - | S61: TL 120 | T61: Model | U61: 250 | V61: 2450 | W61: 600 | X61: 6000 | Y61: 290 | Z61: 145 | AA61: 200 | AB61: 5.78 | AC61: 0 | AD61: 1 | AE61: 1 | AF61: 1 | AG61: 1 | AH61: 1 | AI61: 1 | AJ61: 1
A62: =IF('Kwaliteit conversie'!$D$4='Prijs karton'!C62,"X"," ") | B62: B | C62: BT12 M | D62: 0.37 | E62: 2.72 | F62: 0 | G62: 31.6 | H62: 30.4 | I62: 30.2 | J62: 29.9 | K62: 29.9 | L62: B 12 | M62: TL 120 | N62: WS 100 | O62: - | P62: - | Q62: - | R62: - | S62: TL 120 | T62: Model | U62: 250 | V62: 2450 | W62: 600 | X62: 6000 | Y62: 290 | Z62: 145 | AA62: 200 | AB62: 4.31 | AC62: 0 | AD62: 1 | AE62: 1 | AF62: 1 | AG62: 1 | AH62: 1 | AI62: 1 | AJ62: 1
A63: =IF('Kwaliteit conversie'!$D$4='Prijs karton'!C63,"X"," ") | B63: B | C63: BDUWT14 M | D63: 0.375 | E63: 2.72 | F63: 0 | G63: 40 | H63: 38.7 | I63: 38.4 | J63: 38.1 | K63: 38.1 | L63: B 61 | M63: TLW 125 | N63: WS 100 | O63: - | P63: - | Q63: - | R63: - | S63: TL 120 | T63: Model | U63: 250 | V63: 2450 | W63: 600 | X63: 6000 | Y63: 290 | Z63: 145 | AA63: 200 | AB63: 4.22 | AC63: 0 | AD63: 1 | AE63: 1 | AF63: 1 | AG63: 1 | AH63: 1 | AI63: 1 | AJ63: 1
A64: =IF('Kwaliteit conversie'!$D$4='Prijs karton'!C64,"X"," ") | B64: B | C64: BKT14WW M | D64: 0.4 | E64: 2.72 | F64: 0 | G64: 49.5 | H64: 48.1 | I64: 48 | J64: 47.7 | K64: 47.7 | L64: B 73 | M64: KLW 135 | N64: WS 100 | O64: - | P64: - | Q64: - | R64: - | S64: KLW 135 | T64: Model | U64: 250 | V64: 2450 | W64: 600 | X64: 6000 | Y64: 290 | Z64: 145 | AA64: 200 | AB64: 5.22 | AC64: 0 | AD64: 1 | AE64: 1 | AF64: 1 | AG64: 1 | AH64: 1 | AI64: 1 | AJ64: 1
A65: =IF('Kwaliteit conversie'!$D$4='Prijs karton'!C65,"X"," ") | B65: B | C65: BTS12/11 M | D65: 0.297 | E65: 2.61 | F65: 0 | G65: 28.1 | H65: 26.8 | I65: 26.5 | J65: 26.2 | K65: 26.2 | L65: B 10 | M65: WS 90 | N65: WS 90 | O65: - | P65: - | Q65: - | R65: - | S65: WS 90 | T65: Model | U65: 250 | V65: 2450 | W65: 600 | X65: 6000 | Y65: 290 | Z65: 145 | AA65: 200 | AB65: 3.06 | AC65: 0 | AD65: 1 | AE65: 1 | AF65: 1 | AG65: 1 | AH65: 1 | AI65: 1 | AJ65: 1
A66: =IF('Kwaliteit conversie'!$D$4='Prijs karton'!C66,"X"," ") | B66: B
A67: =IF('Kwaliteit conversie'!$D$4='Prijs karton'!C67,"X"," ") | B67: B
A68: =IF('Kwaliteit conversie'!$D$4='Prijs karton'!C68,"X"," ") | B68: B
A69: =IF('Kwaliteit conversie'!$D$4='Prijs karton'!C69,"X"," ") | B69: B
A70: =IF('Kwaliteit conversie'!$D$4='Prijs karton'!C70,"X"," ") | B70: B
A71: =IF('Kwaliteit conversie'!$D$4='Prijs karton'!C71,"X"," ") | B71: B
A72: =IF('Kwaliteit conversie'!$D$4='Prijs karton'!C72,"X"," ") | B72: B
A73: =IF('Kwaliteit conversie'!$D$4='Prijs karton'!C73,"X"," ") | B73: B
A74: =IF('Kwaliteit conversie'!$D$4='Prijs karton'!C74,"X"," ") | B74: B
A75: =IF('Kwaliteit conversie'!$D$4='Prijs karton'!C75,"X"," ") | B75: B
A76: =IF('Kwaliteit conversie'!$D$4='Prijs karton'!C76,"X"," ") | B76: B
A77: =IF('Kwaliteit conversie'!$D$4='Prijs karton'!C77,"X"," ") | B77: B | C77: B prijs speciaal | D77: 0.5 | E77: 2.9 | F77: 0 | G77: 0 | H77: 0 | I77: 0 | J77: 0 | K77: 0 | L77: - | M77: - | N77: - | O77: - | P77: - | Q77: - | R77: - | S77: - | T77: Pro | U77: 250 | V77: 2450 | W77: 500 | X77: 6200 | Y77: 480 | Z77: 240 | AA77: 200 | AB77: 5 | AC77: 0 | AD77: 1 | AE77: 1 | AF77: 1 | AG77: 1 | AH77: 1 | AI77: 1 | AJ77: 1
A78: =IF('Kwaliteit conversie'!$D$4='Prijs karton'!C78,"X"," ")
A79: =IF('Kwaliteit conversie'!$D$4='Prijs karton'!C79,"X"," ")
A80: =IF('Kwaliteit conversie'!$D$4='Prijs karton'!C80,"X"," ")
A81: =IF('Kwaliteit conversie'!$D$4='Prijs karton'!C81,"X"," ") | B81: BC | C81: DKT12 T2 | D81: 0.56 | E81: 5.6 | F81: 0 | G81: 57.7 | H81: 54.7 | I81: 54.2 | J81: 54.2 | K81: 53.7 | L81: 2.31 BC T2 | M81: KL135 | N81: WS 80 | O81: WS 90 | P81: WS 90 | Q81: - | R81: - | S81: TL 90 | T81: Pro | U81: 250 | V81: 2450 | W81: 500 | X81: 6200 | Y81: 180 | Z81: 90 | AA81: 200 | AB81: 6.6 | AC81: 0 | AD81: 1 | AE81: 1 | AF81: 1 | AG81: 1 | AH81: 1 | AI81: 1 | AJ81: 1
A82: =IF('Kwaliteit conversie'!$D$4='Prijs karton'!C82,"X"," ") | B82: BC | C82: DT14/12 N2 | D82: 0.54 | E82: 5.6 | F82: 0 | G82: 45.5 | H82: 42.5 | I82: 42 | J82: 42 | K82: 41.5 | L82: 2.03 BC N2 | M82: TL 115 | N82: WS 80 | O82: WS 90 | P82: WS 90 | Q82: - | R82: - | S82: TL 90 | T82: Pro | U82: 250 | V82: 2450 | W82: 500 | X82: 6200 | Y82: 180 | Z82: 90 | AA82: 200 | AB82: 6 | AC82: 10 | AD82: 1 | AE82: 1 | AF82: 1 | AG82: 1 | AH82: 1 | AI82: 1 | AJ82: 1
A83: =IF('Kwaliteit conversie'!$D$4='Prijs karton'!C83,"X"," ") | B83: BC | C83: DT14 K | D83: 0.618 | E83: 6.62 | F83: 0 | G83: 64.7 | H83: 61.7 | I83: 61.7 | J83: 59.7 | K83: 59.7 | L83: BC 914 | M83: THP 125 | N83: RF1 100 | O83: RF1 80 | P83: RF1 100 | Q83: - | R83: - | S83: THP 125 | T83: Kappa | U83: 240 | V83: 2450 | W83: 500 | X83: 6000 | Y83: 60 | Z83: 60 | AA83: 200 | AB83: 7.54 | AD83: 1 | AE83: 1 | AF83: 1 | AG83: 1 | AH83: 1 | AI83: 1 | AJ83: 1
A84: =IF('Kwaliteit conversie'!$D$4='Prijs karton'!C84,"X"," ") | B84: BC | C84: DT14 N7 | D84: 0.62 | E84: 5.6 | F84: 0 | G84: 53.9 | H84: 50.9 | I84: 50.4 | J84: 50.4 | K84: 49.9 | L84: 2.30 BC N7 | M84: TL 135 | N84: WS 80 | O84: WS 90 | P84: WS 115 | Q84: - | R84: - | S84: TL 115 | T84: Pro | U84: 250 | V84: 2450 | W84: 500 | X84: 6200 | Y84: 180 | Z84: 90 | AA84: 200 | AB84: 7.2 | AC84: 0 | AD84: 1 | AE84: 1 | AF84: 1 | AG84: 1 | AH84: 1 | AI84: 1 | AJ84: 1
A85: =IF('Kwaliteit conversie'!$D$4='Prijs karton'!C85,"X"," ") | B85: BC | C85: DT14 N2 | D85: 0.585 | E85: 5.6 | F85: 0 | G85: 47.4 | H85: 44.4 | I85: 43.9 | J85: 43.9 | K85: 43.4 | L85: 2.30 BC N2 | M85: TL 135 | N85: WS 80 | O85: WS 90 | P85: WS 90 | Q85: - | R85: - | S85: TL 115 | T85: Pro | U85: 250 | V85: 2450 | W85: 500 | X85: 6200 | Y85: 180 | Z85: 90 | AA85: 200 | AB85: 6.6 | AC85: 0 | AD85: 1 | AE85: 1 | AF85: 1 | AG85: 1 | AH85: 1 | AI85: 1 | AJ85: 1
A86: =IF('Kwaliteit conversie'!$D$4='Prijs karton'!C86,"X"," ") | B86: BC | C86: DKT12 N2 | D86: 0.57 | E86: 5.6 | F86: 0 | G86: 52.6 | H86: 49.6 | I86: 49.1 | J86: 49.1 | K86: 48.6 | L86: 2.31 BC N2 | M86: PLK 120 | N86: WS 80 | O86: WS 90 | P86: WS 90 | Q86: - | R86: - | S86: TL 115 | T86: Pro | U86: 250 | V86: 2450 | W86: 500 | X86: 6200 | Y86: 180 | Z86: 90 | AA86: 200 | AB86: 6.8 | AC86: 0 | AD86: 1 | AE86: 1 | AF86: 1 | AG86: 1 | AH86: 1 | AI86: 1 | AJ86: 1
A87: =IF('Kwaliteit conversie'!$D$4='Prijs karton'!C87,"X"," ") | B87: BC | C87: DKT13/12W N2 | D87: 0.56 | E87: 5.6 | F87: 0 | G87: 59.4 | H87: 56.4 | I87: 55.9 | J87: 55.9 | K87: 55.4 | L87: 2.35 BC N2 | M87: KLW 135 | N87: WS 80 | O87: WS 90 | P87: WS 90 | Q87: - | R87: - | S87: TL 90 | T87: Pro | U87: 250 | V87: 2450 | W87: 500 | X87: 6200 | Y87: 180 | Z87: 90 | AA87: 200 | AB87: 6.5 | AC87: 0 | AD87: 1 | AE87: 1 | AF87: 1 | AG87: 1 | AH87: 1 | AI87: 1 | AJ87: 1
A88: =IF('Kwaliteit conversie'!$D$4='Prijs karton'!C88,"X"," ") | B88: BC | C88: DKT13/12W K | D88: 0.604 | E88: 6.58 | F88: 0 | G88: - | H88: 69.1 | I88: 69.1 | J88: 68.1 | K88: 67.6 | L88: BC 966 | M88: KLW 135 | N88: WS 100 | O88: WS 80 | P88: WS 100 | Q88: - | R88: - | S88: THP 125 | T88: Kappa | U88: 240 | V88: 2450 | W88: 500 | X88: 6000 | Y88: 60 | Z88: 60 | AA88: 500 | AB88: 7.51 | AD88: 1 | AE88: 1 | AF88: 1 | AG88: 1 | AH88: 1 | AI88: 1 | AJ88: 1
A89: =IF('Kwaliteit conversie'!$D$4='Prijs karton'!C89,"X"," ") | B89: BC | C89: DKT14 N2 | D89: 0.645 | E89: 5.6 | F89: 0 | G89: 56.4 | H89: 53.4 | I89: 52.9 | J89: 52.9 | K89: 52.4 | L89: 2.40 BC N2 | M89: PLK 140 | N89: WS 80 | O89: WS 90 | P89: WS 115 | Q89: - | R89: - | S89: TL 135 | T89: Pro | U89: 250 | V89: 2450 | W89: 500 | X89: 6200 | Y89: 180 | Z89: 90 | AA89: 200 | AB89: 8.1 | AC89: 10 | AD89: 1 | AE89: 1 | AF89: 1 | AG89: 1 | AH89: 1 | AI89: 1 | AJ89: 1
A90: =IF('Kwaliteit conversie'!$D$4='Prijs karton'!C90,"X"," ") | B90: BC | C90: DKT14 N2 K | D90: 0.589 | E90: 6.59 | F90: 0 | G90: 67.2 | H90: 64.2 | I90: 64.2 | J90: 63.7 | K90: 63.2 | L90: BC 92242 | M90: KL 110 | N90: WS 100 | O90: WS 80 | P90: WS 100 | Q90: - | R90: - | S90: THP 125 | T90: Kappa | U90: 240 | V90: 2450 | W90: 500 | X90: 6000 | Y90: 60 | Z90: 60 | AA90: 200 | AB90: 7.35 | AC90: 0 | AD90: 1 | AE90: 1 | AF90: 1 | AG90: 1 | AH90: 1 | AI90: 1 | AJ90: 1
A91: =IF('Kwaliteit conversie'!$D$4='Prijs karton'!C91,"X"," ") | B91: BC | AC91: 0
A92: =IF('Kwaliteit conversie'!$D$4='Prijs karton'!C92,"X"," ") | B92: BC | C92: DKT14 K | D92: 0.614 | E92: 6.62 | F92: 0 | G92: 72.2 | H92: 69.2 | I92: 69.2 | J92: 67.2 | K92: 67.2 | L92: BC 922 | M92: KL 135 | N92: WS 100 | O92: WS 80 | P92: WS 100 | Q92: - | R92: - | S92: THP 125 | T92: Kappa | U92: 240 | V92: 2450 | W92: 500 | X92: 6000 | Y92: 60 | Z92: 60 | AA92: 200 | AB92: 7.7 | AC92: 0 | AD92: 1 | AE92: 1 | AF92: 1 | AG92: 1 | AH92: 1 | AI92: 1 | AJ92: 1
A93: =IF('Kwaliteit conversie'!$D$4='Prijs karton'!C93,"X"," ") | B93: BC | C93: DKT14K N1 | D93: 0.665 | E93: 5.7 | F93: 0 | G93: 63.4 | H93: 60.4 | I93: 59.9 | J93: 59.9 | K93: 59.4 | L93: 2.41 BC N1 | M93: KL 135 | N93: WS 80 | O93: WS 90 | P93: WS 135 | Q93: - | R93: - | S93: TL 135 | T93: Pro | U93: 250 | V93: 2450 | W93: 500 | X93: 6200 | Y93: 180 | Z93: 90 | AA93: 200 | AB93: 8.1 | AC93: 0 | AD93: 1 | AE93: 1 | AF93: 1 | AG93: 1 | AH93: 1 | AI93: 1 | AJ93: 1
A94: =IF('Kwaliteit conversie'!$D$4='Prijs karton'!C94,"X"," ") | B94: BC | C94: DKT19 K | D94: 0.699 | E94: 6.75 | F94: 0 | G94: 77.9 | H94: 74.9 | I94: 74.9 | J94: 72.9 | K94: 72.9 | L94: BC 932 | M94: KL 170 | N94: WS 100 | O94: WS 80 | P94: WS 100 | Q94: - | R94: - | S94: THP 150 | T94: Kappa | U94: 240 | V94: 2450 | W94: 500 | X94: 6000 | Y94: 60 | Z94: 60 | AA94: 200 | AB94: 8.49 | AD94: 1 | AE94: 1 | AF94: 1 | AG94: 1 | AH94: 1 | AI94: 1 | AJ94: 1
A95: =IF('Kwaliteit conversie'!$D$4='Prijs karton'!C95,"X"," ") | B95: BC | C95: DKT19 N2 | D95: 0.685 | E95: 5.7 | F95: 0 | G95: 66.7 | H95: 63.7 | I95: 63.2 | J95: 63.2 | K95: 62.7 | L95: 2.50 BC N2 | M95: PLK 175 | N95: WS 80 | O95: WS 90 | P95: WS 115 | Q95: - | R95: - | S95: PLK 140 | T95: Pro | U95: 250 | V95: 2450 | W95: 500 | X95: 6200 | Y95: 180 | Z95: 90 | AA95: 200 | AB95: 9 | AC95: 0 | AD95: 1 | AE95: 1 | AF95: 1 | AG95: 1 | AH95: 1 | AI95: 1 | AJ95: 1
A96: =IF('Kwaliteit conversie'!$D$4='Prijs karton'!C96,"X"," ") | B96: BC
A97: =IF('Kwaliteit conversie'!$D$4='Prijs karton'!C97,"X"," ") | B97: BC | C97: DKT19K N1 | D97: 0.71 | E97: 5.7 | F97: 0 | G97: 73 | H97: 70 | I97: 69.5 | J97: 69.5 | K97: 69 | L97: 2.51 BC N1 | M97: KL 175 | N97: WS 80 | O97: WS 90 | P97: WS 135 | Q97: - | R97: - | S97: PLK 140 | T97: Pro | U97: 250 | V97: 2450 | W97: 500 | X97: 6200 | Y97: 180 | Z97: 90 | AA97: 200 | AB97: 9.1 | AC97: 0 | AD97: 1 | AE97: 1 | AF97: 1 | AG97: 1 | AH97: 1 | AI97: 1 | AJ97: 1
A98: =IF('Kwaliteit conversie'!$D$4='Prijs karton'!C98,"X"," ") | B98: BC | C98: DK19X N1 | D98: 0.745 | E98: 5.7 | F98: 0 | G98: 75.6 | H98: 72.6 | I98: 72.1 | J98: 72.1 | K98: 71.6 | L98: 2.60 BC N1 | M98: PLK 175 | N98: WS 80 | O98: WS 90 | P98: WS 135 | Q98: - | R98: - | S98: PLK 175 | T98: Pro | U98: 250 | V98: 2450 | W98: 500 | X98: 6200 | Y98: 180 | Z98: 90 | AA98: 200 | AB98: 9.6 | AC98: 0 | AD98: 1 | AE98: 1 | AF98: 1 | AG98: 1 | AH98: 1 | AI98: 1 | AJ98: 1
A99: =IF('Kwaliteit conversie'!$D$4='Prijs karton'!C99,"X"," ") | B99: BC | C99: DK19 N1 | D99: 0.745 | E99: 5.8 | F99: 0 | G99: 75.9 | H99: 72.9 | I99: 72.4 | J99: 72.4 | K99: 71.9 | L99: 2.61 BC N1 | M99: KL 175 | N99: WS 80 | O99: WS 90 | P99: WS 135 | Q99: - | R99: - | S99: KL 175 | T99: Pro | U99: 250 | V99: 2450 | W99: 500 | X99: 6200 | Y99: 180 | Z99: 90 | AA99: 200 | AB99: 9.3 | AC99: 10 | AD99: 1 | AE99: 1 | AF99: 1 | AG99: 1 | AH99: 1 | AI99: 1 | AJ99: 1
A100: =IF('Kwaliteit conversie'!$D$4='Prijs karton'!C100,"X"," ") | B100: BC | C100: DK19FP K | D100: 0.784 | E100: 6.86 | F100: 0 | G100: 91.9 | H100: 88.9 | I100: 88.9 | J100: 86.9 | K100: 86.9 | L100: BC 950 | M100: KL 170 | N100: WS 100 | O100: THP 150 | P100: WS 100 | Q100: - | R100: - | S100: KL 170 | T100: Kappa | U100: 240 | V100: 2450 | W100: 500 | X100: 6000 | Y100: 60 | Z100: 60 | AA100: 200 | AB100: 9.71 | AC100: 0 | AD100: 1 | AE100: 1 | AF100: 1 | AG100: 1 | AH100: 1 | AI100: 1 | AJ100: 1
A101: =IF('Kwaliteit conversie'!$D$4='Prijs karton'!C101,"X"," ") | B101: BC
A102: =IF('Kwaliteit conversie'!$D$4='Prijs karton'!C102,"X"," ") | B102: BC | C102: DK19F N1 | D102: 0.85 | E102: 5.9 | F102: 0 | G102: 78.3 | H102: 75.3 | I102: 74.8 | J102: 74.8 | K102: 74.3 | L102: 2.71 BC N1 | M102: KL 175 | N102: WS 135 | O102: TL 115 | P102: PMS 140 | Q102: - | R102: - | S102: KL 175 | T102: Pro | U102: 250 | V102: 2450 | W102: 500 | X102: 6200 | Y102: 180 | Z102: 90 | AA102: 200 | AB102: 10.9 | AC102: 10 | AD102: 1 | AE102: 1 | AF102: 1 | AG102: 1 | AH102: 1 | AI102: 1 | AJ102: 1
...

Sheet Marge tabel
H1: 0 | J1: 0.01 | K1: Oude instelling
H2: -0.06 | J2: -0.04 | K2: Instelling SD
E3: =IF(OR(Rekenblad!E362=1,Rekenblad!F362=1),1,0) -> 1 | F3: =IF(E3=1,0,1) -> 0
C4: Order bedrag | E4: Marge Emba | F4: Marge Overige | H4: Correctie | I4: Basis | J4: Correctie
C5: tussen | E5: % | F5: % | H5: Marge Emba | I5: marge | J5: Overige
B6: =IF(AND($B$73>C6,$B$73<=D6),1,"") | C6: 1 | D6: 25 | E6: =I6+H6 -> 0.74 | F6: =J6+I6 -> 0.75 | H6: -0.06 | I6: 0.8 | J6: -0.05
B7: =IF(AND($B$73>C7,$B$73<=D7),1,"") | C7: 25 | D7: 50 | E7: =I7+H7 -> 0.34 | F7: =J7+I7 -> 0.35 | H7: -0.06 | I7: 0.4 | J7: -0.05
B8: =IF(AND($B$73>C8,$B$73<=D8),1,"") | C8: 50 | D8: 55 | E8: =I8+H8 -> 0.31 | F8: =J8+I8 -> 0.32 | H8: -0.06 | I8: 0.37 | J8: -0.05
B9: =IF(AND($B$73>C9,$B$73<=D9),1,"") | C9: 55 | D9: 60 | E9: =I9+H9 -> 0.29 | F9: =J9+I9 -> 0.3 | H9: -0.06 | I9: 0.35 | J9: -0.05
B10: =IF(AND($B$73>C10,$B$73<=D10),1,"") | C10: 60 | D10: 65 | E10: =I10+H10 -> 0.23 | F10: =J10+I10 -> 0.24 | H10: -0.06 | I10: 0.29 | J10: -0.05
B11: =IF(AND($B$73>C11,$B$73<=D11),1,"") | C11: 65 | D11: 70 | E11: =I11+H11 -> 0.22 | F11: =J11+I11 -> 0.23 | H11: -0.06 | I11: 0.28 | J11: -0.05
B12: =IF(AND($B$73>C12,$B$73<=D12),1,"") | C12: 70 | D12: 75 | E12: =I12+H12 -> 0.21 | F12: =J12+I12 -> 0.22 | H12: -0.06 | I12: 0.27 | J12: -0.05
B13: =IF(AND($B$73>C13,$B$73<=D13),1,"") | C13: 75 | D13: 80 | E13: =I13+H13 -> 0.2 | F13: =J13+I13 -> 0.21 | H13: -0.06 | I13: 0.26 | J13: -0.05
B14: =IF(AND($B$73>C14,$B$73<=D14),1,"") | C14: 80 | D14: 85 | E14: =I14+H14 -> 0.19 | F14: =J14+I14 -> 0.2 | H14: -0.06 | I14: 0.25 | J14: -0.05
B15: =IF(AND($B$73>C15,$B$73<=D15),1,"") | C15: 85 | D15: 90 | E15: =I15+H15 -> 0.18 | F15: =J15+I15 -> 0.19 | H15: -0.06 | I15: 0.24 | J15: -0.05
B16: =IF(AND($B$73>C16,$B$73<=D16),1,"") | C16: 90 | D16: 95 | E16: =I16+H16 -> 0.17 | F16: =J16+I16 -> 0.18 | H16: -0.06 | I16: 0.23 | J16: -0.05
B17: =IF(AND($B$73>C17,$B$73<=D17),1,"") | C17: 95 | D17: 100 | E17: =I17+H17 -> 0.16 | F17: =J17+I17 -> 0.17 | H17: -0.06 | I17: 0.22 | J17: -0.05
... B65: =IF(AND($B$73>C65,$B$73<=D65),1,"") | C65: 8000 | D65: 1000000 | E65: =I65+H65 -> 0.03 | F65: =J65+I65 -> 0.04 | H65: -0.06 | I65: 0.09 | J65: -0.05
E66: =VLOOKUP(1,B6:F65,4,FALSE) -> 0.095 | F66: =VLOOKUP(1,B6:F65,5,FALSE) -> 0.105
E68: Wellicht nog vullen
D69: 1 | F69: =Rekenblad!J372 -> 0 | G69: =Rekenblad!J373 -> 0 | H69: =H79 -> 0 | I69: =IF(AND(Rekenblad!C2=Rekenblad!B50,Rekenblad!J365=1),1,IF(AND(Rekenblad!C2=Rekenblad!B50,Rekenblad!J369=1),1,0)) -> 0 | J69: =C83 -> 0 | K69: =IF(AND(Rekenblad!F347=1,U93=1,J69=0),1,0) -> 0 | L69: 0 | M69: 0 | N69: 0
B70: Kosten totaal | C70: Basis marge | D70: Extra marge | E70: Extra marge | F70: Extra marge | G70: Extra marge | H70: Kleine doos | I70: Plaatjes | J70: Kokerdozen | K70: Plaatformaat | O70: Totaal
D71: Fefco | E71: Kokerdoos | F71: Stapelen | G71: Bundelen | H71: Emba 170 | I71: Mini / roda | J71: Emba 295 | K71: Emba 295 | O71: Marge
C72: =IF(SUM(B6:B65)>0,HLOOKUP(1,E3:F66,64,FALSE),0) -> 0.095 | D72: =Rekenblad!AU46 -> 0 | E72: 0.03 | F72: 0.03 | G72: 0.03 | H72: 0.1 | I72: 0.08 | J72: =D85*H107 -> 0 | K72: =HLOOKUP(1,Q97:AI100,4,FALSE) -> 0.07
B73: =Rekenblad!C1085 -> 191.28173 | C73: =B73*C72 -> 18.171765 | D73: =IF(D72>0,D72*B73*D69,0) -> 0 | E73: =IF(E72>0,E72*B73*E69,0) -> 0 | F73: =IF(F72>0,F72*B73*F69,0) -> 0 | G73: =IF(G72>0,G72*B73*G69,0) -> 0 | H73: =IF(H72>0,H72*B73*H69,0) -> 0 | I73: =IF(I72>0,I72*B73*I69,0) -> 0 | J73: =IF(J72>0,J72*B73*J69,0) -> 0 | K73: =IF(K72>0,K72*B73*K69,0) -> 0 | L73: =IF(L72>0,L72*B73*L69,0) -> 0 | M73: =IF(M72>0,M72*B73*M69,0) -> 0 | N73: =IF(N72>0,N72*B73*N69,0) -> 0 | O73: =SUM(C73:N73) -> 18.171765
C76: =Rekenblad!B228 -> 361 | D76: =Rekenblad!C228 -> 1150 | E76: 0 | F76: =Rekenblad!C7 -> 250
C77: Plaathoogte < dan | D77: Plaatlengte < dan | E77: Formaat | F77: Breedte < dan | G77: Productie | H77: Klein formaat
C78: 280 | D78: 690 | E78: Klein | F78: 125 | G78: Emba 170 | H78: Emba 170
B79: Kleine doos Emba 170 | C79: =IF(C76<C78,1,0) -> 0 | D79: =IF(D76<D78,1,0) -> 0 | E79: =IF(SUM(C79:D79)=E76,0,1) -> 0 | F79: =IF(F76<F78,1,0) -> 0 | G79: =Rekenblad!J367 -> 1 | H79: =IF(AND(G79=1,SUM(E79:F79)>1),1,0) -> 0
B82: Tabel Kokerdoos Emba 295
B83: Koker / plaat bepalen | C83: =IF(AND(Rekenblad!F347,Rekenblad!AA46=1,SUM(B86:B100)+SUM(E83:N83)=2),1,0) -> 0 | D83: =IF(AND(SUM(B86:B100)=1,SUM(E83:N83)=1),HLOOKUP(1,E83:N101,19,FALSE),0) -> 0 | E83: =IF(AND($C$85>E84,$C$85<=E85),1," ") | F83: =IF(AND($C$85>F84,$C$85<=F85),1," ") | G83: =IF(AND($C$85>G84,$C$85<=G85),1," ") | H83: =IF(AND($C$85>H84,$C$85<=H85),1," ") | I83: =IF(AND($C$85>I84,$C$85<=I85),1," ") | J83: =IF(AND($C$85>J84,$C$85<=J85),1," ") -> 1 | K83: =IF(AND($C$85>K84,$C$85<=K85),1," ") | L83: =IF(AND($C$85>L84,$C$85<=L85),1," ") | ... N83: =IF(AND($C$85>N84,$C$85<=N85),1," ") | Q83: Factor | R83: =HLOOKUP(1,R84:AJ87,4,FALSE) -> 1
B84: Breedte plaat | C84: =Rekenblad!C645 -> 361 | D84: =R83 -> 1 | E84: 0 | F84: 700 | G84: 800 | H84: 900 | I84: 1000 | J84: 1100 | K84: 1200 | L84: 1300 | M84: 1450 | N84: 1600 | Q84: Selecte | R84: =IF(AND($Q$86>=R85,$Q$86<R86),1,0) -> 1 | S84: =IF(AND($Q$86>=S85,$Q$86<S86),1,0) -> 0 | T84: =IF(AND($Q$86>=T85,$Q$86<T86),1,0) -> 0 | U84: =IF(AND($Q$86>=U85,$Q$86<U86),1,0) -> 0 | V84: =IF(AND($Q$86>=V85,$Q$86<V86),1,0) -> 0 | W84: =IF(AND($Q$86>=W85,$Q$86<W86),1,0) -> 0 | X84: =IF(AND($Q$86>=X85,$Q$86<X86),1,0) -> 0 | Y84: =IF(AND($Q$86>=Y85,$Q$86<Y86),1,0) -> 0 | ... AJ84: =IF(AND($Q$86>=AJ85,$Q$86<AJ86),1,0) -> 0
B85: Lengte plaat | C85: =Rekenblad!C646 -> 1150 | D85: =D83*D84 -> 0 | E85: 700 | F85: 800 | G85: 900 | H85: 1000 | I85: 1100 | J85: 1200 | K85: 1300 | L85: 1450 | M85: 1600 | N85: 1700 | Q85: M2 | R85: 0 | S85: 200 | T85: 500 | U85: 750 | V85: 1000 | W85: 1250 | X85: 1500 | Y85: 1750 | Z85: 2000 | AA85: 2250 | AB85: 2500 | AC85: 2750 | AD85: 3000 | AE85: 3500 | AF85: 4000 | AG85: 5000 | AH85: 6000 | AI85: 8000 | AJ85: 10000
B86: =IF(AND($C$84>C86,$C$84<=D86),1," ") -> 1 | C86: 0 | D86: 400 | E86: 0 | F86: 0 | G86: 0 | H86: 0 | I86: 0 | J86: 0 | K86: 0 | L86: 0 | M86: 0 | N86: 0 | Q86: =Rekenblad!I108 -> 160.8616 | R86: 200 | S86: 500 | T86: 750 | U86: 1000 | V86: 1250 | W86: 1500 | X86: 1750 | Y86: 2000 | Z86: 2250 | AA86: 2500 | AB86: 2750 | AC86: 3000 | AD86: 3500 | AE86: 4000 | AF86: 5000 | AG86: 6000 | AH86: 8000 | AI86: 10000 | AJ86: 99999999
B87: =IF(AND($C$84>C87,$C$84<=D87),1," ") | C87: 400 | D87: 450 | E87: 0.03 | F87: 0 | G87: 0 | H87: 0 | I87: 0 | J87: 0 | K87: 0 | L87: 0 | M87: 0 | N87: 0 | Q87: Factor | R87: 1 | S87: 1 | T87: 1 | U87: 1 | V87: 1 | W87: 1 | X87: 1 | Y87: 1 | Z87: 1 | AA87: 1 | AB87: 0.9 | AC87: 0.8 | AD87: 0.7 | AE87: 0.6 | AF87: 0.6 | AG87: 0.6 | AH87: 0.6 | AI87: 0.6 | AJ87: 0.6
B88: =IF(AND($C$84>C88,$C$84<=D88),1," ") | C88: 450 | D88: 500 | E88: 0.05 | F88: 0.03 | G88: 0 | H88: 0 | I88: 0 | J88: 0 | K88: 0 | L88: 0 | M88: 0 | N88: 0
B89: =IF(AND($C$84>C89,$C$84<=D89),1," ") | C89: 500 | D89: 550 | E89: 0.05 | F89: 0.05 | G89: 0.03 | H89: 0.02 | I89: 0.01 | J89: 0 | K89: 0 | L89: 0 | M89: 0 | N89: 0
B90: =IF(AND($C$84>C90,$C$84<=D90),1," ") | C90: 550 | D90: 600 | E90: 0.1 | F90: 0.08 | G90: 0.05 | H90: 0.03 | I90: 0.02 | J90: 0.01 | K90: 0 | L90: 0 | M90: 0 | N90: 0
B91: =IF(AND($C$84>C91,$C$84<=D91),1," ") | C91: 600 | D91: 700 | E91: 0.15 | F91: 0.1 | G91: 0.08 | H91: 0.06 | I91: 0.04 | J91: 0.02 | K91: 0.02 | L91: 0.01 | M91: 0 | N91: 0 | Q91: Plaat t.b.v. extra marge
B92: =IF(AND($C$84>C92,$C$84<=D92),1," ") | C92: 700 | D92: 800 | E92: 0.16 | F92: 0.13 | G92: 0.12 | H92: 0.08 | I92: 0.06 | J92: 0.04 | K92: 0.03 | L92: 0.02 | M92: 0.01 | N92: 0 | Q92: Hoogte | R92: Lengte | S92: =C84 -> 361 | T92: =C85 -> 1150 | U92: selectie | V92: Instelling
B93: =IF(AND($C$84>C93,$C$84<=D93),1," ") | C93: 800 | D93: 900 | E93: 0.17 | F93: 0.15 | G93: 0.13 | H93: 0.1 | I93: 0.08 | J93: 0.06 | K93: 0.04 | L93: 0.03 | M93: 0.02 | N93: 0.01 | Q93: 1100 | R93: 2420 | S93: =IF(S92>Q93,1,0) -> 0 | T93: =IF(T92>R93,1,0) -> 0 | U93: =IF(SUM(S93:T93)>0,1,0) -> 0 | V93: 0.07
B94: =IF(AND($C$84>C94,$C$84<=D94),1," ") | C94: 900 | D94: 1000 | E94: 0.18 | F94: 0.16 | G94: 0.14 | H94: 0.12 | I94: 0.1 | J94: 0.08 | K94: 0.06 | L94: 0.05 | M94: 0.03 | N94: 0.03
B95: =IF(AND($C$84>C95,$C$84<=D95),1," ") | C95: 1000 | D95: 1150 | E95: 0.2 | F95: 0.2 | G95: 0.16 | H95: 0.14 | I95: 0.12 | J95: 0.1 | K95: 0.08 | L95: 0.07 | M95: 0.05 | N95: 0.04
B96: =IF(AND($C$84>C96,$C$84<=D96),1," ") | C96: 1150 | D96: 1300 | E96: 0.2 | F96: 0.2 | G96: 0.18 | H96: 0.16 | I96: 0.14 | J96: 0.12 | K96: 0.1 | L96: 0.09 | M96: 0.07 | N96: 0.06 | Q96: 1 | R96: 1 | S96: 1 | T96: 1 | U96: 1 | V96: 1 | W96: 1 | X96: 1 | Y96: 1 | Z96: 0.7 | AA96: 0.3 | AB96: 0 | AC96: 0 | AD96: 0 | AE96: 0 | AF96: 0 | AG96: 0 | AH96: 0 | AI96: 0
B97: =IF(AND($C$84>C97,$C$84<=D97),1," ") | C97: 1300 | D97: 1450 | E97: 0.2 | F97: 0.2 | G97: 0.2 | H97: 0.18 | I97: 0.16 | J97: 0.16 | K97: 0.12 | L97: 0.11 | M97: 0.09 | N97: 0.08 | Q97: =IF(AND($Q$86>=Q98,$Q$86<Q99),1,0) -> 1 | R97: =IF(AND($Q$86>=R98,$Q$86<R99),1,0) -> 0 | S97: =IF(AND($Q$86>=S98,$Q$86<S99),1,0) -> 0 | T97: =IF(AND($Q$86>=T98,$Q$86<T99),1,0) -> 0 | U97: =IF(AND($Q$86>=U98,$Q$86<U99),1,0) -> 0 | V97: =IF(AND($Q$86>=V98,$Q$86<V99),1,0) -> 0 | W97: =IF(AND($Q$86>=W98,$Q$86<W99),1,0) -> 0 | X97: =IF(AND($Q$86>=X98,$Q$86<X99),1,0) -> 0 | ... AI97: =IF(AND($Q$86>=AI98,$Q$86<AI99),1,0) -> 0
B98: =IF(AND($C$84>C98,$C$84<=D98),1," ") | C98: 1450 | D98: 1600 | E98: 0.2 | F98: 0.2 | G98: 0.2 | H98: 0.2 | I98: 0.2 | J98: 0.18 | K98: 0.16 | L98: 0.13 | M98: 0.11 | N98: 0.1 | Q98: 0 | R98: 200 | S98: 500 | T98: 750 | U98: 1000 | V98: 1250 | W98: 1500 | X98: 1750 | Y98: 2000 | Z98: 2250 | AA98: 2500 | AB98: 2750 | AC98: 3000 | AD98: 3500 | AE98: 4000 | AF98: 5000 | AG98: 6000 | AH98: 8000 | AI98: 10000
B99: =IF(AND($C$84>C99,$C$84<=D99),1," ") | C99: 1600 | D99: 1750 | E99: 0.25 | F99: 0.25 | G99: 0.25 | H99: 0.25 | I99: 0.25 | J99: 0.22 | K99: 0.2 | L99: 0.17 | M99: 0.14 | N99: 0.13 | Q99: 200 | R99: 500 | S99: 750 | T99: 1000 | U99: 1250 | V99: 1500 | W99: 1750 | X99: 2000 | Y99: 2250 | Z99: 2500 | AA99: 2750 | AB99: 3000 | AC99: 3500 | AD99: 4000 | AE99: 5000 | AF99: 6000 | AG99: 8000 | AH99: 10000 | AI99: 99999999
B100: =IF(AND($C$84>C100,$C$84<=D100),1," ") | C100: 1750 | D100: 9999 | E100: 0.25 | F100: 0.25 | G100: 0.25 | H100: 0.25 | I100: 0.25 | J100: 0.25 | K100: 0.25 | L100: 0.2 | M100: 0.18 | N100: 0.16 | Q100: =$V$93*Q96 -> 0.07 | R100: =$V$93*R96 -> 0.07 | S100: =$V$93*S96 -> 0.07 | T100: =$V$93*T96 -> 0.07 | U100: =$V$93*U96 -> 0.07 | V100: =$V$93*V96 -> 0.07 | W100: =$V$93*W96 -> 0.07 | X100: =$V$93*X96 -> 0.07 | ... AI100: =$V$93*AI96 -> 0
E101: =IF(SUM($B$86:$B$100)=1,VLOOKUP(1,$B$86:$N$100,4,FALSE),0) -> 0 | F101: =IF(SUM($B$86:$B$100)=1,VLOOKUP(1,$B$86:$N$100,5,FALSE),0) -> 0 | G101: =IF(SUM($B$86:$B$100)=1,VLOOKUP(1,$B$86:$N$100,6,FALSE),0) -> 0 | H101: =IF(SUM($B$86:$B$100)=1,VLOOKUP(1,$B$86:$N$100,7,FALSE),0) -> 0 | I101: =IF(SUM($B$86:$B$100)=1,VLOOKUP(1,$B$86:$N$100,8,FALSE),0) -> 0 | J101: =IF(SUM($B$86:$B$100)=1,VLOOKUP(1,$B$86:$N$100,9,FALSE),0) -> 0 | K101: =IF(SUM($B$86:$B$100)=1,VLOOKUP(1,$B$86:$N$100,10,FALSE),0) -> 0 | L101: =IF(SUM($B$86:$B$100)=1,VLOOKUP(1,$B$86:$N$100,11,FALSE),0) -> 0 | M101: =IF(SUM($B$86:$B$100)=1,VLOOKUP(1,$B$86:$N$100,12,FALSE),0) -> 0 | N101: =IF(SUM($B$86:$B$100)=1,VLOOKUP(1,$B$86:$N$100,13,FALSE),0) -> 0
B104: =IF(AND($C$85>B105,$C$85<=B106),1," ") | C104: =IF(AND($C$85>C105,$C$85<=C106),1," ") | D104: =IF(AND($C$85>D105,$C$85<=D106),1," ") | E104: =IF(AND($C$85>E105,$C$85<=E106),1," ") | F104: =IF(AND($C$85>F105,$C$85<=F106),1," ") | G104: =IF(AND($C$85>G105,$C$85<=G106),1," ") -> 1
B105: 0 | C105: 800 | D105: 850 | E105: 900 | F105: 950 | G105: 1000
B106: 800 | C106: 850 | D106: 900 | E106: 950 | F106: 1000 | G106: 9999999
B107: 1 | C107: 0.8 | D107: 0.6 | E107: 0.4 | F107: 0.2 | G107: 0 | H107: =IF(SUM(B104:G104)>0,HLOOKUP(1,B104:G107,4,FALSE),0) -> 0

Sheet Pallet en transport
C1: Palletstapeling berekenen | D1: =IF(SUM(Rekenblad!C362:I362)=0,0,1) -> 1
C3: Breedte product t.b.v. transport | D3: =Rekenblad!F108 -> 361 | E3: mm
C4: Lengte product t.b.v. transport | D4: =Rekenblad!G108 -> 557 | E4: mm
C5: M2 per product | D5: =(D3/1000)*(D4/1000) -> 0.201077 | E5: m2
C7: B | D7: L
C8: =IF(AND($D$3>E8,$D$3<=F8),1,0) -> 0 | D8: =IF(AND($D$4>E8,$D$4<=F8),1,0) -> 0 | E8: 0 | F8: 100 | G8: 30
C9: =IF(AND($D$3>E9,$D$3<=F9),1,0) -> 0 | D9: =IF(AND($D$4>E9,$D$4<=F9),1,0) -> 0 | E9: 100 | F9: 200 | G9: 40
C10: =IF(AND($D$3>E10,$D$3<=F10),1,0) -> 0 | D10: =IF(AND($D$4>E10,$D$4<=F10),1,0) -> 0 | E10: 200 | F10: 300 | G10: 50
C11: =IF(AND($D$3>E11,$D$3<=F11),1,0) -> 1 | D11: =IF(AND($D$4>E11,$D$4<=F11),1,0) -> 0 | E11: 300 | F11: 400 | G11: 60
C12: =IF(AND($D$3>E12,$D$3<=F12),1,0) -> 0 | D12: =IF(AND($D$4>E12,$D$4<=F12),1,0) -> 0 | E12: 400 | F12: 500 | G12: 70
C13: =IF(AND($D$3>E13,$D$3<=F13),1,0) -> 0 | D13: =IF(AND($D$4>E13,$D$4<=F13),1,0) -> 1 | E13: 500 | F13: 600 | G13: 80
C14: =IF(AND($D$3>E14,$D$3<=F14),1,0) -> 0 | D14: =IF(AND($D$4>E14,$D$4<=F14),1,0) -> 0 | E14: 600 | F14: 700 | G14: 100
C15: =IF(AND($D$3>E15,$D$3<=F15),1,0) -> 0 | D15: =IF(AND($D$4>E15,$D$4<=F15),1,0) -> 0 | E15: 700 | F15: 800 | G15: 120
C16: =IF(AND($D$3>E16,$D$3<=F16),1,0) -> 0 | D16: =IF(AND($D$4>E16,$D$4<=F16),1,0) -> 0 | E16: 800 | F16: 900 | G16: 140
C17: =IF(AND($D$3>E17,$D$3<=F17),1,0) -> 0 | D17: =IF(AND($D$4>E17,$D$4<=F17),1,0) -> 0 | E17: 900 | F17: 1000 | G17: 160
C18: =IF(AND($D$3>E18,$D$3<=F18),1,0) -> 0 | D18: =IF(AND($D$4>E18,$D$4<=F18),1,0) -> 0 | E18: 1000 | F18: 1200 | G18: 180
C19: =IF(AND($D$3>E19,$D$3<=F19),1,0) -> 0 | D19: =IF(AND($D$4>E19,$D$4<=F19),1,0) -> 0 | E19: 1200 | F19: 1400 | G19: 190
... C23: =IF(AND($D$3>E23,$D$3<=F23),1,0) -> 0 | D23: =IF(AND($D$4>E23,$D$4<=F23),1,0) -> 0 | E23: 2000 | F23: 99999 | G23: 240
C24: =VLOOKUP(1,C8:G23,5,FALSE) -> 60 | D24: =VLOOKUP(1,D8:G23,4,FALSE) -> 80
E28: 1 | F28: 2 | G28: 3 | H28: 4 | I28: 5 | J28: 6 | K28: 7 | L28: 8 | M28: 9 | N28: 10 | O28: 11 | P28: 12 | Q28: 13 | R28: 14 | S28: 15 | T28: 16 | U28: 17 | V28: 18 | W28: 19 | X28: 20 | Y28: 21 | Z28: 22 | AA28: 23 | AB28: 24 | AC28: 25
C29: Pallet selectie | D29: Pallet | E29: Formaat | F29: Aantal | G29: Pallet | H29: Pallet | I29: Pallet | J29: Pallet | L29: L over L | M29: Afgerond | N29: Factor | O29: Oversteek | P29: Max | Q29: Aantal | S29: B over B | T29: Afgerond | U29: Factor | V29: Oversteek | W29: Max | X29: Aantal | Z29: Stapels | AA29: m2 | AB29: m2 per | AC29: Pallet
C30: =MAX(C31:C69) -> 39 | D30: groep | E30: nummer | F30: pallets | G30: lengte | H30: breedte | I30: 800x1200 | J30: 1000x1200 | P30: Oversteek | Q30: stapels | W30: Oversteek | X30: stapels | Z30: Pallet | AA30: karton | AB30: pallet | AC30: vulling
C31: =IF(Z31>0,1,0) -> 1 | D31: 10 | E31: 1 | F31: 1 | G31: 1200 | H31: 800 | I31: 1 | J31: 0 | L31: =G31/$D$4 -> 2.1543986 | M31: =FLOOR(L31,1) -> 2 | N31: =(1-(L31-M31)) -> 0.84560144 | O31: =$D$4-((L31-M31)*$D$4) -> 471 | P31: =$D$24*2 -> 160 | Q31: =IF(P31>=O31,M31+1,M31) -> 2 | S31: =H31/$D$3 -> 2.2160665 | T31: =FLOOR(S31,1) -> 2 | U31: =(1-(S31-T31)) -> 0.78393352 | V31: =$D$3-((S31-T31)*$D$3) -> 283 | W31: =$C$24*2 -> 120 | X31: =IF(W31>=V31,T31+1,T31) -> 2 | Z31: =Q31*X31 -> 4 | AA31: =Z31*$D$5 -> 0.804308 | AB31: =(G31/1000)*(H31/1000) -> 0.96 | AC31: =IF(Z31>0,AA31/AB31,0) -> 0.83782083
C32: =IF(Z32>0,MAX(C31)+1,0) -> 2 | D32: 20 | E32: 2 | F32: 1 | G32: 1200 | H32: 1000 | I32: 0 | J32: 1 | L32: =G32/$D$4 -> 2.1543986 | M32: =FLOOR(L32,1) -> 2 | N32: =(1-(L32-M32)) -> 0.84560144 | O32: =$D$4-((L32-M32)*$D$4) -> 471 | P32: =$D$24*2 -> 160 | Q32: =IF(P32>=O32,M32+1,M32) -> 2 | S32: =H32/$D$3 -> 2.7700831 | T32: =FLOOR(S32,1) -> 2 | U32: =(1-(S32-T32)) -> 0.2299169 | V32: =$D$3-((S32-T32)*$D$3) -> 83 | W32: =$C$24*2 -> 120 | X32: =IF(W32>=V32,T32+1,T32) -> 3 | Z32: =Q32*X32 -> 6 | AA32: =Z32*$D$5 -> 1.206462 | AB32: =(G32/1000)*(H32/1000) -> 1.2 | AC32: =IF(Z32>0,AA32/AB32,0) -> 1.005385
C33: =IF(Z33>0,MAX(C31:C32)+1,0) -> 3 | D33: 10 | E33: 3 | F33: 2 | G33: 1600 | H33: 1200 | I33: 2 | J33: 0 | L33: =G33/$D$4 -> 2.8725314 | M33: =FLOOR(L33,1) -> 2 | N33: =(1-(L33-M33)) -> 0.12746858 | O33: =$D$4-((L33-M33)*$D$4) -> 71 | P33: =$D$24*2 -> 160 | Q33: =IF(P33>=O33,M33+1,M33) -> 3 | S33: =H33/$D$3 -> 3.3240997 | T33: =FLOOR(S33,1) -> 3 | U33: =(1-(S33-T33)) -> 0.67590028 | V33: =$D$3-((S33-T33)*$D$3) -> 244 | W33: =$C$24*2 -> 120 | X33: =IF(W33>=V33,T33+1,T33) -> 3 | Z33: =Q33*X33 -> 9 | AA33: =Z33*$D$5 -> 1.809693 | AB33: =(G33/1000)*(H33/1000) -> 1.92 | AC33: =IF(Z33>0,AA33/AB33,0) -> 0.94254844
C34: =IF(Z34>0,MAX(C31:C33)+1,0) -> 4 | D34: 10 | E34: 4 | F34: 2 | G34: 2400 | H34: 800 | I34: 2 | J34: 0 | L34: =G34/$D$4 -> 4.3087971 | M34: =FLOOR(L34,1) -> 4 | N34: =(1-(L34-M34)) -> 0.69120287 | O34: =$D$4-((L34-M34)*$D$4) -> 385 | P34: =$D$24*2 -> 160 | Q34: =IF(P34>=O34,M34+1,M34) -> 4 | S34: =H34/$D$3 -> 2.2160665 | T34: =FLOOR(S34,1) -> 2 | U34: =(1-(S34-T34)) -> 0.78393352 | V34: =$D$3-((S34-T34)*$D$3) -> 283 | W34: =$C$24*2 -> 120 | X34: =IF(W34>=V34,T34+1,T34) -> 2 | Z34: =Q34*X34 -> 8 | AA34: =Z34*$D$5 -> 1.608616 | AB34: =(G34/1000)*(H34/1000) -> 1.92 | AC34: =IF(Z34>0,AA34/AB34,0) -> 0.83782083
C35: =IF(Z35>0,MAX(C31:C34)+1,0) -> 5 | D35: 20 | E35: 5 | F35: 2 | G35: 2000 | H35: 1200 | I35: 0 | J35: 2 | L35: =G35/$D$4 -> 3.5906643 | M35: =FLOOR(L35,1) -> 3 | N35: =(1-(L35-M35)) -> 0.40933573 | O35: =$D$4-((L35-M35)*$D$4) -> 228 | P35: =$D$24*2 -> 160 | Q35: =IF(P35>=O35,M35+1,M35) -> 3 | S35: =H35/$D$3 -> 3.3240997 | T35: =FLOOR(S35,1) -> 3 | U35: =(1-(S35-T35)) -> 0.67590028 | V35: =$D$3-((S35-T35)*$D$3) -> 244 | W35: =$C$24*2 -> 120 | X35: =IF(W35>=V35,T35+1,T35) -> 3 | Z35: =Q35*X35 -> 9 | AA35: =Z35*$D$5 -> 1.809693 | AB35: =(G35/1000)*(H35/1000) -> 2.4 | AC35: =IF(Z35>0,AA35/AB35,0) -> 0.75403875
C36: =IF(Z36>0,MAX(C31:C35)+1,0) -> 6 | D36: 20 | E36: 6 | F36: 2 | G36: 2400 | H36: 1000 | I36: 0 | J36: 2 | L36: =G36/$D$4 -> 4.3087971 | M36: =FLOOR(L36,1) -> 4 | N36: =(1-(L36-M36)) -> 0.69120287 | O36: =$D$4-((L36-M36)*$D$4) -> 385 | P36: =$D$24*2 -> 160 | Q36: =IF(P36>=O36,M36+1,M36) -> 4 | S36: =H36/$D$3 -> 2.7700831 | T36: =FLOOR(S36,1) -> 2 | U36: =(1-(S36-T36)) -> 0.2299169 | V36: =$D$3-((S36-T36)*$D$3) -> 83 | W36: =$C$24*2 -> 120 | X36: =IF(W36>=V36,T36+1,T36) -> 3 | Z36: =Q36*X36 -> 12 | AA36: =Z36*$D$5 -> 2.412924 | AB36: =(G36/1000)*(H36/1000) -> 2.4 | AC36: =IF(Z36>0,AA36/AB36,0) -> 1.005385
C37: =IF(Z37>0,MAX(C31:C36)+1,0) -> 7 | D37: 10 | E37: 7 | F37: 3 | G37: 2400 | H37: 1200 | I37: 3 | J37: 0 | L37: =G37/$D$4 -> 4.3087971 | M37: =FLOOR(L37,1) -> 4 | N37: =(1-(L37-M37)) -> 0.69120287 | O37: =$D$4-((L37-M37)*$D$4) -> 385 | P37: =$D$24*2 -> 160 | Q37: =IF(P37>=O37,M37+1,M37) -> 4 | S37: =H37/$D$3 -> 3.3240997 | T37: =FLOOR(S37,1) -> 3 | U37: =(1-(S37-T37)) -> 0.67590028 | V37: =$D$3-((S37-T37)*$D$3) -> 244 | W37: =$C$24*2 -> 120 | X37: =IF(W37>=V37,T37+1,T37) -> 3 | Z37: =Q37*X37 -> 12 | AA37: =Z37*$D$5 -> 2.412924 | AB37: =(G37/1000)*(H37/1000) -> 2.88 | AC37: =IF(Z37>0,AA37/AB37,0) -> 0.83782083
C38: =IF(Z38>0,MAX(C31:C37)+1,0) -> 8 | D38: 10 | E38: 8 | F38: 3 | G38: 3600 | H38: 800 | I38: 3 | J38: 0 | L38: =G38/$D$4 -> 6.4631957 | M38: =FLOOR(L38,1) -> 6 | N38: =(1-(L38-M38)) -> 0.53680431 | O38: =$D$4-((L38-M38)*$D$4) -> 299 | P38: =$D$24*2 -> 160 | Q38: =IF(P38>=O38,M38+1,M38) -> 6 | S38: =H38/$D$3 -> 2.2160665 | T38: =FLOOR(S38,1) -> 2 | U38: =(1-(S38-T38)) -> 0.78393352 | V38: =$D$3-((S38-T38)*$D$3) -> 283 | W38: =$C$24*2 -> 120 | X38: =IF(W38>=V38,T38+1,T38) -> 2 | Z38: =Q38*X38 -> 12 | AA38: =Z38*$D$5 -> 2.412924 | AB38: =(G38/1000)*(H38/1000) -> 2.88 | AC38: =IF(Z38>0,AA38/AB38,0) -> 0.83782083
C39: =IF(Z39>0,MAX(C31:C38)+1,0) -> 9 | D39: 20 | E39: 9 | F39: 3 | G39: 3000 | H39: 1200 | I39: 0 | J39: 3 | L39: =G39/$D$4 -> 5.3859964 | M39: =FLOOR(L39,1) -> 5 | N39: =(1-(L39-M39)) -> 0.61400359 | O39: =$D$4-((L39-M39)*$D$4) -> 342 | P39: =$D$24*2 -> 160 | Q39: =IF(P39>=O39,M39+1,M39) -> 5 | S39: =H39/$D$3 -> 3.3240997 | T39: =FLOOR(S39,1) -> 3 | U39: =(1-(S39-T39)) -> 0.67590028 | V39: =$D$3-((S39-T39)*$D$3) -> 244 | W39: =$C$24*2 -> 120 | X39: =IF(W39>=V39,T39+1,T39) -> 3 | Z39: =Q39*X39 -> 15 | AA39: =Z39*$D$5 -> 3.016155 | AB39: =(G39/1000)*(H39/1000) -> 3.6 | AC39: =IF(Z39>0,AA39/AB39,0) -> 0.83782083
C40: =IF(Z40>0,MAX(C31:C39)+1,0) -> 10 | D40: 20 | E40: 10 | F40: 3 | G40: 3600 | H40: 1000 | I40: 0 | J40: 3 | L40: =G40/$D$4 -> 6.4631957 | M40: =FLOOR(L40,1) -> 6 | N40: =(1-(L40-M40)) -> 0.53680431 | O40: =$D$4-((L40-M40)*$D$4) -> 299 | P40: =$D$24*2 -> 160 | Q40: =IF(P40>=O40,M40+1,M40) -> 6 | S40: =H40/$D$3 -> 2.7700831 | T40: =FLOOR(S40,1) -> 2 | U40: =(1-(S40-T40)) -> 0.2299169 | V40: =$D$3-((S40-T40)*$D$3) -> 83 | W40: =$C$24*2 -> 120 | X40: =IF(W40>=V40,T40+1,T40) -> 3 | Z40: =Q40*X40 -> 18 | AA40: =Z40*$D$5 -> 3.619386 | AB40: =(G40/1000)*(H40/1000) -> 3.6 | AC40: =IF(Z40>0,AA40/AB40,0) -> 1.005385
C41: =IF(Z41>0,MAX(C31:C40)+1,0) -> 11 | D41: 10 | E41: 11 | F41: 4 | G41: 2400 | H41: 1600 | I41: 4 | J41: 0 | L41: =G41/$D$4 -> 4.3087971 | M41: =FLOOR(L41,1) -> 4 | N41: =(1-(L41-M41)) -> 0.69120287 | O41: =$D$4-((L41-M41)*$D$4) -> 385 | P41: =$D$24*2 -> 160 | Q41: =IF(P41>=O41,M41+1,M41) -> 4 | S41: =H41/$D$3 -> 4.432133 | T41: =FLOOR(S41,1) -> 4 | U41: =(1-(S41-T41)) -> 0.56786704 | V41: =$D$3-((S41-T41)*$D$3) -> 205 | W41: =$C$24*2 -> 120 | X41: =IF(W41>=V41,T41+1,T41) -> 4 | Z41: =Q41*X41 -> 16 | AA41: =Z41*$D$5 -> 3.217232 | AB41: =(G41/1000)*(H41/1000) -> 3.84 | AC41: =IF(Z41>0,AA41/AB41,0) -> 0.83782083
C42: =IF(Z42>0,MAX(C31:C41)+1,0) -> 12 | D42: 10 | E42: 12 | F42: 4 | G42: 3200 | H42: 1200 | I42: 4 | J42: 0 | L42: =G42/$D$4 -> 5.7450628 | M42: =FLOOR(L42,1) -> 5 | N42: =(1-(L42-M42)) -> 0.25493716 | O42: =$D$4-((L42-M42)*$D$4) -> 142 | P42: =$D$24*2 -> 160 | Q42: =IF(P42>=O42,M42+1,M42) -> 6 | S42: =H42/$D$3 -> 3.3240997 | T42: =FLOOR(S42,1) -> 3 | U42: =(1-(S42-T42)) -> 0.67590028 | V42: =$D$3-((S42-T42)*$D$3) -> 244 | W42: =$C$24*2 -> 120 | X42: =IF(W42>=V42,T42+1,T42) -> 3 | Z42: =Q42*X42 -> 18 | AA42: =Z42*$D$5 -> 3.619386 | AB42: =(G42/1000)*(H42/1000) -> 3.84 | AC42: =IF(Z42>0,AA42/AB42,0) -> 0.94254844
C43: =IF(Z43>0,MAX(C31:C42)+1,0) -> 13 | D43: 10 | E43: 13 | F43: 4 | G43: 4800 | H43: 800 | I43: 4 | J43: 0 | L43: =G43/$D$4 -> 8.6175943 | M43: =FLOOR(L43,1) -> 8 | N43: =(1-(L43-M43)) -> 0.38240575 | O43: =$D$4-((L43-M43)*$D$4) -> 213 | P43: =$D$24*2 -> 160 | Q43: =IF(P43>=O43,M43+1,M43) -> 8 | S43: =H43/$D$3 -> 2.2160665 | T43: =FLOOR(S43,1) -> 2 | U43: =(1-(S43-T43)) -> 0.78393352 | V43: =$D$3-((S43-T43)*$D$3) -> 283 | W43: =$C$24*2 -> 120 | X43: =IF(W43>=V43,T43+1,T43) -> 2 | Z43: =Q43*X43 -> 16 | AA43: =Z43*$D$5 -> 3.217232 | AB43: =(G43/1000)*(H43/1000) -> 3.84 | AC43: =IF(Z43>0,AA43/AB43,0) -> 0.83782083
C44: =IF(Z44>0,MAX(C31:C43)+1,0) -> 14 | D44: 20 | E44: 14 | F44: 4 | G44: 2400 | H44: 2000 | I44: 0 | J44: 4 | L44: =G44/$D$4 -> 4.3087971 | M44: =FLOOR(L44,1) -> 4 | N44: =(1-(L44-M44)) -> 0.69120287 | O44: =$D$4-((L44-M44)*$D$4) -> 385 | P44: =$D$24*2 -> 160 | Q44: =IF(P44>=O44,M44+1,M44) -> 4 | S44: =H44/$D$3 -> 5.5401662 | T44: =FLOOR(S44,1) -> 5 | U44: =(1-(S44-T44)) -> 0.4598338 | V44: =$D$3-((S44-T44)*$D$3) -> 166 | W44: =$C$24*2 -> 120 | X44: =IF(W44>=V44,T44+1,T44) -> 5 | Z44: =Q44*X44 -> 20 | AA44: =Z44*$D$5 -> 4.02154 | AB44: =(G44/1000)*(H44/1000) -> 4.8 | AC44: =IF(Z44>0,AA44/AB44,0) -> 0.83782083
C45: =IF(Z45>0,MAX(C31:C44)+1,0) -> 15 | D45: 20 | E45: 15 | F45: 4 | G45: 4000 | H45: 1200 | I45: 0 | J45: 4 | L45: =G45/$D$4 -> 7.1813285 | M45: =FLOOR(L45,1) -> 7 | N45: =(1-(L45-M45)) -> 0.81867145 | O45: =$D$4-((L45-M45)*$D$4) -> 456 | P45: =$D$24*2 -> 160 | Q45: =IF(P45>=O45,M45+1,M45) -> 7 | S45: =H45/$D$3 -> 3.3240997 | T45: =FLOOR(S45,1) -> 3 | U45: =(1-(S45-T45)) -> 0.67590028 | V45: =$D$3-((S45-T45)*$D$3) -> 244 | W45: =$C$24*2 -> 120 | X45: =IF(W45>=V45,T45+1,T45) -> 3 | Z45: =Q45*X45 -> 21 | AA45: =Z45*$D$5 -> 4.222617 | AB45: =(G45/1000)*(H45/1000) -> 4.8 | AC45: =IF(Z45>0,AA45/AB45,0) -> 0.87971188
C46: =IF(Z46>0,MAX(C31:C45)+1,0) -> 16 | D46: 10 | E46: 16 | F46: 5 | G46: 4000 | H46: 1200 | I46: 5 | J46: 0 | L46: =G46/$D$4 -> 7.1813285 | M46: =FLOOR(L46,1) -> 7 | N46: =(1-(L46-M46)) -> 0.81867145 | O46: =$D$4-((L46-M46)*$D$4) -> 456 | P46: =$D$24*2 -> 160 | Q46: =IF(P46>=O46,M46+1,M46) -> 7 | S46: =H46/$D$3 -> 3.3240997 | T46: =FLOOR(S46,1) -> 3 | U46: =(1-(S46-T46)) -> 0.67590028 | V46: =$D$3-((S46-T46)*$D$3) -> 244 | W46: =$C$24*2 -> 120 | X46: =IF(W46>=V46,T46+1,T46) -> 3 | Z46: =Q46*X46 -> 21 | AA46: =Z46*$D$5 -> 4.222617 | AB46: =(G46/1000)*(H46/1000) -> 4.8 | AC46: =IF(Z46>0,AA46/AB46,0) -> 0.87971188
C47: =IF(Z47>0,MAX(C31:C46)+1,0) -> 17 | D47: 20 | E47: 17 | F47: 4 | G47: 4800 | H47: 1000 | I47: 0 | J47: 4 | L47: =G47/$D$4 -> 8.6175943 | M47: =FLOOR(L47,1) -> 8 | N47: =(1-(L47-M47)) -> 0.38240575 | O47: =$D$4-((L47-M47)*$D$4) -> 213 | P47: =$D$24*2 -> 160 | Q47: =IF(P47>=O47,M47+1,M47) -> 8 | S47: =H47/$D$3 -> 2.7700831 | T47: =FLOOR(S47,1) -> 2 | U47: =(1-(S47-T47)) -> 0.2299169 | V47: =$D$3-((S47-T47)*$D$3) -> 83 | W47: =$C$24*2 -> 120 | X47: =IF(W47>=V47,T47+1,T47) -> 3 | Z47: =Q47*X47 -> 24 | AA47: =Z47*$D$5 -> 4.825848 | AB47: =(G47/1000)*(H47/1000) -> 4.8 | AC47: =IF(Z47>0,AA47/AB47,0) -> 1.005385
C48: =IF(Z48>0,MAX(C31:C47)+1,0) -> 18 | D48: 10 | E48: 18 | F48: 5 | G48: 6000 | H48: 800 | I48: 5 | J48: 0 | L48: =G48/$D$4 -> 10.771993 | M48: =FLOOR(L48,1) -> 10 | N48: =(1-(L48-M48)) -> 0.22800718 | O48: =$D$4-((L48-M48)*$D$4) -> 127 | P48: =$D$24*2 -> 160 | Q48: =IF(P48>=O48,M48+1,M48) -> 11 | S48: =H48/$D$3 -> 2.2160665 | T48: =FLOOR(S48,1) -> 2 | U48: =(1-(S48-T48)) -> 0.78393352 | V48: =$D$3-((S48-T48)*$D$3) -> 283 | W48: =$C$24*2 -> 120 | X48: =IF(W48>=V48,T48+1,T48) -> 2 | Z48: =Q48*X48 -> 22 | AA48: =Z48*$D$5 -> 4.423694 | AB48: =(G48/1000)*(H48/1000) -> 4.8 | AC48: =IF(Z48>0,AA48/AB48,0) -> 0.92160292
C49: =IF(Z49>0,MAX(C31:C48)+1,0) -> 19 | D49: 10 | E49: 19 | F49: 6 | G49: 2400 | H49: 2400 | I49: 6 | J49: 0 | L49: =G49/$D$4 -> 4.3087971 | M49: =FLOOR(L49,1) -> 4 | N49: =(1-(L49-M49)) -> 0.69120287 | O49: =$D$4-((L49-M49)*$D$4) -> 385 | P49: =$D$24*2 -> 160 | Q49: =IF(P49>=O49,M49+1,M49) -> 4 | S49: =H49/$D$3 -> 6.6481994 | T49: =FLOOR(S49,1) -> 6 | U49: =(1-(S49-T49)) -> 0.35180055 | V49: =$D$3-((S49-T49)*$D$3) -> 127 | W49: =$C$24*2 -> 120 | X49: =IF(W49>=V49,T49+1,T49) -> 6 | Z49: =Q49*X49 -> 24 | AA49: =Z49*$D$5 -> 4.825848 | AB49: =(G49/1000)*(H49/1000) -> 5.76 | AC49: =IF(Z49>0,AA49/AB49,0) -> 0.83782083
C50: =IF(Z50>0,MAX(C31:C49)+1,0) -> 20 | D50: 10 | E50: 20 | F50: 6 | G50: 4800 | H50: 1200 | I50: 6 | J50: 0 | L50: =G50/$D$4 -> 8.6175943 | M50: =FLOOR(L50,1) -> 8 | N50: =(1-(L50-M50)) -> 0.38240575 | O50: =$D$4-((L50-M50)*$D$4) -> 213 | P50: =$D$24*2 -> 160 | Q50: =IF(P50>=O50,M50+1,M50) -> 8 | S50: =H50/$D$3 -> 3.3240997 | T50: =FLOOR(S50,1) -> 3 | U50: =(1-(S50-T50)) -> 0.67590028 | V50: =$D$3-((S50-T50)*$D$3) -> 244 | W50: =$C$24*2 -> 120 | X50: =IF(W50>=V50,T50+1,T50) -> 3 | Z50: =Q50*X50 -> 24 | AA50: =Z50*$D$5 -> 4.825848 | AB50: =(G50/1000)*(H50/1000) -> 5.76 | AC50: =IF(Z50>0,AA50/AB50,0) -> 0.83782083
C51: =IF(Z51>0,MAX(C31:C50)+1,0) -> 21 | D51: 10 | E51: 21 | F51: 6 | G51: 3600 | H51: 1600 | I51: 6 | J51: 0 | L51: =G51/$D$4 -> 6.4631957 | M51: =FLOOR(L51,1) -> 6 | N51: =(1-(L51-M51)) -> 0.53680431 | O51: =$D$4-((L51-M51)*$D$4) -> 299 | P51: =$D$24*2 -> 160 | Q51: =IF(P51>=O51,M51+1,M51) -> 6 | S51: =H51/$D$3 -> 4.432133 | T51: =FLOOR(S51,1) -> 4 | U51: =(1-(S51-T51)) -> 0.56786704 | V51: =$D$3-((S51-T51)*$D$3) -> 205 | W51: =$C$24*2 -> 120 | X51: =IF(W51>=V51,T51+1,T51) -> 4 | Z51: =Q51*X51 -> 24 | AA51: =Z51*$D$5 -> 4.825848 | AB51: =(G51/1000)*(H51/1000) -> 5.76 | AC51: =IF(Z51>0,AA51/AB51,0) -> 0.83782083
C52: =IF(Z52>0,MAX(C31:C51)+1,0) -> 22 | D52: 20 | E52: 22 | F52: 5 | G52: 5000 | H52: 1200 | I52: 0 | J52: 5 | L52: =G52/$D$4 -> 8.9766607 | M52: =FLOOR(L52,1) -> 8 | N52: =(1-(L52-M52)) -> 0.023339318 | O52: =$D$4-((L52-M52)*$D$4) -> 13 | P52: =$D$24*2 -> 160 | Q52: =IF(P52>=O52,M52+1,M52) -> 9 | S52: =H52/$D$3 -> 3.3240997 | T52: =FLOOR(S52,1) -> 3 | U52: =(1-(S52-T52)) -> 0.67590028 | V52: =$D$3-((S52-T52)*$D$3) -> 244 | W52: =$C$24*2 -> 120 | X52: =IF(W52>=V52,T52+1,T52) -> 3 | Z52: =Q52*X52 -> 27 | AA52: =Z52*$D$5 -> 5.429079 | AB52: =(G52/1000)*(H52/1000) -> 6 | AC52: =IF(Z52>0,AA52/AB52,0) -> 0.9048465
C53: =IF(Z53>0,MAX(C31:C52)+1,0) -> 23 | D53: 20 | E53: 23 | F53: 5 | G53: 6000 | H53: 1000 | I53: 0 | J53: 5 | L53: =G53/$D$4 -> 10.771993 | M53: =FLOOR(L53,1) -> 10 | N53: =(1-(L53-M53)) -> 0.22800718 | O53: =$D$4-((L53-M53)*$D$4) -> 127 | P53: =$D$24*2 -> 160 | Q53: =IF(P53>=O53,M53+1,M53) -> 11 | S53: =H53/$D$3 -> 2.7700831 | T53: =FLOOR(S53,1) -> 2 | U53: =(1-(S53-T53)) -> 0.2299169 | V53: =$D$3-((S53-T53)*$D$3) -> 83 | W53: =$C$24*2 -> 120 | X53: =IF(W53>=V53,T53+1,T53) -> 3 | Z53: =Q53*X53 -> 33 | AA53: =Z53*$D$5 -> 6.635541 | AB53: =(G53/1000)*(H53/1000) -> 6 | AC53: =IF(Z53>0,AA53/AB53,0) -> 1.1059235
C54: =IF(Z54>0,MAX(C31:C53)+1,0) -> 24 | D54: 20 | E54: 24 | F54: 6 | G54: 6000 | H54: 1200 | I54: 0 | J54: 6 | L54: =G54/$D$4 -> 10.771993 | M54: =FLOOR(L54,1) -> 10 | N54: =(1-(L54-M54)) -> 0.22800718 | O54: =$D$4-((L54-M54)*$D$4) -> 127 | P54: =$D$24*2 -> 160 | Q54: =IF(P54>=O54,M54+1,M54) -> 11 | S54: =H54/$D$3 -> 3.3240997 | T54: =FLOOR(S54,1) -> 3 | U54: =(1-(S54-T54)) -> 0.67590028 | V54: =$D$3-((S54-T54)*$D$3) -> 244 | W54: =$C$24*2 -> 120 | X54: =IF(W54>=V54,T54+1,T54) -> 3 | Z54: =Q54*X54 -> 33 | AA54: =Z54*$D$5 -> 6.635541 | AB54: =(G54/1000)*(H54/1000) -> 7.2 | AC54: =IF(Z54>0,AA54/AB54,0) -> 0.92160292
C55: =IF(Z55>0,MAX(C31:C54)+1,0) -> 25 | D55: 20 | E55: 25 | F55: 6 | G55: 3000 | H55: 2400 | I55: 0 | J55: 6 | L55: =G55/$D$4 -> 5.3859964 | M55: =FLOOR(L55,1) -> 5 | N55: =(1-(L55-M55)) -> 0.61400359 | O55: =$D$4-((L55-M55)*$D$4) -> 342 | P55: =$D$24*2 -> 160 | Q55: =IF(P55>=O55,M55+1,M55) -> 5 | S55: =H55/$D$3 -> 6.6481994 | T55: =FLOOR(S55,1) -> 6 | U55: =(1-(S55-T55)) -> 0.35180055 | V55: =$D$3-((S55-T55)*$D$3) -> 127 | W55: =$C$24*2 -> 120 | X55: =IF(W55>=V55,T55+1,T55) -> 6 | Z55: =Q55*X55 -> 30 | AA55: =Z55*$D$5 -> 6.03231 | AB55: =(G55/1000)*(H55/1000) -> 7.2 | AC55: =IF(Z55>0,AA55/AB55,0) -> 0.83782083
C56: =IF(Z56>0,MAX(C31:C55)+1,0) -> 26 | D56: 20 | E56: 26 | F56: 6 | G56: 3600 | H56: 2000 | I56: 0 | J56: 6 | L56: =G56/$D$4 -> 6.4631957 | M56: =FLOOR(L56,1) -> 6 | N56: =(1-(L56-M56)) -> 0.53680431 | O56: =$D$4-((L56-M56)*$D$4) -> 299 | P56: =$D$24*2 -> 160 | Q56: =IF(P56>=O56,M56+1,M56) -> 6 | S56: =H56/$D$3 -> 5.5401662 | T56: =FLOOR(S56,1) -> 5 | U56: =(1-(S56-T56)) -> 0.4598338 | V56: =$D$3-((S56-T56)*$D$3) -> 166 | W56: =$C$24*2 -> 120 | X56: =IF(W56>=V56,T56+1,T56) -> 5 | Z56: =Q56*X56 -> 30 | AA56: =Z56*$D$5 -> 6.03231 | AB56: =(G56/1000)*(H56/1000) -> 7.2 | AC56: =IF(Z56>0,AA56/AB56,0) -> 0.83782083
C57: =IF(Z57>0,MAX(C31:C56)+1,0) -> 27 | D57: 10 | E57: 27 | F57: 8 | G57: 6400 | H57: 1200 | I57: 8 | J57: 0 | L57: =G57/$D$4 -> 11.490126 | M57: =FLOOR(L57,1) -> 11 | N57: =(1-(L57-M57)) -> 0.50987433 | O57: =$D$4-((L57-M57)*$D$4) -> 284 | P57: =$D$24*2 -> 160 | Q57: =IF(P57>=O57,M57+1,M57) -> 11 | S57: =H57/$D$3 -> 3.3240997 | T57: =FLOOR(S57,1) -> 3 | U57: =(1-(S57-T57)) -> 0.67590028 | V57: =$D$3-((S57-T57)*$D$3) -> 244 | W57: =$C$24*2 -> 120 | X57: =IF(W57>=V57,T57+1,T57) -> 3 | Z57: =Q57*X57 -> 33 | AA57: =Z57*$D$5 -> 6.635541 | AB57: =(G57/1000)*(H57/1000) -> 7.68 | AC57: =IF(Z57>0,AA57/AB57,0) -> 0.86400273
C58: =IF(Z58>0,MAX(C31:C57)+1,0) -> 28 | D58: 10 | E58: 28 | F58: 8 | G58: 3200 | H58: 2400 | I58: 8 | J58: 0 | L58: =G58/$D$4 -> 5.7450628 | M58: =FLOOR(L58,1) -> 5 | N58: =(1-(L58-M58)) -> 0.25493716 | O58: =$D$4-((L58-M58)*$D$4) -> 142 | P58: =$D$24*2 -> 160 | Q58: =IF(P58>=O58,M58+1,M58) -> 6 | S58: =H58/$D$3 -> 6.6481994 | T58: =FLOOR(S58,1) -> 6 | U58: =(1-(S58-T58)) -> 0.35180055 | V58: =$D$3-((S58-T58)*$D$3) -> 127 | W58: =$C$24*2 -> 120 | X58: =IF(W58>=V58,T58+1,T58) -> 6 | Z58: =Q58*X58 -> 36 | AA58: =Z58*$D$5 -> 7.238772 | AB58: =(G58/1000)*(H58/1000) -> 7.68 | AC58: =IF(Z58>0,AA58/AB58,0) -> 0.94254844
C59: =IF(Z59>0,MAX(C41:C58)+1,0) -> 29 | D59: 10 | E59: 29 | F59: 8 | G59: 4800 | H59: 1600 | I59: 8 | J59: 0 | L59: =G59/$D$4 -> 8.6175943 | M59: =FLOOR(L59,1) -> 8 | N59: =(1-(L59-M59)) -> 0.38240575 | O59: =$D$4-((L59-M59)*$D$4) -> 213 | P59: =$D$24*2 -> 160 | Q59: =IF(P59>=O59,M59+1,M59) -> 8 | S59: =H59/$D$3 -> 4.432133 | T59: =FLOOR(S59,1) -> 4 | U59: =(1-(S59-T59)) -> 0.56786704 | V59: =$D$3-((S59-T59)*$D$3) -> 205 | W59: =$C$24*2 -> 120 | X59: =IF(W59>=V59,T59+1,T59) -> 4 | Z59: =Q59*X59 -> 32 | AA59: =Z59*$D$5 -> 6.434464 | AB59: =(G59/1000)*(H59/1000) -> 7.68 | AC59: =IF(Z59>0,AA59/AB59,0) -> 0.83782083
C60: =IF(Z60>0,MAX(C31:C59)+1,0) -> 30 | D60: 20 | E60: 30 | F60: 8 | G60: 4800 | H60: 2000 | I60: 0 | J60: 8 | L60: =G60/$D$4 -> 8.6175943 | M60: =FLOOR(L60,1) -> 8 | N60: =(1-(L60-M60)) -> 0.38240575 | O60: =$D$4-((L60-M60)*$D$4) -> 213 | P60: =$D$24*2 -> 160 | Q60: =IF(P60>=O60,M60+1,M60) -> 8 | S60: =H60/$D$3 -> 5.5401662 | T60: =FLOOR(S60,1) -> 5 | U60: =(1-(S60-T60)) -> 0.4598338 | V60: =$D$3-((S60-T60)*$D$3) -> 166 | W60: =$C$24*2 -> 120 | X60: =IF(W60>=V60,T60+1,T60) -> 5 | Z60: =Q60*X60 -> 40 | AA60: =Z60*$D$5 -> 8.04308 | AB60: =(G60/1000)*(H60/1000) -> 9.6 | AC60: =IF(Z60>0,AA60/AB60,0) -> 0.83782083
C61: =IF(Z61>0,MAX(C31:C60)+1,0) -> 31 | D61: 20 | E61: 31 | F61: 8 | G61: 4000 | H61: 2400 | I61: 0 | J61: 8 | L61: =G61/$D$4 -> 7.1813285 | M61: =FLOOR(L61,1) -> 7 | N61: =(1-(L61-M61)) -> 0.81867145 | O61: =$D$4-((L61-M61)*$D$4) -> 456 | P61: =$D$24*2 -> 160 | Q61: =IF(P61>=O61,M61+1,M61) -> 7 | S61: =H61/$D$3 -> 6.6481994 | T61: =FLOOR(S61,1) -> 6 | U61: =(1-(S61-T61)) -> 0.35180055 | V61: =$D$3-((S61-T61)*$D$3) -> 127 | W61: =$C$24*2 -> 120 | X61: =IF(W61>=V61,T61+1,T61) -> 6 | Z61: =Q61*X61 -> 42 | AA61: =Z61*$D$5 -> 8.445234 | AB61: =(G61/1000)*(H61/1000) -> 9.6 | AC61: =IF(Z61>0,AA61/AB61,0) -> 0.87971188
C62: =IF(Z62>0,MAX(C31:C61)+1,0) -> 32 | D62: 10 | E62: 32 | F62: 10 | G62: 4000 | H62: 2400 | I62: 10 | J62: 0 | L62: =G62/$D$4 -> 7.1813285 | M62: =FLOOR(L62,1) -> 7 | N62: =(1-(L62-M62)) -> 0.81867145 | O62: =$D$4-((L62-M62)*$D$4) -> 456 | P62: =$D$24*2 -> 160 | Q62: =IF(P62>=O62,M62+1,M62) -> 7 | S62: =H62/$D$3 -> 6.6481994 | T62: =FLOOR(S62,1) -> 6 | U62: =(1-(S62-T62)) -> 0.35180055 | V62: =$D$3-((S62-T62)*$D$3) -> 127 | W62: =$C$24*2 -> 120 | X62: =IF(W62>=V62,T62+1,T62) -> 6 | Z62: =Q62*X62 -> 42 | AA62: =Z62*$D$5 -> 8.445234 | AB62: =(G62/1000)*(H62/1000) -> 9.6 | AC62: =IF(Z62>0,AA62/AB62,0) -> 0.87971188
C63: =IF(Z63>0,MAX(C31:C62)+1,0) -> 33 | D63: 10 | E63: 33 | F63: 10 | G63: 6000 | H63: 1600 | I63: 10 | J63: 0 | L63: =G63/$D$4 -> 10.771993 | M63: =FLOOR(L63,1) -> 10 | N63: =(1-(L63-M63)) -> 0.22800718 | O63: =$D$4-((L63-M63)*$D$4) -> 127 | P63: =$D$24*2 -> 160 | Q63: =IF(P63>=O63,M63+1,M63) -> 11 | S63: =H63/$D$3 -> 4.432133 | T63: =FLOOR(S63,1) -> 4 | U63: =(1-(S63-T63)) -> 0.56786704 | V63: =$D$3-((S63-T63)*$D$3) -> 205 | W63: =$C$24*2 -> 120 | X63: =IF(W63>=V63,T63+1,T63) -> 4 | Z63: =Q63*X63 -> 44 | AA63: =Z63*$D$5 -> 8.847388 | AB63: =(G63/1000)*(H63/1000) -> 9.6 | AC63: =IF(Z63>0,AA63/AB63,0) -> 0.92160292
C64: =IF(Z64>0,MAX(C31:C63)+1,0) -> 34 | D64: 10 | E64: 34 | F64: 12 | G64: 4800 | H64: 2400 | I64: 12 | J64: 0 | L64: =G64/$D$4 -> 8.6175943 | M64: =FLOOR(L64,1) -> 8 | N64: =(1-(L64-M64)) -> 0.38240575 | O64: =$D$4-((L64-M64)*$D$4) -> 213 | P64: =$D$24*2 -> 160 | Q64: =IF(P64>=O64,M64+1,M64) -> 8 | S64: =H64/$D$3 -> 6.6481994 | T64: =FLOOR(S64,1) -> 6 | U64: =(1-(S64-T64)) -> 0.35180055 | V64: =$D$3-((S64-T64)*$D$3) -> 127 | W64: =$C$24*2 -> 120 | X64: =IF(W64>=V64,T64+1,T64) -> 6 | Z64: =Q64*X64 -> 48 | AA64: =Z64*$D$5 -> 9.651696 | AB64: =(G64/1000)*(H64/1000) -> 11.52 | AC64: =IF(Z64>0,AA64/AB64,0) -> 0.83782083
C65: =IF(Z65>0,MAX(C31:C64)+1,0) -> 35 | D65: 20 | E65: 35 | F65: 10 | G65: 5000 | H65: 2400 | I65: 0 | J65: 10 | L65: =G65/$D$4 -> 8.9766607 | M65: =FLOOR(L65,1) -> 8 | N65: =(1-(L65-M65)) -> 0.023339318 | O65: =$D$4-((L65-M65)*$D$4) -> 13 | P65: =$D$24*2 -> 160 | Q65: =IF(P65>=O65,M65+1,M65) -> 9 | S65: =H65/$D$3 -> 6.6481994 | T65: =FLOOR(S65,1) -> 6 | U65: =(1-(S65-T65)) -> 0.35180055 | V65: =$D$3-((S65-T65)*$D$3) -> 127 | W65: =$C$24*2 -> 120 | X65: =IF(W65>=V65,T65+1,T65) -> 6 | Z65: =Q65*X65 -> 54 | AA65: =Z65*$D$5 -> 10.858158 | AB65: =(G65/1000)*(H65/1000) -> 12 | AC65: =IF(Z65>0,AA65/AB65,0) -> 0.9048465
C66: =IF(Z66>0,MAX(C31:C65)+1,0) -> 36 | D66: 20 | E66: 36 | F66: 10 | G66: 6000 | H66: 2000 | I66: 0 | J66: 10 | L66: =G66/$D$4 -> 10.771993 | M66: =FLOOR(L66,1) -> 10 | N66: =(1-(L66-M66)) -> 0.22800718 | O66: =$D$4-((L66-M66)*$D$4) -> 127 | P66: =$D$24*2 -> 160 | Q66: =IF(P66>=O66,M66+1,M66) -> 11 | S66: =H66/$D$3 -> 5.5401662 | T66: =FLOOR(S66,1) -> 5 | U66: =(1-(S66-T66)) -> 0.4598338 | V66: =$D$3-((S66-T66)*$D$3) -> 166 | W66: =$C$24*2 -> 120 | X66: =IF(W66>=V66,T66+1,T66) -> 5 | Z66: =Q66*X66 -> 55 | AA66: =Z66*$D$5 -> 11.059235 | AB66: =(G66/1000)*(H66/1000) -> 12 | AC66: =IF(Z66>0,AA66/AB66,0) -> 0.92160292
C67: =IF(Z67>0,MAX(C31:C66)+1,0) -> 37 | D67: 10 | E67: 37 | F67: 14 | G67: 5600 | H67: 2400 | I67: 14 | J67: 0 | L67: =G67/$D$4 -> 10.05386 | M67: =FLOOR(L67,1) -> 10 | N67: =(1-(L67-M67)) -> 0.94614004 | O67: =$D$4-((L67-M67)*$D$4) -> 527 | P67: =$D$24*2 -> 160 | Q67: =IF(P67>=O67,M67+1,M67) -> 10 | S67: =H67/$D$3 -> 6.6481994 | T67: =FLOOR(S67,1) -> 6 | U67: =(1-(S67-T67)) -> 0.35180055 | V67: =$D$3-((S67-T67)*$D$3) -> 127 | W67: =$C$24*2 -> 120 | X67: =IF(W67>=V67,T67+1,T67) -> 6 | Z67: =Q67*X67 -> 60 | AA67: =Z67*$D$5 -> 12.06462 | AB67: =(G67/1000)*(H67/1000) -> 13.44 | AC67: =IF(Z67>0,AA67/AB67,0) -> 0.89766518
C68: =IF(Z68>0,MAX(C31:C67)+1,0) -> 38 | D68: 20 | E68: 38 | F68: 12 | G68: 6000 | H68: 2400 | I68: 0 | J68: 12 | L68: =G68/$D$4 -> 10.771993 | M68: =FLOOR(L68,1) -> 10 | N68: =(1-(L68-M68)) -> 0.22800718 | O68: =$D$4-((L68-M68)*$D$4) -> 127 | P68: =$D$24*2 -> 160 | Q68: =IF(P68>=O68,M68+1,M68) -> 11 | S68: =H68/$D$3 -> 6.6481994 | T68: =FLOOR(S68,1) -> 6 | U68: =(1-(S68-T68)) -> 0.35180055 | V68: =$D$3-((S68-T68)*$D$3) -> 127 | W68: =$C$24*2 -> 120 | X68: =IF(W68>=V68,T68+1,T68) -> 6 | Z68: =Q68*X68 -> 66 | AA68: =Z68*$D$5 -> 13.271082 | AB68: =(G68/1000)*(H68/1000) -> 14.4 | AC68: =IF(Z68>0,AA68/AB68,0) -> 0.92160292
C69: =IF(Z69>0,MAX(C31:C68)+1,0) -> 39 | D69: 10 | E69: 39 | F69: 16 | G69: 6400 | H69: 2400 | I69: 16 | J69: 0 | L69: =G69/$D$4 -> 11.490126 | M69: =FLOOR(L69,1) -> 11 | N69: =(1-(L69-M69)) -> 0.50987433 | O69: =$D$4-((L69-M69)*$D$4) -> 284 | P69: =$D$24*2 -> 160 | Q69: =IF(P69>=O69,M69+1,M69) -> 11 | S69: =H69/$D$3 -> 6.6481994 | T69: =FLOOR(S69,1) -> 6 | U69: =(1-(S69-T69)) -> 0.35180055 | V69: =$D$3-((S69-T69)*$D$3) -> 127 | W69: =$C$24*2 -> 120 | X69: =IF(W69>=V69,T69+1,T69) -> 6 | Z69: =Q69*X69 -> 66 | AA69: =Z69*$D$5 -> 13.271082 | AB69: =(G69/1000)*(H69/1000) -> 15.36 | AC69: =IF(Z69>0,AA69/AB69,0) -> 0.86400273
C71: Pallet selectie | D71: Pallet | E71: Formaat | F71: Aantal | G71: Pallet | H71: Pallet | I71: Pallet | J71: Pallet | L71: B over L | M71: Afgerond | N71: Factor | O71: Oversteek | P71: Max | Q71: Aantal | S71: L over B | T71: Afgerond | U71: Factor | V71: Oversteek | W71: Max | X71: Aantal | Z71: Stapels | AA71: m2 | AB71: m2 per | AC71: Pallet
C72: =MAX(C73:C111) -> 39 | D72: groep | E72: nummer | F72: pallets | G72: lengte | H72: breedte | I72: 800x1200 | J72: 1000x1200 | P72: Oversteek | Q72: stapels | W72: Oversteek | X72: stapels | Z72: Pallet | AA72: karton | AB72: pallet | AC72: vulling
C73: =IF(Z73>0,1,0) -> 1 | D73: 10 | E73: 101 | F73: 1 | G73: 1200 | H73: 800 | I73: 1 | J73: 0 | L73: =G73/$D$3 -> 3.3240997 | M73: =FLOOR(L73,1) -> 3 | N73: =(1-(L73-M73)) -> 0.67590028 | O73: =$D$3-((L73-M73)*$D$3) -> 244 | P73: =$C$24*2 -> 120 | Q73: =IF(P73>=O73,M73+1,M73) -> 3 | S73: =H73/$D$4 -> 1.4362657 | T73: =FLOOR(S73,1) -> 1 | U73: =(1-(S73-T73)) -> 0.56373429 | V73: =$D$4-((S73-T73)*$D$4) -> 314 | W73: =$D$24*2 -> 160 | X73: =IF(W73>=V73,T73+1,T73) -> 1 | Z73: =Q73*X73 -> 3 | AA73: =Z73*$D$5 -> 0.603231 | AB73: =(G73/1000)*(H73/1000) -> 0.96 | AC73: =IF(Z73>0,AA73/AB73,0) -> 0.62836563
C74: =IF(Z74>0,MAX(C73)+1,0) -> 2 | D74: 20 | E74: 102 | F74: 1 | G74: 1200 | H74: 1000 | I74: 0 | J74: 1 | L74: =G74/$D$3 -> 3.3240997 | M74: =FLOOR(L74,1) -> 3 | N74: =(1-(L74-M74)) -> 0.67590028 | O74: =$D$3-((L74-M74)*$D$3) -> 244 | P74: =$C$24*2 -> 120 | Q74: =IF(P74>=O74,M74+1,M74) -> 3 | S74: =H74/$D$4 -> 1.7953321 | T74: =FLOOR(S74,1) -> 1 | U74: =(1-(S74-T74)) -> 0.20466786 | V74: =$D$4-((S74-T74)*$D$4) -> 114 | W74: =$D$24*2 -> 160 | X74: =IF(W74>=V74,T74+1,T74) -> 2 | Z74: =Q74*X74 -> 6 | AA74: =Z74*$D$5 -> 1.206462 | AB74: =(G74/1000)*(H74/1000) -> 1.2 | AC74: =IF(Z74>0,AA74/AB74,0) -> 1.005385
C75: =IF(Z75>0,MAX(C73:C74)+1,0) -> 3 | D75: 10 | E75: 103 | F75: 2 | G75: 1600 | H75: 1200 | I75: 2 | J75: 0 | L75: =G75/$D$3 -> 4.432133 | M75: =FLOOR(L75,1) -> 4 | N75: =(1-(L75-M75)) -> 0.56786704 | O75: =$D$3-((L75-M75)*$D$3) -> 205 | P75: =$C$24*2 -> 120 | Q75: =IF(P75>=O75,M75+1,M75) -> 4 | S75: =H75/$D$4 -> 2.1543986 | T75: =FLOOR(S75,1) -> 2 | U75: =(1-(S75-T75)) -> 0.84560144 | V75: =$D$4-((S75-T75)*$D$4) -> 471 | W75: =$D$24*2 -> 160 | X75: =IF(W75>=V75,T75+1,T75) -> 2 | Z75: =Q75*X75 -> 8 | AA75: =Z75*$D$5 -> 1.608616 | AB75: =(G75/1000)*(H75/1000) -> 1.92 | AC75: =IF(Z75>0,AA75/AB75,0) -> 0.83782083
C76: =IF(Z76>0,MAX(C73:C75)+1,0) -> 4 | D76: 10 | E76: 104 | F76: 2 | G76: 2400 | H76: 800 | I76: 2 | J76: 0 | L76: =G76/$D$3 -> 6.6481994 | M76: =FLOOR(L76,1) -> 6 | N76: =(1-(L76-M76)) -> 0.35180055 | O76: =$D$3-((L76-M76)*$D$3) -> 127 | P76: =$C$24*2 -> 120 | Q76: =IF(P76>=O76,M76+1,M76) -> 6 | S76: =H76/$D$4 -> 1.4362657 | T76: =FLOOR(S76,1) -> 1 | U76: =(1-(S76-T76)) -> 0.56373429 | V76: =$D$4-((S76-T76)*$D$4) -> 314 | W76: =$D$24*2 -> 160 | X76: =IF(W76>=V76,T76+1,T76) -> 1 | Z76: =Q76*X76 -> 6 | AA76: =Z76*$D$5 -> 1.206462 | AB76: =(G76/1000)*(H76/1000) -> 1.92 | AC76: =IF(Z76>0,AA76/AB76,0) -> 0.62836563
C77: =IF(Z77>0,MAX(C73:C76)+1,0) -> 5 | D77: 20 | E77: 105 | F77: 2 | G77: 2000 | H77: 1200 | I77: 0 | J77: 2 | L77: =G77/$D$3 -> 5.5401662 | M77: =FLOOR(L77,1) -> 5 | N77: =(1-(L77-M77)) -> 0.4598338 | O77: =$D$3-((L77-M77)*$D$3) -> 166 | P77: =$C$24*2 -> 120 | Q77: =IF(P77>=O77,M77+1,M77) -> 5 | S77: =H77/$D$4 -> 2.1543986 | T77: =FLOOR(S77,1) -> 2 | U77: =(1-(S77-T77)) -> 0.84560144 | V77: =$D$4-((S77-T77)*$D$4) -> 471 | W77: =$D$24*2 -> 160 | X77: =IF(W77>=V77,T77+1,T77) -> 2 | Z77: =Q77*X77 -> 10 | AA77: =Z77*$D$5 -> 2.01077 | AB77: =(G77/1000)*(H77/1000) -> 2.4 | AC77: =IF(Z77>0,AA77/AB77,0) -> 0.83782083
C78: =IF(Z78>0,MAX(C73:C77)+1,0) -> 6 | D78: 20 | E78: 106 | F78: 2 | G78: 2400 | H78: 1000 | I78: 0 | J78: 2 | L78: =G78/$D$3 -> 6.6481994 | M78: =FLOOR(L78,1) -> 6 | N78: =(1-(L78-M78)) -> 0.35180055 | O78: =$D$3-((L78-M78)*$D$3) -> 127 | P78: =$C$24*2 -> 120 | Q78: =IF(P78>=O78,M78+1,M78) -> 6 | S78: =H78/$D$4 -> 1.7953321 | T78: =FLOOR(S78,1) -> 1 | U78: =(1-(S78-T78)) -> 0.20466786 | V78: =$D$4-((S78-T78)*$D$4) -> 114 | W78: =$D$24*2 -> 160 | X78: =IF(W78>=V78,T78+1,T78) -> 2 | Z78: =Q78*X78 -> 12 | AA78: =Z78*$D$5 -> 2.412924 | AB78: =(G78/1000)*(H78/1000) -> 2.4 | AC78: =IF(Z78>0,AA78/AB78,0) -> 1.005385
C79: =IF(Z79>0,MAX(C73:C78)+1,0) -> 7 | D79: 10 | E79: 107 | F79: 3 | G79: 2400 | H79: 1200 | I79: 3 | J79: 0 | L79: =G79/$D$3 -> 6.6481994 | M79: =FLOOR(L79,1) -> 6 | N79: =(1-(L79-M79)) -> 0.35180055 | O79: =$D$3-((L79-M79)*$D$3) -> 127 | P79: =$C$24*2 -> 120 | Q79: =IF(P79>=O79,M79+1,M79) -> 6 | S79: =H79/$D$4 -> 2.1543986 | T79: =FLOOR(S79,1) -> 2 | U79: =(1-(S79-T79)) -> 0.84560144 | V79: =$D$4-((S79-T79)*$D$4) -> 471 | W79: =$D$24*2 -> 160 | X79: =IF(W79>=V79,T79+1,T79) -> 2 | Z79: =Q79*X79 -> 12 | AA79: =Z79*$D$5 -> 2.412924 | AB79: =(G79/1000)*(H79/1000) -> 2.88 | AC79: =IF(Z79>0,AA79/AB79,0) -> 0.83782083
C80: =IF(Z80>0,MAX(C73:C79)+1,0) -> 8 | D80: 10 | E80: 108 | F80: 3 | G80: 3600 | H80: 800 | I80: 3 | J80: 0 | L80: =G80/$D$3 -> 9.9722992 | M80: =FLOOR(L80,1) -> 9 | N80: =(1-(L80-M80)) -> 0.027700831 | O80: =$D$3-((L80-M80)*$D$3) -> 10 | P80: =$C$24*2 -> 120 | Q80: =IF(P80>=O80,M80+1,M80) -> 10 | S80: =H80/$D$4 -> 1.4362657 | T80: =FLOOR(S80,1) -> 1 | U80: =(1-(S80-T80)) -> 0.56373429 | V80: =$D$4-((S80-T80)*$D$4) -> 314 | W80: =$D$24*2 -> 160 | X80: =IF(W80>=V80,T80+1,T80) -> 1 | Z80: =Q80*X80 -> 10 | AA80: =Z80*$D$5 -> 2.01077 | AB80: =(G80/1000)*(H80/1000) -> 2.88 | AC80: =IF(Z80>0,AA80/AB80,0) -> 0.69818403
C81: =IF(Z81>0,MAX(C73:C80)+1,0) -> 9 | D81: 20 | E81: 109 | F81: 3 | G81: 3000 | H81: 1200 | I81: 0 | J81: 3 | L81: =G81/$D$3 -> 8.3102493 | M81: =FLOOR(L81,1) -> 8 | N81: =(1-(L81-M81)) -> 0.68975069 | O81: =$D$3-((L81-M81)*$D$3) -> 249 | P81: =$C$24*2 -> 120 | Q81: =IF(P81>=O81,M81+1,M81) -> 8 | S81: =H81/$D$4 -> 2.1543986 | T81: =FLOOR(S81,1) -> 2 | U81: =(1-(S81-T81)) -> 0.84560144 | V81: =$D$4-((S81-T81)*$D$4) -> 471 | W81: =$D$24*2 -> 160 | X81: =IF(W81>=V81,T81+1,T81) -> 2 | Z81: =Q81*X81 -> 16 | AA81: =Z81*$D$5 -> 3.217232 | AB81: =(G81/1000)*(H81/1000) -> 3.6 | AC81: =IF(Z81>0,AA81/AB81,0) -> 0.89367556
C82: =IF(Z82>0,MAX(C73:C81)+1,0) -> 10 | D82: 20 | E82: 110 | F82: 3 | G82: 3600 | H82: 1000 | I82: 0 | J82: 3 | L82: =G82/$D$3 -> 9.9722992 | M82: =FLOOR(L82,1) -> 9 | N82: =(1-(L82-M82)) -> 0.027700831 | O82: =$D$3-((L82-M82)*$D$3) -> 10 | P82: =$C$24*2 -> 120 | Q82: =IF(P82>=O82,M82+1,M82) -> 10 | S82: =H82/$D$4 -> 1.7953321 | T82: =FLOOR(S82,1) -> 1 | U82: =(1-(S82-T82)) -> 0.20466786 | V82: =$D$4-((S82-T82)*$D$4) -> 114 | W82: =$D$24*2 -> 160 | X82: =IF(W82>=V82,T82+1,T82) -> 2 | Z82: =Q82*X82 -> 20 | AA82: =Z82*$D$5 -> 4.02154 | AB82: =(G82/1000)*(H82/1000) -> 3.6 | AC82: =IF(Z82>0,AA82/AB82,0) -> 1.1170944
C83: =IF(Z83>0,MAX(C73:C82)+1,0) -> 11 | D83: 10 | E83: 111 | F83: 4 | G83: 2400 | H83: 1600 | I83: 4 | J83: 0 | L83: =G83/$D$3 -> 6.6481994 | M83: =FLOOR(L83,1) -> 6 | N83: =(1-(L83-M83)) -> 0.35180055 | O83: =$D$3-((L83-M83)*$D$3) -> 127 | P83: =$C$24*2 -> 120 | Q83: =IF(P83>=O83,M83+1,M83) -> 6 | S83: =H83/$D$4 -> 2.8725314 | T83: =FLOOR(S83,1) -> 2 | U83: =(1-(S83-T83)) -> 0.12746858 | V83: =$D$4-((S83-T83)*$D$4) -> 71 | W83: =$D$24*2 -> 160 | X83: =IF(W83>=V83,T83+1,T83) -> 3 | Z83: =Q83*X83 -> 18 | AA83: =Z83*$D$5 -> 3.619386 | AB83: =(G83/1000)*(H83/1000) -> 3.84 | AC83: =IF(Z83>0,AA83/AB83,0) -> 0.94254844
C84: =IF(Z84>0,MAX(C73:C83)+1,0) -> 12 | D84: 10 | E84: 112 | F84: 4 | G84: 3200 | H84: 1200 | I84: 4 | J84: 0 | L84: =G84/$D$3 -> 8.8642659 | M84: =FLOOR(L84,1) -> 8 | N84: =(1-(L84-M84)) -> 0.13573407 | O84: =$D$3-((L84-M84)*$D$3) -> 49 | P84: =$C$24*2 -> 120 | Q84: =IF(P84>=O84,M84+1,M84) -> 9 | S84: =H84/$D$4 -> 2.1543986 | T84: =FLOOR(S84,1) -> 2 | U84: =(1-(S84-T84)) -> 0.84560144 | V84: =$D$4-((S84-T84)*$D$4) -> 471 | W84: =$D$24*2 -> 160 | X84: =IF(W84>=V84,T84+1,T84) -> 2 | Z84: =Q84*X84 -> 18 | AA84: =Z84*$D$5 -> 3.619386 | AB84: =(G84/1000)*(H84/1000) -> 3.84 | AC84: =IF(Z84>0,AA84/AB84,0) -> 0.94254844
C85: =IF(Z85>0,MAX(C73:C84)+1,0) -> 13 | D85: 10 | E85: 113 | F85: 4 | G85: 4800 | H85: 800 | I85: 4 | J85: 0 | L85: =G85/$D$3 -> 13.296399 | M85: =FLOOR(L85,1) -> 13 | N85: =(1-(L85-M85)) -> 0.70360111 | O85: =$D$3-((L85-M85)*$D$3) -> 254 | P85: =$C$24*2 -> 120 | Q85: =IF(P85>=O85,M85+1,M85) -> 13 | S85: =H85/$D$4 -> 1.4362657 | T85: =FLOOR(S85,1) -> 1 | U85: =(1-(S85-T85)) -> 0.56373429 | V85: =$D$4-((S85-T85)*$D$4) -> 314 | W85: =$D$24*2 -> 160 | X85: =IF(W85>=V85,T85+1,T85) -> 1 | Z85: =Q85*X85 -> 13 | AA85: =Z85*$D$5 -> 2.614001 | AB85: =(G85/1000)*(H85/1000) -> 3.84 | AC85: =IF(Z85>0,AA85/AB85,0) -> 0.68072943
C86: =IF(Z86>0,MAX(C73:C85)+1,0) -> 14 | D86: 20 | E86: 114 | F86: 4 | G86: 2400 | H86: 2000 | I86: 0 | J86: 4 | L86: =G86/$D$3 -> 6.6481994 | M86: =FLOOR(L86,1) -> 6 | N86: =(1-(L86-M86)) -> 0.35180055 | O86: =$D$3-((L86-M86)*$D$3) -> 127 | P86: =$C$24*2 -> 120 | Q86: =IF(P86>=O86,M86+1,M86) -> 6 | S86: =H86/$D$4 -> 3.5906643 | T86: =FLOOR(S86,1) -> 3 | U86: =(1-(S86-T86)) -> 0.40933573 | V86: =$D$4-((S86-T86)*$D$4) -> 228 | W86: =$D$24*2 -> 160 | X86: =IF(W86>=V86,T86+1,T86) -> 3 | Z86: =Q86*X86 -> 18 | AA86: =Z86*$D$5 -> 3.619386 | AB86: =(G86/1000)*(H86/1000) -> 4.8 | AC86: =IF(Z86>0,AA86/AB86,0) -> 0.75403875
C87: =IF(Z87>0,MAX(C73:C86)+1,0) -> 15 | D87: 20 | E87: 115 | F87: 4 | G87: 4000 | H87: 1200 | I87: 0 | J87: 4 | L87: =G87/$D$3 -> 11.080332 | M87: =FLOOR(L87,1) -> 11 | N87: =(1-(L87-M87)) -> 0.91966759 | O87: =$D$3-((L87-M87)*$D$3) -> 332 | P87: =$C$24*2 -> 120 | Q87: =IF(P87>=O87,M87+1,M87) -> 11 | S87: =H87/$D$4 -> 2.1543986 | T87: =FLOOR(S87,1) -> 2 | U87: =(1-(S87-T87)) -> 0.84560144 | V87: =$D$4-((S87-T87)*$D$4) -> 471 | W87: =$D$24*2 -> 160 | X87: =IF(W87>=V87,T87+1,T87) -> 2 | Z87: =Q87*X87 -> 22 | AA87: =Z87*$D$5 -> 4.423694 | AB87: =(G87/1000)*(H87/1000) -> 4.8 | AC87: =IF(Z87>0,AA87/AB87,0) -> 0.92160292
C88: =IF(Z88>0,MAX(C73:C87)+1,0) -> 16 | D88: 10 | E88: 116 | F88: 5 | G88: 4000 | H88: 1200 | I88: 5 | J88: 0 | L88: =G88/$D$3 -> 11.080332 | M88: =FLOOR(L88,1) -> 11 | N88: =(1-(L88-M88)) -> 0.91966759 | O88: =$D$3-((L88-M88)*$D$3) -> 332 | P88: =$C$24*2 -> 120 | Q88: =IF(P88>=O88,M88+1,M88) -> 11 | S88: =H88/$D$4 -> 2.1543986 | T88: =FLOOR(S88,1) -> 2 | U88: =(1-(S88-T88)) -> 0.84560144 | V88: =$D$4-((S88-T88)*$D$4) -> 471 | W88: =$D$24*2 -> 160 | X88: =IF(W88>=V88,T88+1,T88) -> 2 | Z88: =Q88*X88 -> 22 | AA88: =Z88*$D$5 -> 4.423694 | AB88: =(G88/1000)*(H88/1000) -> 4.8 | AC88: =IF(Z88>0,AA88/AB88,0) -> 0.92160292
C89: =IF(Z89>0,MAX(C73:C88)+1,0) -> 17 | D89: 20 | E89: 117 | F89: 4 | G89: 4800 | H89: 1000 | I89: 0 | J89: 4 | L89: =G89/$D$3 -> 13.296399 | M89: =FLOOR(L89,1) -> 13 | N89: =(1-(L89-M89)) -> 0.70360111 | O89: =$D$3-((L89-M89)*$D$3) -> 254 | P89: =$C$24*2 -> 120 | Q89: =IF(P89>=O89,M89+1,M89) -> 13 | S89: =H89/$D$4 -> 1.7953321 | T89: =FLOOR(S89,1) -> 1 | U89: =(1-(S89-T89)) -> 0.20466786 | V89: =$D$4-((S89-T89)*$D$4) -> 114 | W89: =$D$24*2 -> 160 | X89: =IF(W89>=V89,T89+1,T89) -> 2 | Z89: =Q89*X89 -> 26 | AA89: =Z89*$D$5 -> 5.228002 | AB89: =(G89/1000)*(H89/1000) -> 4.8 | AC89: =IF(Z89>0,AA89/AB89,0) -> 1.0891671
C90: =IF(Z90>0,MAX(C73:C89)+1,0) -> 18 | D90: 10 | E90: 118 | F90: 5 | G90: 6000 | H90: 800 | I90: 5 | J90: 0 | L90: =G90/$D$3 -> 16.620499 | M90: =FLOOR(L90,1) -> 16 | N90: =(1-(L90-M90)) -> 0.37950139 | O90: =$D$3-((L90-M90)*$D$3) -> 137 | P90: =$C$24*2 -> 120 | Q90: =IF(P90>=O90,M90+1,M90) -> 16 | S90: =H90/$D$4 -> 1.4362657 | T90: =FLOOR(S90,1) -> 1 | U90: =(1-(S90-T90)) -> 0.56373429 | V90: =$D$4-((S90-T90)*$D$4) -> 314 | W90: =$D$24*2 -> 160 | X90: =IF(W90>=V90,T90+1,T90) -> 1 | Z90: =Q90*X90 -> 16 | AA90: =Z90*$D$5 -> 3.217232 | AB90: =(G90/1000)*(H90/1000) -> 4.8 | AC90: =IF(Z90>0,AA90/AB90,0) -> 0.67025667
C91: =IF(Z91>0,MAX(C73:C90)+1,0) -> 19 | D91: 10 | E91: 119 | F91: 6 | G91: 2400 | H91: 2400 | I91: 6 | J91: 0 | L91: =G91/$D$3 -> 6.6481994 | M91: =FLOOR(L91,1) -> 6 | N91: =(1-(L91-M91)) -> 0.35180055 | O91: =$D$3-((L91-M91)*$D$3) -> 127 | P91: =$C$24*2 -> 120 | Q91: =IF(P91>=O91,M91+1,M91) -> 6 | S91: =H91/$D$4 -> 4.3087971 | T91: =FLOOR(S91,1) -> 4 | U91: =(1-(S91-T91)) -> 0.69120287 | V91: =$D$4-((S91-T91)*$D$4) -> 385 | W91: =$D$24*2 -> 160 | X91: =IF(W91>=V91,T91+1,T91) -> 4 | Z91: =Q91*X91 -> 24 | AA91: =Z91*$D$5 -> 4.825848 | AB91: =(G91/1000)*(H91/1000) -> 5.76 | AC91: =IF(Z91>0,AA91/AB91,0) -> 0.83782083
C92: =IF(Z92>0,MAX(C73:C91)+1,0) -> 20 | D92: 10 | E92: 120 | F92: 6 | G92: 4800 | H92: 1200 | I92: 6 | J92: 0 | L92: =G92/$D$3 -> 13.296399 | M92: =FLOOR(L92,1) -> 13 | N92: =(1-(L92-M92)) -> 0.70360111 | O92: =$D$3-((L92-M92)*$D$3) -> 254 | P92: =$C$24*2 -> 120 | Q92: =IF(P92>=O92,M92+1,M92) -> 13 | S92: =H92/$D$4 -> 2.1543986 | T92: =FLOOR(S92,1) -> 2 | U92: =(1-(S92-T92)) -> 0.84560144 | V92: =$D$4-((S92-T92)*$D$4) -> 471 | W92: =$D$24*2 -> 160 | X92: =IF(W92>=V92,T92+1,T92) -> 2 | Z92: =Q92*X92 -> 26 | AA92: =Z92*$D$5 -> 5.228002 | AB92: =(G92/1000)*(H92/1000) -> 5.76 | AC92: =IF(Z92>0,AA92/AB92,0) -> 0.90763924
C93: =IF(Z93>0,MAX(C73:C92)+1,0) -> 21 | D93: 10 | E93: 121 | F93: 6 | G93: 3600 | H93: 1600 | I93: 6 | J93: 0 | L93: =G93/$D$3 -> 9.9722992 | M93: =FLOOR(L93,1) -> 9 | N93: =(1-(L93-M93)) -> 0.027700831 | O93: =$D$3-((L93-M93)*$D$3) -> 10 | P93: =$C$24*2 -> 120 | Q93: =IF(P93>=O93,M93+1,M93) -> 10 | S93: =H93/$D$4 -> 2.8725314 | T93: =FLOOR(S93,1) -> 2 | U93: =(1-(S93-T93)) -> 0.12746858 | V93: =$D$4-((S93-T93)*$D$4) -> 71 | W93: =$D$24*2 -> 160 | X93: =IF(W93>=V93,T93+1,T93) -> 3 | Z93: =Q93*X93 -> 30 | AA93: =Z93*$D$5 -> 6.03231 | AB93: =(G93/1000)*(H93/1000) -> 5.76 | AC93: =IF(Z93>0,AA93/AB93,0) -> 1.047276
C94: =IF(Z94>0,MAX(C73:C93)+1,0) -> 22 | D94: 20 | E94: 122 | F94: 5 | G94: 5000 | H94: 1200 | I94: 0 | J94: 5 | L94: =G94/$D$3 -> 13.850416 | M94: =FLOOR(L94,1) -> 13 | N94: =(1-(L94-M94)) -> 0.14958449 | O94: =$D$3-((L94-M94)*$D$3) -> 54 | P94: =$C$24*2 -> 120 | Q94: =IF(P94>=O94,M94+1,M94) -> 14 | S94: =H94/$D$4 -> 2.1543986 | T94: =FLOOR(S94,1) -> 2 | U94: =(1-(S94-T94)) -> 0.84560144 | V94: =$D$4-((S94-T94)*$D$4) -> 471 | W94: =$D$24*2 -> 160 | X94: =IF(W94>=V94,T94+1,T94) -> 2 | Z94: =Q94*X94 -> 28 | AA94: =Z94*$D$5 -> 5.630156 | AB94: =(G94/1000)*(H94/1000) -> 6 | AC94: =IF(Z94>0,AA94/AB94,0) -> 0.93835933
C95: =IF(Z95>0,MAX(C73:C94)+1,0) -> 23 | D95: 20 | E95: 123 | F95: 5 | G95: 6000 | H95: 1000 | I95: 0 | J95: 5 | L95: =G95/$D$3 -> 16.620499 | M95: =FLOOR(L95,1) -> 16 | N95: =(1-(L95-M95)) -> 0.37950139 | O95: =$D$3-((L95-M95)*$D$3) -> 137 | P95: =$C$24*2 -> 120 | Q95: =IF(P95>=O95,M95+1,M95) -> 16 | S95: =H95/$D$4 -> 1.7953321 | T95: =FLOOR(S95,1) -> 1 | U95: =(1-(S95-T95)) -> 0.20466786 | V95: =$D$4-((S95-T95)*$D$4) -> 114 | W95: =$D$24*2 -> 160 | X95: =IF(W95>=V95,T95+1,T95) -> 2 | Z95: =Q95*X95 -> 32 | AA95: =Z95*$D$5 -> 6.434464 | AB95: =(G95/1000)*(H95/1000) -> 6 | AC95: =IF(Z95>0,AA95/AB95,0) -> 1.0724107
C96: =IF(Z96>0,MAX(C73:C95)+1,0) -> 24 | D96: 20 | E96: 124 | F96: 6 | G96: 6000 | H96: 1200 | I96: 0 | J96: 6 | L96: =G96/$D$3 -> 16.620499 | M96: =FLOOR(L96,1) -> 16 | N96: =(1-(L96-M96)) -> 0.37950139 | O96: =$D$3-((L96-M96)*$D$3) -> 137 | P96: =$C$24*2 -> 120 | Q96: =IF(P96>=O96,M96+1,M96) -> 16 | S96: =H96/$D$4 -> 2.1543986 | T96: =FLOOR(S96,1) -> 2 | U96: =(1-(S96-T96)) -> 0.84560144 | V96: =$D$4-((S96-T96)*$D$4) -> 471 | W96: =$D$24*2 -> 160 | X96: =IF(W96>=V96,T96+1,T96) -> 2 | Z96: =Q96*X96 -> 32 | AA96: =Z96*$D$5 -> 6.434464 | AB96: =(G96/1000)*(H96/1000) -> 7.2 | AC96: =IF(Z96>0,AA96/AB96,0) -> 0.89367556
C97: =IF(Z97>0,MAX(C73:C96)+1,0) -> 25 | D97: 20 | E97: 125 | F97: 6 | G97: 3000 | H97: 2400 | I97: 0 | J97: 6 | L97: =G97/$D$3 -> 8.3102493 | M97: =FLOOR(L97,1) -> 8 | N97: =(1-(L97-M97)) -> 0.68975069 | O97: =$D$3-((L97-M97)*$D$3) -> 249 | P97: =$C$24*2 -> 120 | Q97: =IF(P97>=O97,M97+1,M97) -> 8 | S97: =H97/$D$4 -> 4.3087971 | T97: =FLOOR(S97,1) -> 4 | U97: =(1-(S97-T97)) -> 0.69120287 | V97: =$D$4-((S97-T97)*$D$4) -> 385 | W97: =$D$24*2 -> 160 | X97: =IF(W97>=V97,T97+1,T97) -> 4 | Z97: =Q97*X97 -> 32 | AA97: =Z97*$D$5 -> 6.434464 | AB97: =(G97/1000)*(H97/1000) -> 7.2 | AC97: =IF(Z97>0,AA97/AB97,0) -> 0.89367556
C98: =IF(Z98>0,MAX(C73:C97)+1,0) -> 26 | D98: 20 | E98: 126 | F98: 6 | G98: 3600 | H98: 2000 | I98: 0 | J98: 6 | L98: =G98/$D$3 -> 9.9722992 | M98: =FLOOR(L98,1) -> 9 | N98: =(1-(L98-M98)) -> 0.027700831 | O98: =$D$3-((L98-M98)*$D$3) -> 10 | P98: =$C$24*2 -> 120 | Q98: =IF(P98>=O98,M98+1,M98) -> 10 | S98: =H98/$D$4 -> 3.5906643 | T98: =FLOOR(S98,1) -> 3 | U98: =(1-(S98-T98)) -> 0.40933573 | V98: =$D$4-((S98-T98)*$D$4) -> 228 | W98: =$D$24*2 -> 160 | X98: =IF(W98>=V98,T98+1,T98) -> 3 | Z98: =Q98*X98 -> 30 | AA98: =Z98*$D$5 -> 6.03231 | AB98: =(G98/1000)*(H98/1000) -> 7.2 | AC98: =IF(Z98>0,AA98/AB98,0) -> 0.83782083
C99: =IF(Z99>0,MAX(C73:C98)+1,0) -> 27 | D99: 10 | E99: 127 | F99: 8 | G99: 6400 | H99: 1200 | I99: 8 | J99: 0 | L99: =G99/$D$3 -> 17.728532 | M99: =FLOOR(L99,1) -> 17 | N99: =(1-(L99-M99)) -> 0.27146814 | O99: =$D$3-((L99-M99)*$D$3) -> 98 | P99: =$C$24*2 -> 120 | Q99: =IF(P99>=O99,M99+1,M99) -> 18 | S99: =H99/$D$4 -> 2.1543986 | T99: =FLOOR(S99,1) -> 2 | U99: =(1-(S99-T99)) -> 0.84560144 | V99: =$D$4-((S99-T99)*$D$4) -> 471 | W99: =$D$24*2 -> 160 | X99: =IF(W99>=V99,T99+1,T99) -> 2 | Z99: =Q99*X99 -> 36 | AA99: =Z99*$D$5 -> 7.238772 | AB99: =(G99/1000)*(H99/1000) -> 7.68 | AC99: =IF(Z99>0,AA99/AB99,0) -> 0.94254844
C100: =IF(Z100>0,MAX(C73:C99)+1,0) -> 28 | D100: 10 | E100: 128 | F100: 8 | G100: 3200 | H100: 2400 | I100: 8 | J100: 0 | L100: =G100/$D$3 -> 8.8642659 | M100: =FLOOR(L100,1) -> 8 | N100: =(1-(L100-M100)) -> 0.13573407 | O100: =$D$3-((L100-M100)*$D$3) -> 49 | P100: =$C$24*2 -> 120 | Q100: =IF(P100>=O100,M100+1,M100) -> 9 | S100: =H100/$D$4 -> 4.3087971 | T100: =FLOOR(S100,1) -> 4 | U100: =(1-(S100-T100)) -> 0.69120287 | V100: =$D$4-((S100-T100)*$D$4) -> 385 | W100: =$D$24*2 -> 160 | X100: =IF(W100>=V100,T100+1,T100) -> 4 | Z100: =Q100*X100 -> 36 | AA100: =Z100*$D$5 -> 7.238772 | AB100: =(G100/1000)*(H100/1000) -> 7.68 | AC100: =IF(Z100>0,AA100/AB100,0) -> 0.94254844
C101: =IF(Z101>0,MAX(C83:C100)+1,0) -> 29 | D101: 10 | E101: 129 | F101: 8 | G101: 4800 | H101: 1600 | I101: 8 | J101: 0 | L101: =G101/$D$3 -> 13.296399 | M101: =FLOOR(L101,1) -> 13 | N101: =(1-(L101-M101)) -> 0.70360111 | O101: =$D$3-((L101-M101)*$D$3) -> 254 | P101: =$C$24*2 -> 120 | Q101: =IF(P101>=O101,M101+1,M101) -> 13 | S101: =H101/$D$4 -> 2.8725314 | T101: =FLOOR(S101,1) -> 2 | U101: =(1-(S101-T101)) -> 0.12746858 | V101: =$D$4-((S101-T101)*$D$4) -> 71 | W101: =$D$24*2 -> 160 | X101: =IF(W101>=V101,T101+1,T101) -> 3 | Z101: =Q101*X101 -> 39 | AA101: =Z101*$D$5 -> 7.842003 | AB101: =(G101/1000)*(H101/1000) -> 7.68 | AC101: =IF(Z101>0,AA101/AB101,0) -> 1.0210941
C102: =IF(Z102>0,MAX(C73:C101)+1,0) -> 30 | D102: 20 | E102: 130 | F102: 8 | G102: 4800 | H102: 2000 | I102: 0 | J102: 8 | L102: =G102/$D$3 -> 13.296399 | M102: =FLOOR(L102,1) -> 13 | N102: =(1-(L102-M102)) -> 0.70360111 | O102: =$D$3-((L102-M102)*$D$3) -> 254 | P102: =$C$24*2 -> 120 | Q102: =IF(P102>=O102,M102+1,M102) -> 13 | S102: =H102/$D$4 -> 3.5906643 | T102: =FLOOR(S102,1) -> 3 | U102: =(1-(S102-T102)) -> 0.40933573 | V102: =$D$4-((S102-T102)*$D$4) -> 228 | W102: =$D$24*2 -> 160 | X102: =IF(W102>=V102,T102+1,T102) -> 3 | Z102: =Q102*X102 -> 39 | AA102: =Z102*$D$5 -> 7.842003 | AB102: =(G102/1000)*(H102/1000) -> 9.6 | AC102: =IF(Z102>0,AA102/AB102,0) -> 0.81687531
C103: =IF(Z103>0,MAX(C73:C102)+1,0) -> 31 | D103: 20 | E103: 131 | F103: 8 | G103: 4000 | H103: 2400 | I103: 0 | J103: 8 | L103: =G103/$D$3 -> 11.080332 | M103: =FLOOR(L103,1) -> 11 | N103: =(1-(L103-M103)) -> 0.91966759 | O103: =$D$3-((L103-M103)*$D$3) -> 332 | P103: =$C$24*2 -> 120 | Q103: =IF(P103>=O103,M103+1,M103) -> 11 | S103: =H103/$D$4 -> 4.3087971 | T103: =FLOOR(S103,1) -> 4 | U103: =(1-(S103-T103)) -> 0.69120287 | V103: =$D$4-((S103-T103)*$D$4) -> 385 | W103: =$D$24*2 -> 160 | X103: =IF(W103>=V103,T103+1,T103) -> 4 | Z103: =Q103*X103 -> 44 | AA103: =Z103*$D$5 -> 8.847388 | AB103: =(G103/1000)*(H103/1000) -> 9.6 | AC103: =IF(Z103>0,AA103/AB103,0) -> 0.92160292
C104: =IF(Z104>0,MAX(C73:C103)+1,0) -> 32 | D104: 10 | E104: 132 | F104: 10 | G104: 4000 | H104: 2400 | I104: 10 | J104: 0 | L104: =G104/$D$3 -> 11.080332 | M104: =FLOOR(L104,1) -> 11 | N104: =(1-(L104-M104)) -> 0.91966759 | O104: =$D$3-((L104-M104)*$D$3) -> 332 | P104: =$C$24*2 -> 120 | Q104: =IF(P104>=O104,M104+1,M104) -> 11 | S104: =H104/$D$4 -> 4.3087971 | T104: =FLOOR(S104,1) -> 4 | U104: =(1-(S104-T104)) -> 0.69120287 | V104: =$D$4-((S104-T104)*$D$4) -> 385 | W104: =$D$24*2 -> 160 | X104: =IF(W104>=V104,T104+1,T104) -> 4 | Z104: =Q104*X104 -> 44 | AA104: =Z104*$D$5 -> 8.847388 | AB104: =(G104/1000)*(H104/1000) -> 9.6 | AC104: =IF(Z104>0,AA104/AB104,0) -> 0.92160292
C105: =IF(Z105>0,MAX(C73:C104)+1,0) -> 33 | D105: 10 | E105: 133 | F105: 10 | G105: 6000 | H105: 1600 | I105: 10 | J105: 0 | L105: =G105/$D$3 -> 16.620499 | M105: =FLOOR(L105,1) -> 16 | N105: =(1-(L105-M105)) -> 0.37950139 | O105: =$D$3-((L105-M105)*$D$3) -> 137 | P105: =$C$24*2 -> 120 | Q105: =IF(P105>=O105,M105+1,M105) -> 16 | S105: =H105/$D$4 -> 2.8725314 | T105: =FLOOR(S105,1) -> 2 | U105: =(1-(S105-T105)) -> 0.12746858 | V105: =$D$4-((S105-T105)*$D$4) -> 71 | W105: =$D$24*2 -> 160 | X105: =IF(W105>=V105,T105+1,T105) -> 3 | Z105: =Q105*X105 -> 48 | AA105: =Z105*$D$5 -> 9.651696 | AB105: =(G105/1000)*(H105/1000) -> 9.6 | AC105: =IF(Z105>0,AA105/AB105,0) -> 1.005385
C106: =IF(Z106>0,MAX(C73:C105)+1,0) -> 34 | D106: 10 | E106: 134 | F106: 12 | G106: 4800 | H106: 2400 | I106: 12 | J106: 0 | L106: =G106/$D$3 -> 13.296399 | M106: =FLOOR(L106,1) -> 13 | N106: =(1-(L106-M106)) -> 0.70360111 | O106: =$D$3-((L106-M106)*$D$3) -> 254 | P106: =$C$24*2 -> 120 | Q106: =IF(P106>=O106,M106+1,M106) -> 13 | S106: =H106/$D$4 -> 4.3087971 | T106: =FLOOR(S106,1) -> 4 | U106: =(1-(S106-T106)) -> 0.69120287 | V106: =$D$4-((S106-T106)*$D$4) -> 385 | W106: =$D$24*2 -> 160 | X106: =IF(W106>=V106,T106+1,T106) -> 4 | Z106: =Q106*X106 -> 52 | AA106: =Z106*$D$5 -> 10.456004 | AB106: =(G106/1000)*(H106/1000) -> 11.52 | AC106: =IF(Z106>0,AA106/AB106,0) -> 0.90763924
C107: =IF(Z107>0,MAX(C73:C106)+1,0) -> 35 | D107: 20 | E107: 135 | F107: 10 | G107: 5000 | H107: 2400 | I107: 0 | J107: 10 | L107: =G107/$D$3 -> 13.850416 | M107: =FLOOR(L107,1) -> 13 | N107: =(1-(L107-M107)) -> 0.14958449 | O107: =$D$3-((L107-M107)*$D$3) -> 54 | P107: =$C$24*2 -> 120 | Q107: =IF(P107>=O107,M107+1,M107) -> 14 | S107: =H107/$D$4 -> 4.3087971 | T107: =FLOOR(S107,1) -> 4 | U107: =(1-(S107-T107)) -> 0.69120287 | V107: =$D$4-((S107-T107)*$D$4) -> 385 | W107: =$D$24*2 -> 160 | X107: =IF(W107>=V107,T107+1,T107) -> 4 | Z107: =Q107*X107 -> 56 | AA107: =Z107*$D$5 -> 11.260312 | AB107: =(G107/1000)*(H107/1000) -> 12 | AC107: =IF(Z107>0,AA107/AB107,0) -> 0.93835933
C108: =IF(Z108>0,MAX(C73:C107)+1,0) -> 36 | D108: 20 | E108: 136 | F108: 10 | G108: 6000 | H108: 2000 | I108: 0 | J108: 10 | L108: =G108/$D$3 -> 16.620499 | M108: =FLOOR(L108,1) -> 16 | N108: =(1-(L108-M108)) -> 0.37950139 | O108: =$D$3-((L108-M108)*$D$3) -> 137 | P108: =$C$24*2 -> 120 | Q108: =IF(P108>=O108,M108+1,M108) -> 16 | S108: =H108/$D$4 -> 3.5906643 | T108: =FLOOR(S108,1) -> 3 | U108: =(1-(S108-T108)) -> 0.40933573 | V108: =$D$4-((S108-T108)*$D$4) -> 228 | W108: =$D$24*2 -> 160 | X108: =IF(W108>=V108,T108+1,T108) -> 3 | Z108: =Q108*X108 -> 48 | AA108: =Z108*$D$5 -> 9.651696 | AB108: =(G108/1000)*(H108/1000) -> 12 | AC108: =IF(Z108>0,AA108/AB108,0) -> 0.804308
C109: =IF(Z109>0,MAX(C73:C108)+1,0) -> 37 | D109: 10 | E109: 137 | F109: 14 | G109: 5600 | H109: 2400 | I109: 14 | J109: 0 | L109: =G109/$D$3 -> 15.512465 | M109: =FLOOR(L109,1) -> 15 | N109: =(1-(L109-M109)) -> 0.48753463 | O109: =$D$3-((L109-M109)*$D$3) -> 176 | P109: =$C$24*2 -> 120 | Q109: =IF(P109>=O109,M109+1,M109) -> 15 | S109: =H109/$D$4 -> 4.3087971 | T109: =FLOOR(S109,1) -> 4 | U109: =(1-(S109-T109)) -> 0.69120287 | V109: =$D$4-((S109-T109)*$D$4) -> 385 | W109: =$D$24*2 -> 160 | X109: =IF(W109>=V109,T109+1,T109) -> 4 | Z109: =Q109*X109 -> 60 | AA109: =Z109*$D$5 -> 12.06462 | AB109: =(G109/1000)*(H109/1000) -> 13.44 | AC109: =IF(Z109>0,AA109/AB109,0) -> 0.89766518
...

Sheet Transport tarieven
A4: Cotrans laadmeter calculatie:
A6: Laadmeter (rest) pallet | B6: ='Pallet en transport'!D191 -> 0.5415 | C6: Ldm
B10: 1 | C10: 0
A11: Landcode | B11: NL | C11: BE
A12: Postcode | B12: 3030 | C12: 8080
E14: 4 | F14: 5 | G14: 6 | H14: 7 | I14: 8 | J14: 9 | K14: 10
E15: =IF(AND($B$10=1,$B$12>=E17,$B$12<=E18),1,IF(AND($B$10=1,$B$12>=E19,$B$12<=E20),1,IF(AND($B$10=1,$B$12>=E21,$B$12<=E22),1,IF(AND($B$10=1,$B$12>=E23,$B$12<=E24),1,IF(AND($B$10=1,$B$12>=E25,$B$12<=E26),1,IF(AND($B$10=1,$B$12>=E27,$B$12<=E28),1,IF(AND($B$10=1,$B$12>=E29,$B$12<=E30),1,IF(AND($B$10=1,$B$12>=E31,$B$12<=E32),1,IF(AND($B$10=1,$B$12>=E33,$B$12<=E34),1," "))))))))) | F15: =IF(AND($B$10=1,$B$12>=F17,$B$12<=F18),1,IF(AND($B$10=1,$B$12>=F19,$B$12<=F20),1,IF(AND($B$10=1,$B$12>=F21,$B$12<=F22),1,IF(AND($B$10=1,$B$12>=F23,$B$12<=F24),1,IF(AND($B$10=1,$B$12>=F25,$B$12<=F26),1,IF(AND($B$10=1,$B$12>=F27,$B$12<=F28),1,IF(AND($B$10=1,$B$12>=F29,$B$12<=F30),1,IF(AND($B$10=1,$B$12>=F31,$B$12<=F32),1,IF(AND($B$10=1,$B$12>=F33,$B$12<=F34),1," "))))))))) | G15: =IF(AND($B$10=1,$B$12>=G17,$B$12<=G18),1,IF(AND($B$10=1,$B$12>=G19,$B$12<=G20),1,IF(AND($B$10=1,$B$12>=G21,$B$12<=G22),1,IF(AND($B$10=1,$B$12>=G23,$B$12<=G24),1,IF(AND($B$10=1,$B$12>=G25,$B$12<=G26),1,IF(AND($B$10=1,$B$12>=G27,$B$12<=G28),1,IF(AND($B$10=1,$B$12>=G29,$B$12<=G30),1,IF(AND($B$10=1,$B$12>=G31,$B$12<=G32),1,IF(AND($B$10=1,$B$12>=G33,$B$12<=G34),1," "))))))))) -> 1 | H15: =IF(AND($B$10=1,$B$12>=H17,$B$12<=H18),1,IF(AND($B$10=1,$B$12>=H19,$B$12<=H20),1,IF(AND($B$10=1,$B$12>=H21,$B$12<=H22),1,IF(AND($B$10=1,$B$12>=H23,$B$12<=H24),1,IF(AND($B$10=1,$B$12>=H25,$B$12<=H26),1,IF(AND($B$10=1,$B$12>=H27,$B$12<=H28),1,IF(AND($B$10=1,$B$12>=H29,$B$12<=H30),1,IF(AND($B$10=1,$B$12>=H31,$B$12<=H32),1,IF(AND($B$10=1,$B$12>=H33,$B$12<=H34),1," "))))))))) | I15: =IF(AND($C$10=1,$C$12>=I17,$C$12<=I18),1,IF(AND($C$10=1,$C$12>=I19,$C$12<=I20),1,IF(AND($C$10=1,$C$12>=I21,$C$12<=I22),1,IF(AND($C$10=1,$C$12>=I23,$C$12<=I24),1,IF(AND($C$10=1,$C$12>=I25,$C$12<=I26),1,IF(AND($C$10=1,$C$12>=I27,$C$12<=I28),1,IF(AND($C$10=1,$C$12>=I29,$C$12<=I30),1,IF(AND($C$10=1,$C$12>=I31,$C$12<=I32),1,IF(AND($C$10=1,$C$12>=I33,$C$12<=I34),1," "))))))))) | J15: =IF(AND($C$10=1,$C$12>=J17,$C$12<=J18),1,IF(AND($C$10=1,$C$12>=J19,$C$12<=J20),1,IF(AND($C$10=1,$C$12>=J21,$C$12<=J22),1,IF(AND($C$10=1,$C$12>=J23,$C$12<=J24),1,IF(AND($C$10=1,$C$12>=J25,$C$12<=J26),1,IF(AND($C$10=1,$C$12>=J27,$C$12<=J28),1,IF(AND($C$10=1,$C$12>=J29,$C$12<=J30),1,IF(AND($C$10=1,$C$12>=J31,$C$12<=J32),1,IF(AND($C$10=1,$C$12>=J33,$C$12<=J34),1," "))))))))) | K15: =IF(AND($C$10=1,$C$12>=K17,$C$12<=K18),1,IF(AND($C$10=1,$C$12>=K19,$C$12<=K20),1,IF(AND($C$10=1,$C$12>=K21,$C$12<=K22),1,IF(AND($C$10=1,$C$12>=K23,$C$12<=K24),1,IF(AND($C$10=1,$C$12>=K25,$C$12<=K26),1,IF(AND($C$10=1,$C$12>=K27,$C$12<=K28),1,IF(AND($C$10=1,$C$12>=K29,$C$12<=K30),1,IF(AND($C$10=1,$C$12>=K31,$C$12<=K32),1,IF(AND($C$10=1,$C$12>=K33,$C$12<=K34),1," ")))))))))
B16: Volle vracht | C16: (rest) vracht | D16: Laadmeter (Ldm) | E16: Zone 1 | F16: Zone 2 | G16: Zone 3 | H16: Zone 4 | I16: België Zone 1 | J16: België Zone 2 | K16: België Zone 3
D17: PC1 | E17: 5000 | F17: 5100 | G17: 1000 | H17: 1500 | I17: 2300 | J17: 1000 | K17: 4700
E18: 5099 | F18: 5499 | G18: 1499 | H18: 1999 | I18: 2399 | J18: 2299 | K18: 4999
D19: PC2 | E19: 5500 | F19: 5700 | G19: 2000 | H19: 4500 | I19: 2400 | J19: 2500 | K19: 5500
E20: 5599 | F20: 6099 | G20: 4499 | H20: 4599 | I20: 2499 | J20: 2899 | K20: 5999
D21: PC3 | E21: 5600 | G21: 4600 | H21: 7000 | I21: 2900 | J21: 3000 | K21: 6400
E22: 5699 | G22: 4999 | H22: 9999 | I22: 2999 | J22: 3499 | K22: 6499
D23: PC4 | G23: 6100 | I23: 3500 | J23: 3800
G24: 6999 | I24: 3599 | J24: 3899
D25: PC5 | I25: 3600 | J25: 4000
I26: 3699 | J26: 4699
D27: PC6 | I27: 3700 | J27: 5000
I28: 3799 | J28: 5499
D29: PC7 | I29: 3900 | J29: 6000
I30: 3999 | J30: 6399
D31: PC8 | J31: 7000 | N31: NL | O31: BE
J32: 9999 | M32: Factor correctie | N32: 1 | O32: 1
D33: PC9 | U33: Correctie | V33: Standaard
M34: Zone 1 | N34: Zone 2 | O34: Zone 3 | P34: Zone 4 | Q34: België Zone 1 | R34: België Zone 2 | S34: België Zone 3 | U34: factor | V34: Zone 1
C35: =IF(AND($B$6>0,$B$6<=D35),"D"," ") | D35: 0.2 | E35: =M35*$N$32 -> 26.605 | F35: =N35*$N$32 -> 34.7 | G35: =O35*$N$32 -> 38.1 | H35: =P35*$N$32 -> 47.62 | I35: =Q35*$O$32 -> 43.66 | J35: =R35*$O$32 -> 53.42 | K35: =S35*$O$32 -> 65.32 | M35: =U35*V35 -> 26.605 | N35: 34.7 | O35: 38.1 | P35: 47.62 | Q35: 43.66 | R35: 53.42 | S35: 65.32 | U35: 0.85 | V35: 31.3
C36: =IF(AND($B$6>0,$B$6>D35,$B$6<=D36),"D"," ") | D36: 0.4 | E36: =M36*$N$32 -> 32.4993 | F36: =N36*$N$32 -> 42.52 | G36: =O36*$N$32 -> 46.93 | H36: =P36*$N$32 -> 52.37 | I36: =Q36*$O$32 -> 50.22 | J36: =R36*$O$32 -> 63.35 | K36: =S36*$O$32 -> 77.2 | M36: =U36*V36 -> 32.4993 | N36: 42.52 | O36: 46.93 | P36: 52.37 | Q36: 50.22 | R36: 63.35 | S36: 77.2 | U36: 0.853 | V36: 38.1
C37: =IF(AND($B$6>0,$B$6>D36,$B$6<=D37),"D"," ") | D37: 0.5 | E37: =M37*$N$32 -> 36.65392 | F37: =N37*$N$32 -> 48.9 | G37: =O37*$N$32 -> 54.98 | H37: =P37*$N$32 -> 63.07 | I37: =Q37*$O$32 -> 58.83 | J37: =R37*$O$32 -> 74.59 | K37: =S37*$O$32 -> 91.39 | M37: =U37*V37 -> 36.65392 | N37: 48.9 | O37: 54.98 | P37: 63.07 | Q37: 58.83 | R37: 74.59 | S37: 91.39 | U37: 0.856 | V37: 42.82
C38: =IF(AND($B$6>0,$B$6>D37,$B$6<=D38),"D"," ") -> D | D38: 0.6 | E38: =M38*$N$32 -> 40.83686 | F38: =N38*$N$32 -> 55.29 | G38: =O38*$N$32 -> 63.03 | H38: =P38*$N$32 -> 73.76 | I38: =Q38*$O$32 -> 67.44 | J38: =R38*$O$32 -> 85.82 | K38: =S38*$O$32 -> 105.58 | M38: =U38*V38 -> 40.83686 | N38: 55.29 | O38: 63.03 | P38: 73.76 | Q38: 67.44 | R38: 85.82 | S38: 105.58 | U38: 0.859 | V38: 47.54
C39: =IF(AND($B$6>0,$B$6>D38,$B$6<=D39),"D"," ") | D39: 0.7 | E39: =M39*$N$32 -> 45.05674 | F39: =N39*$N$32 -> 51.67 | G39: =O39*$N$32 -> 71.08 | H39: =P39*$N$32 -> 84.46 | I39: =Q39*$O$32 -> 76.06 | J39: =R39*$O$32 -> 97.06 | K39: =S39*$O$32 -> 119.77 | M39: =U39*V39 -> 45.05674 | N39: 51.67 | O39: 71.08 | P39: 84.46 | Q39: 76.06 | R39: 97.06 | S39: 119.77 | U39: 0.862 | V39: 52.27
C40: =IF(AND($B$6>0,$B$6>D39,$B$6<=D40),"D"," ") | D40: 0.8 | E40: =M40*$N$32 -> 49.29635 | F40: =N40*$N$32 -> 68.06 | G40: =O40*$N$32 -> 79.13 | H40: =P40*$N$32 -> 95.15 | I40: =Q40*$O$32 -> 84.67 | J40: =R40*$O$32 -> 108.3 | K40: =S40*$O$32 -> 133.95 | M40: =U40*V40 -> 49.29635 | N40: 68.06 | O40: 79.13 | P40: 95.15 | Q40: 84.67 | R40: 108.3 | S40: 133.95 | U40: 0.865 | V40: 56.99
C41: =IF(AND($B$6>0,$B$6>D40,$B$6<=D41),"D"," ") | D41: 0.9 | E41: =M41*$N$32 -> 53.56428 | F41: =N41*$N$32 -> 74.44 | G41: =O41*$N$32 -> 87.18 | H41: =P41*$N$32 -> 105.85 | I41: =Q41*$O$32 -> 93.28 | J41: =R41*$O$32 -> 119.53 | K41: =S41*$O$32 -> 148.14 | M41: =U41*V41 -> 53.56428 | N41: 74.44 | O41: 87.18 | P41: 105.85 | Q41: 93.28 | R41: 119.53 | S41: 148.14 | U41: 0.868 | V41: 61.71
C42: =IF(AND($B$6>0,$B$6>D41,$B$6<=D42),"D"," ") | D42: 1 | E42: =M42*$N$32 -> 57.86053 | F42: =N42*$N$32 -> 80.83 | G42: =O42*$N$32 -> 95.23 | H42: =P42*$N$32 -> 116.54 | I42: =Q42*$O$32 -> 101.89 | J42: =R42*$O$32 -> 130.77 | K42: =S42*$O$32 -> 162.33 | M42: =U42*V42 -> 57.86053 | N42: 80.83 | O42: 95.23 | P42: 116.54 | Q42: 101.89 | R42: 130.77 | S42: 162.33 | U42: 0.871 | V42: 66.43
C43: =IF(AND($B$6>0,$B$6>D42,$B$6<=D43),"D"," ") | D43: 1.2 | E43: =M43*$N$32 -> 64.99938 | F43: =N43*$N$32 -> 90.92 | G43: =O43*$N$32 -> 107.47 | H43: =P43*$N$32 -> 132.41 | I43: =Q43*$O$32 -> 114.99 | J43: =R43*$O$32 -> 148.58 | K43: =S43*$O$32 -> 179.75 | M43: =U43*V43 -> 64.99938 | N43: 90.92 | O43: 107.47 | P43: 132.41 | Q43: 114.99 | R43: 148.58 | S43: 179.75 | U43: 0.874 | V43: 74.37
C44: =IF(AND($B$6>0,$B$6>D43,$B$6<=D44),"D"," ") | D44: 1.4 | E44: =M44*$N$32 -> 72.18587 | F44: =N44*$N$32 -> 101.01 | G44: =O44*$N$32 -> 119.72 | H44: =P44*$N$32 -> 148.28 | I44: =Q44*$O$32 -> 128.09 | J44: =R44*$O$32 -> 166.38 | K44: =S44*$O$32 -> 197.17 | M44: =U44*V44 -> 72.18587 | N44: 101.01 | O44: 119.72 | P44: 148.28 | Q44: 128.09 | R44: 166.38 | S44: 197.17 | U44: 0.877 | V44: 82.31
C45: =IF(AND($B$6>0,$B$6>D44,$B$6<=D45),"D"," ") | D45: 1.6 | E45: =M45*$N$32 -> 79.4112 | F45: =N45*$N$32 -> 111.1 | G45: =O45*$N$32 -> 131.96 | H45: =P45*$N$32 -> 164.14 | I45: =Q45*$O$32 -> 141.2 | J45: =R45*$O$32 -> 184.19 | K45: =S45*$O$32 -> 214.58 | M45: =U45*V45 -> 79.4112 | N45: 111.1 | O45: 131.96 | P45: 164.14 | Q45: 141.2 | R45: 184.19 | S45: 214.58 | U45: 0.88 | V45: 90.24
C46: =IF(AND($B$6>0,$B$6>D45,$B$6<=D46),"D"," ") | D46: 1.8 | E46: =M46*$N$32 -> 86.69294 | F46: =N46*$N$32 -> 121.19 | G46: =O46*$N$32 -> 144.21 | H46: =P46*$N$32 -> 180.01 | I46: =Q46*$O$32 -> 154.3 | J46: =R46*$O$32 -> 201.99 | K46: =S46*$O$32 -> 232 | M46: =U46*V46 -> 86.69294 | N46: 121.19 | O46: 144.21 | P46: 180.01 | Q46: 154.3 | R46: 201.99 | S46: 232 | U46: 0.883 | V46: 98.18
C47: =IF(AND($B$6>0,$B$6>D46,$B$6<=D47),"D"," ") | D47: 2 | E47: =M47*$N$32 -> 94.02232 | F47: =N47*$N$32 -> 131.29 | G47: =O47*$N$32 -> 156.45 | H47: =P47*$N$32 -> 195.88 | I47: =Q47*$O$32 -> 167.4 | J47: =R47*$O$32 -> 219.8 | K47: =S47*$O$32 -> 249.42 | M47: =U47*V47 -> 94.02232 | N47: 131.29 | O47: 156.45 | P47: 195.88 | Q47: 167.4 | R47: 219.8 | S47: 249.42 | U47: 0.886 | V47: 106.12
... C56: =IF(AND($B$6>0,$B$6>D55,$B$6<=D56),"D"," ") | D56: 5.6 | E56: =M56*$N$32 -> 158.0642 | F56: =N56*$N$32 -> 197.37 | G56: =O56*$N$32 -> 233.46 | H56: =P56*$N$32 -> 290.39 | I56: =Q56*$O$32 -> 247.31 | J56: =R56*$O$32 -> 323.24 | K56: =S56*$O$32 -> 383.7 | M56: =U56*V56 -> 158.0642 | N56: 197.37 | O56: 233.46 | P56: 290.39 | Q56: 247.31 | R56: 323.24 | S56: 383.7 | U56: 0.98 | V56: 161.29
C57: =IF(AND($B$6>0,$B$6>D56,$B$6<=D57),"D"," ") | D57: 6 | E57: =M57*$N$32 -> 167.42 | F57: =N57*$N$32 -> 204.72 | G57: =O57*$N$32 -> 242.01 | H57: =P57*$N$32 -> 300.89 | I57: =Q57*$O$32 -> 256.19 | J57: =R57*$O$32 -> 334.73 | K57: =S57*$O$32 -> 398.62 | M57: 167.42 | N57: 204.72 | O57: 242.01 | P57: 300.89 | Q57: 256.19 | R57: 334.73 | S57: 398.62
C58: =IF(AND($B$6>0,$B$6>D57,$B$6<=D58),"D"," ") | D58: 6.4 | E58: =M58*$N$32 -> 173.55 | F58: =N58*$N$32 -> 212.06 | G58: =O58*$N$32 -> 250.57 | H58: =P58*$N$32 -> 311.39 | I58: =Q58*$O$32 -> 265.07 | J58: =R58*$O$32 -> 346.22 | K58: =S58*$O$32 -> 413.54 | M58: 173.55 | N58: 212.06 | O58: 250.57 | P58: 311.39 | Q58: 265.07 | R58: 346.22 | S58: 413.54
C59: =IF(AND($B$6>0,$B$6>D58,$B$6<=D59),"D"," ") | D59: 6.8 | E59: =M59*$N$32 -> 179.68 | F59: =N59*$N$32 -> 219.4 | G59: =O59*$N$32 -> 259.13 | H59: =P59*$N$32 -> 321.89 | I59: =Q59*$O$32 -> 273.95 | J59: =R59*$O$32 -> 357.71 | K59: =S59*$O$32 -> 428.46 | M59: 179.68 | N59: 219.4 | O59: 259.13 | P59: 321.89 | Q59: 273.95 | R59: 357.71 | S59: 428.46
C60: =IF(AND($B$6>0,$B$6>D59,$B$6<=D60),"D"," ") | D60: 7.2 | E60: =M60*$N$32 -> 185.81 | F60: =N60*$N$32 -> 226.74 | G60: =O60*$N$32 -> 267.68 | H60: =P60*$N$32 -> 332.29 | I60: =Q60*$O$32 -> 282.83 | J60: =R60*$O$32 -> 369.21 | K60: =S60*$O$32 -> 443.38 | M60: 185.81 | N60: 226.74 | O60: 267.68 | P60: 332.29 | Q60: 282.83 | R60: 369.21 | S60: 443.38
C61: =IF(AND($B$6>0,$B$6>D60,$B$6<=D61),"D"," ") | D61: 7.6 | E61: =M61*$N$32 -> 191.94 | F61: =N61*$N$32 -> 234.09 | G61: =O61*$N$32 -> 276.24 | H61: =P61*$N$32 -> 342.89 | I61: =Q61*$O$32 -> 291.71 | J61: =R61*$O$32 -> 380.7 | K61: =S61*$O$32 -> 458.3 | M61: 191.94 | N61: 234.09 | O61: 276.24 | P61: 342.89 | Q61: 291.71 | R61: 380.7 | S61: 458.3
C62: =IF(AND($B$6>0,$B$6>D61,$B$6<=D62),"D"," ") | D62: 8 | E62: =M62*$N$32 -> 198.06 | F62: =N62*$N$32 -> 241.43 | G62: =O62*$N$32 -> 284.8 | H62: =P62*$N$32 -> 353.39 | I62: =Q62*$O$32 -> 300.59 | J62: =R62*$O$32 -> 392.19 | K62: =S62*$O$32 -> 473.22 | M62: 198.06 | N62: 241.43 | O62: 284.8 | P62: 353.39 | Q62: 300.59 | R62: 392.19 | S62: 473.22
C63: =IF(AND($B$6>0,$B$6>D62,$B$6<=D63),"D"," ") | D63: 8.4 | E63: =M63*$N$32 -> 204.19 | F63: =N63*$N$32 -> 248.77 | G63: =O63*$N$32 -> 293.35 | H63: =P63*$N$32 -> 363.89 | I63: =Q63*$O$32 -> 309.47 | J63: =R63*$O$32 -> 403.69 | K63: =S63*$O$32 -> 488.14 | M63: 204.19 | N63: 248.77 | O63: 293.35 | P63: 363.89 | Q63: 309.47 | R63: 403.69 | S63: 488.14
C64: =IF(AND($B$6>0,$B$6>D63,$B$6<=D64),"D"," ") | D64: 8.8 | E64: =M64*$N$32 -> 210.32 | F64: =N64*$N$32 -> 256.12 | G64: =O64*$N$32 -> 301.91 | H64: =P64*$N$32 -> 374.39 | I64: =Q64*$O$32 -> 318.35 | J64: =R64*$O$32 -> 415.18 | K64: =S64*$O$32 -> 503.06 | M64: 210.32 | N64: 256.12 | O64: 301.91 | P64: 374.39 | Q64: 318.35 | R64: 415.18 | S64: 503.06
C65: =IF(AND($B$6>0,$B$6>D64,$B$6<=D65),"D"," ") | D65: 9.2 | E65: =M65*$N$32 -> 216.45 | F65: =N65*$N$32 -> 263.46 | G65: =O65*$N$32 -> 310.47 | H65: =P65*$N$32 -> 384.89 | I65: =Q65*$O$32 -> 327.23 | J65: =R65*$O$32 -> 426.67 | K65: =S65*$O$32 -> 517.98 | M65: 216.45 | N65: 263.46 | O65: 310.47 | P65: 384.89 | Q65: 327.23 | R65: 426.67 | S65: 517.98
C66: =IF(AND($B$6>0,$B$6>D65,$B$6<=D66),"D"," ") | D66: 9.6 | E66: =M66*$N$32 -> 222.58 | F66: =N66*$N$32 -> 270.8 | G66: =O66*$N$32 -> 319.02 | H66: =P66*$N$32 -> 395.39 | I66: =Q66*$O$32 -> 336.11 | J66: =R66*$O$32 -> 438.16 | K66: =S66*$O$32 -> 532.9 | M66: 222.58 | N66: 270.8 | O66: 319.02 | P66: 395.39 | Q66: 336.11 | R66: 438.16 | S66: 532.9
C67: =IF(AND($B$6>0,$B$6>D66,$B$6<=D67),"D"," ") | D67: 10 | E67: =M67*$N$32 -> 228.71 | F67: =N67*$N$32 -> 278.15 | G67: =O67*$N$32 -> 327.58 | H67: =P67*$N$32 -> 405.89 | I67: =Q67*$O$32 -> 344.969 | J67: =R67*$O$32 -> 449.66 | K67: =S67*$O$32 -> 547.82 | M67: 228.71 | N67: 278.15 | O67: 327.58 | P67: 405.89 | Q67: 344.969 | R67: 449.66 | S67: 547.82
C68: =IF(AND($B$6>0,$B$6>D67,$B$6<=D68),"D"," ") | D68: 10.4 | E68: =M68*$N$32 -> 234.84 | F68: =N68*$N$32 -> 285.49 | G68: =O68*$N$32 -> 336.14 | H68: =P68*$N$32 -> 416.4 | I68: =Q68*$O$32 -> 353.87 | J68: =R68*$O$32 -> 461.15 | K68: =S68*$O$32 -> 562.74 | M68: 234.84 | N68: 285.49 | O68: 336.14 | P68: 416.4 | Q68: 353.87 | R68: 461.15 | S68: 562.74
D69: 10.8 | E69: =M69*$N$32 -> 240.97 | F69: =N69*$N$32 -> 282.83 | G69: =O69*$N$32 -> 344.69 | H69: =P69*$N$32 -> 426.9 | I69: =Q69*$O$32 -> 362.74 | J69: =R69*$O$32 -> 472.64 | K69: =S69*$O$32 -> 577.66 | M69: 240.97 | N69: 282.83 | O69: 344.69 | P69: 426.9 | Q69: 362.74 | R69: 472.64 | S69: 577.66
D70: 11.2 | E70: =M70*$N$32 -> 247.1 | F70: =N70*$N$32 -> 300.17 | G70: =O70*$N$32 -> 353.25 | H70: =P70*$N$32 -> 437.4 | I70: =Q70*$O$32 -> 371.62 | J70: =R70*$O$32 -> 484.14 | K70: =S70*$O$32 -> 592.58 | M70: 247.1 | N70: 300.17 | O70: 353.25 | P70: 437.4 | Q70: 371.62 | R70: 484.14 | S70: 592.58
D71: 11.6 | E71: =M71*$N$32 -> 253.23 | F71: =N71*$N$32 -> 307.52 | G71: =O71*$N$32 -> 361.8 | H71: =P71*$N$32 -> 447.9 | I71: =Q71*$O$32 -> 380.5 | J71: =R71*$O$32 -> 495.63 | K71: =S71*$O$32 -> 607.5 | M71: 253.23 | N71: 307.52 | O71: 361.8 | P71: 447.9 | Q71: 380.5 | R71: 495.63 | S71: 607.5
D72: 12 | E72: =M72*$N$32 -> 259.36 | F72: =N72*$N$32 -> 314.86 | G72: =O72*$N$32 -> 370.36 | H72: =P72*$N$32 -> 458.4 | I72: =Q72*$O$32 -> 389.38 | J72: =R72*$O$32 -> 507.12 | K72: =S72*$O$32 -> 622.42 | M72: 259.36 | N72: 314.86 | O72: 370.36 | P72: 458.4 | Q72: 389.38 | R72: 507.12 | S72: 622.42
C73: =IF(AND($B$6>0,$B$6>D68,$B$6<=D73),"D"," ") | D73: 12.4 | E73: =M73*$N$32 -> 265.49 | F73: =N73*$N$32 -> 322.2 | G73: =O73*$N$32 -> 378.92 | H73: =P73*$N$32 -> 468.9 | I73: =Q73*$O$32 -> 398.26 | J73: =R73*$O$32 -> 518.61 | K73: =S73*$O$32 -> 637.34 | M73: 265.49 | N73: 322.2 | O73: 378.92 | P73: 468.9 | Q73: 398.26 | R73: 518.61 | S73: 637.34
D74: 12.8 | E74: =M74*$N$32 -> 271.62 | F74: =N74*$N$32 -> 329.55 | G74: =O74*$N$32 -> 387.47 | H74: =P74*$N$32 -> 479.4 | I74: =Q74*$O$32 -> 407.14 | J74: =R74*$O$32 -> 530.11 | K74: =S74*$O$32 -> 652.26 | M74: 271.62 | N74: 329.55 | O74: 387.47 | P74: 479.4 | Q74: 407.14 | R74: 530.11 | S74: 652.26
B75: V | C75: =IF(AND($B$6>0,$B$6>D73,$B$6<=D75),"D"," ") | D75: 13.2 | E75: =M75*$N$32 -> 277.75 | F75: =N75*$N$32 -> 336.89 | G75: =O75*$N$32 -> 396.03 | H75: =P75*$N$32 -> 489.9 | I75: =Q75*$O$32 -> 416.2 | J75: =R75*$O$32 -> 541.6 | K75: =S75*$O$32 -> 667.18 | M75: 277.75 | N75: 336.89 | O75: 396.03 | P75: 489.9 | Q75: 416.2 | R75: 541.6 | S75: 667.18
C76: =IF(AND($B$6>0,$B$6>D75,$B$6<=D76),"D"," ")
D77: V | E77: =VLOOKUP("V",$B$35:$U$76,E14,FALSE) -> 277.75 | F77: =VLOOKUP("V",$B$35:$U$76,F14,FALSE) -> 336.89 | G77: =VLOOKUP("V",$B$35:$U$76,G14,FALSE) -> 396.03 | H77: =VLOOKUP("V",$B$35:$U$76,H14,FALSE) -> 489.9 | I77: =VLOOKUP("V",$B$35:$U$76,I14,FALSE) -> 416.2 | J77: =VLOOKUP("V",$B$35:$U$76,J14,FALSE) -> 541.6 | K77: =VLOOKUP("V",$B$35:$U$76,K14,FALSE) -> 667.18
D78: D | E78: =IF($B$6>0,VLOOKUP("D",$C$35:$U$76,E14-1,FALSE)," ") -> 40.83686 | F78: =IF($B$6>0,VLOOKUP("D",$C$35:$U$76,F14-1,FALSE)," ") -> 55.29 | G78: =IF($B$6>0,VLOOKUP("D",$C$35:$U$76,G14-1,FALSE)," ") -> 63.03 | H78: =IF($B$6>0,VLOOKUP("D",$C$35:$U$76,H14-1,FALSE)," ") -> 73.76 | I78: =IF($B$6>0,VLOOKUP("D",$C$35:$U$76,I14-1,FALSE)," ") -> 67.44 | J78: =IF($B$6>0,VLOOKUP("D",$C$35:$U$76,J14-1,FALSE)," ") -> 85.82 | K78: =IF($B$6>0,VLOOKUP("D",$C$35:$U$76,K14-1,FALSE)," ") -> 105.58
A81: Volle vracht | B81: V | C81: =IF(SUM(E15:U15)>0,HLOOKUP(1,E15:K78,63,FALSE)) -> 396.03
A82: (rest) vracht | B82: D | C82: =IF(SUM(E15:U15)>0,HLOOKUP(1,E15:K78,64,FALSE)) -> 63.03

Sheet Versiebeheer
A1: Versie | B1: Datum | C1: Wie | D1: Wijziging | E1: Wijziging in tabbladen
A2: A2 142024 A - V6 RHA | B2: 45601 | C2: RH | D2: Extra marge kokerdozen afankelijk gemaakt van plaatlengte | E2: Tabel toegevoegd bij marge berekening
A3: A2 142024 A - V6 RHA | B3: 45601 | C3: RH | D3: Bij keine bedrukte dozen (plaat langer dan 1000 mm) wordt bij de machinekeuze "Maxi" gekozen i.p.v. "Emba". | E3: Maxi wordt uitgesloten wanneer een Emba mogelijk is. Bij "keuze voorkeuren verschillende productgroepen" de formule kolom D aangepast.
A4: A2 142024 A - V6 RHA | B4: 45603 | C4: RH | D4: Bij een voorbewerking mag de efficientiebeperking voor een lastig doosformaat niet worden meegerekend. | E4: Formule toegevoegd dat bij Emba 295 voorbewerking voor de snelheid alleen wordt gerekend met plaatformaat. Factor Lengte / breedte, hoogte / lengte staat altijd op 1 bij voorbewerking.
A5: A2 142024 A - V6 RHA | B5: 45603 | C5: RH | D5: Verwijzingen factoren t.b.v. efficientie bij Emba 170 verwezen naar tavel bij Emba 295 i.p.v. 170 | E5: Verwijzing aangepast. Inhoudelijk wellicht soms kleine verschillen geweest in de calculatie.
A6: A2 142024 A - V6 RHA | B6: 45603 | C6: RH | D6: Bij plaat (als voorbewerking) op mini werd bij 1 achter elkaar wel een bewerking berekend. Dit is wat aangepast. | E6: Aantal bewerkingen bij doorvoeren van een plaat is aantal achter elkaar -1 geworden.
A7: A2 142024 A - V6 RHA | B7: 45603 | C7: RH | D7: Beinvloeding minimaal aantal bewerkingen moeten beinvloed worden om bij bedrukte dozen bij boxmakers de juiste route te kiezen | E7: Bij keuze productie route is een beinvloeding toegevoegd.
A8: A2 142024 A - V6 RHB | B8: 45603 | C8: RH | D8: Materiaal selectie geeft soms het zelfde aantal platen bij een andere plaatindeling 2-2 is goedkoper dan 1-4. | E8: Selectie van platen is zo aangepast dat er altijd wordt gekozen om zo veel mogelijk boven elkaar bij voorkeur te kiezen.
A9: A2 142024 A - V6 RHB | B9: 45603 | C9: RH | D9: Voorkeur Emba's aangepast zodat bij 2 kleuren indien mogelijk altijd Emba 295 wordt gekozen. | E9: "Voorkeur tussen inliners" aangepast zodat deze niet alleen op basis van aantal kiest maar ook bedrukking meeweegt.
A10: A2 142024 A - V6 RHC | B10: 45603 | C10: RH | D10: Bedrukte dozen op de mini hadden altijd Maxi als voorbewerking om te dukken. Nu is Emba 295 voorbewerking toegevoegd. | E10: Voorselectie bij "mini mogelijk" toegevoegd. Productieroute aangepast. Fase leidend voor materiaal aangepast.
A11: A2 142024 A - V6 RHC | B11: 45604 | C11: RH | D11: Bij voorbewerking op Emba wordt aantal boven elkaar soms hger berekend dan de mini kan verwerken. | E11: Maximaal boven elkaar s bij voor bewerking afgegerendeld op basis van maximaal op mini. Berekening bij "emba mogelijk" aangepast met maximaal op mini mogelijk.
A12: A2 142024 A - V6 RHC | B12: 45604 | C12: RH | D12: Voorwerking platen drukken op Maxi werden soms te veel platen berekend voor doorvoer. Minimalen afname materiaal. | E12: Er wordt nu een vergelijking gemaakt of alles van de minimale afname benodigd is. Anders worden alleen de benodigde platen verwerkt. Calculatie toegevoegd aan "maxi draaitijd berekenen"
A13: A2 142024 A - V6 RHC | B13: 45604 | C13: RH | D13: Bedrukte dozen op de mini worden in de praktijk nooit met meer dan 3 boven elkaar geproduceerd i.v.m. vouwen. | E13: Om calculatieverschillen te voorkomen worden bedrukte dozen op de mini waar mogelijk gemaximaliseerd op 3 boven elkaar.

Sheet Input (2)
A2: Kwaliteitscode | B2: =BLO!B6 -> 10010 | I2: To do:
A3: Golf | B3: ='Kwaliteit conversie (2)'!B4 -> B | I3: Palletaantallen alsof het een Emba doos is. Check of het een Emba doos is.
A4: Kwaliteit | B4: ='Kwaliteit conversie (2)'!C4 -> Wit extra sterk | I4: Kleine stansdozen gaan snel naar 2 uit een plaat. Verschil met verkoopprijsmodel in berekening.
A6: Fefco | B6: =BLO!B2 -> 0201
A7: Lengte | B7: =BLO!B3 -> 300 | C7: mm
A8: Breedte | B8: =BLO!B4 -> 250 | C8: mm
A9: Hoogte | B9: =BLO!B5 -> 100 | C9: mm
A11: Aantal kleuren | B11: =BLO!B12 -> onbedrukt
A12: Bedrukkingspercentage | B12: Onbedrukt / minder dan 10%
A13: Handgrepen | B13: =BLO!B8 -> geen handgrepen / stansbewerking
A14: Extra rillen | B14: Nee
A15: Pallethoogte (max. 2100 mm), niet verplicht vullen. | C15: mm
A17: Aantal | B17: =Mastersheet!H15 -> 1800 | C17: Stuks | I17: Alleen voor prijsvergelijking, niet gebruiken (wordt later weer verwijderd):
I18: Materiaal | L18: ='Rekenblad (2)'!E1081 -> 0.18900119
I19: Totale productiekosten | L19: ='Rekenblad (2)'!E1083 -> 0.086574074 | M19: =L19+L20 -> 0.088796296 | N19: Totaal productie
I20: Overige kosten (inkt/ tape/pallets) | L20: ='Rekenblad (2)'!E1082 -> 0.0022222222
A21: Minimale afname | C21: =IF('Rekenblad (2)'!I445=0," ",CEILING('Rekenblad (2)'!I445,10)) | D21: Stuks | I21: Orderkosten | L21: ='Rekenblad (2)'!E1084 -> 0.011111111
I22: Transport | L22: ='Rekenblad (2)'!E1091 -> 0.041844917
A23: Prijs per stuk, bij afname | B23: ='Rekenblad (2)'!C1094 -> 0.35767044 | C23: =B17 -> 1800 | D23: stuks
I24: Totaal marge (marge + variatie inkoop) | L24: ='Rekenblad (2)'!E1089 -> 0.026916924
I26: Kosten per verpakking | L26: ='Rekenblad (2)'!E1093 -> 0.35767044
A27: Palletstapeling indicatief:
A28: Formaat colli | B28: =IF('Rekenblad (2)'!AV46=1,'Pallet en transport (2)'!D151& " x "&'Pallet en transport (2)'!E151," ") -> 1083 x 1200 | C28: mm
A29: Aantal per bundel | B29: =IF('Rekenblad (2)'!AV46=1,IF('Pallet en transport (2)'!D165=0,0,'Pallet en transport (2)'!D166)," ") -> 25 | C29: stuks
A30: Aantal stapels per colli | B30: =IF('Rekenblad (2)'!AV46=1,'Pallet en transport (2)'!D170," ") -> 6 | C30: stuks | I30: Hoofdbewerking gekozen:
A31: Aantal per colli | B31: =IF('Rekenblad (2)'!AV46=1,'Pallet en transport (2)'!D171," ") -> 1800 | C31: stuks | I31: ='Rekenblad (2)'!C362 -> 0 | J31: ='Rekenblad (2)'!D362 -> 0 | K31: ='Rekenblad (2)'!E362 -> 0 | L31: ='Rekenblad (2)'!F362 -> 1 | M31: ='Rekenblad (2)'!G362 -> 0 | N31: ='Rekenblad (2)'!H362 -> 0 | O31: ='Rekenblad (2)'!I362 -> 0
A32: Hoogte bij benadering | B32: =IF('Rekenblad (2)'!AV46=1,'Pallet en transport (2)'!D160," ") -> 1950 | C32: mm | I32: Mini | J32: Maxi | K32: Emba 170 | L32: Emba 295 | M32: Vlakstans | N32: Roda | O32: Plaat op maat
A33: Aantal colli | B33: =IF('Rekenblad (2)'!AV46=1,'Pallet en transport (2)'!D174," ") -> 1 | C33: stuks

Sheet Rekenblad (2)
B2: Fefco geselecteerd | C2: ='Input (2)'!B6 -> 0201
B3: Aantal | C3: ='Input (2)'!B17 -> 1800
B4: Golfsoort | C4: ='Kwaliteit conversie (2)'!B4 -> B
B6: Lengte | C6: ='Input (2)'!B7 -> 300
B7: breedte | C7: ='Input (2)'!B8 -> 250
B8: hoogte | C8: ='Input (2)'!B9 -> 100
B9: Formaat mogelijk | C9: =IF(SUM(D1072:D1074)=3,1,0) -> 1
B10: L >= B akkoord | C10: =IF(AND(E1071=1,C6>=C7),1,IF(E1071=0,1,0)) -> 1
B12: Toeslag materiaal | C12: =E145 -> 2
B13: Dikte | C13: =F145 -> 3
B14: Bedrukking | C14: ='Input (2)'!B11 -> onbedrukt
B15: Percentage bedrukking | C15: ='Input (2)'!B12 -> Onbedrukt / minder dan 10%
B16: Stansbewerking | C16: ='Input (2)'!B13 -> geen handgrepen / stansbewerking
B17: Pallethoogte | C17: =IF(AND('Input (2)'!B15>0,'Input (2)'!B15<2100),'Input (2)'!B15,2100) -> 2100 | D17: mm
B19: Minimale breedte F02.. op basis van lengte:
B20: =IF(AND($C$6>B21,$C$6<=B22),1,0) -> 0 | C20: =IF(AND($C$6>C21,$C$6<=C22),1,0) -> 0 | D20: =IF(AND($C$6>D21,$C$6<=D22),1,0) -> 1 | E20: =IF(AND($C$6>E21,$C$6<=E22),1,0) -> 0 | F20: =IF(AND($C$6>F21,$C$6<=F22),1,0) -> 0 | G20: =IF(AND($C$6>G21,$C$6<=G22),1,0) -> 0 | H20: =IF(AND($C$6>H21,$C$6<=H22),1,0) -> 0 | I20: =IF(AND($C$6>I21,$C$6<=I22),1,0) -> 0 | ... L20: =IF(AND($C$6>L21,$C$6<=L22),1,0) -> 0
B21: 0 | C21: 200 | D21: 250 | E21: 300 | F21: 350 | G21: 400 | H21: 500 | I21: 600 | J21: 750 | K21: 1000 | L21: 1250
B22: 200 | C22: 250 | D22: 300 | E22: 350 | F22: 400 | G22: 500 | H22: 600 | I22: 750 | J22: 1000 | K22: 1250 | L22: 99999
A23: Stotende klep | B23: 60 | C23: 65 | D23: 70 | E23: 75 | F23: 80 | G23: 85 | H23: 90 | I23: 95 | J23: 100 | K23: 105 | L23: 110 | M23: =HLOOKUP(1,B20:L24,4,FALSE) -> 70
A24: Overslaande klep | B24: 40 | C24: 40 | D24: 40 | E24: 40 | F24: 40 | G24: 40 | H24: 40 | I24: 40 | J24: 50 | K24: 50 | L24: 60 | M24: =HLOOKUP(1,B20:L24,5,FALSE) -> 40
B26: Lengte / hoogte verhouding:
C27: Lengte tussen | E27: Hoogte minimaal
B28: =IF(AND($C$6>C28,$C$6<=D28),1,0) -> 1 | C28: 0 | D28: 400 | E28: 37
B29: =IF(AND($C$6>C29,$C$6<=D29),1,0) -> 0 | C29: 400 | D29: 450 | E29: 40
B30: =IF(AND($C$6>C30,$C$6<=D30),1,0) -> 0 | C30: 450 | D30: 500 | E30: 43
B31: =IF(AND($C$6>C31,$C$6<=D31),1,0) -> 0 | C31: 500 | D31: 550 | E31: 47
B32: =IF(AND($C$6>C32,$C$6<=D32),1,0) -> 0 | C32: 550 | D32: 600 | E32: 50
B33: =IF(AND($C$6>C33,$C$6<=D33),1,0) -> 0 | C33: 600 | D33: 650 | E33: 54
B34: =IF(AND($C$6>C34,$C$6<=D34),1,0) -> 0 | C34: 650 | D34: 700 | E34: 57
B35: =IF(AND($C$6>C35,$C$6<=D35),1,0) -> 0 | C35: 700 | D35: 850 | E35: 60
B36: =IF(AND($C$6>C36,$C$6<=D36),1,0) -> 0 | C36: 850 | D36: 1000 | E36: 70
B37: =IF(AND($C$6>C37,$C$6<=D37),1,0) -> 0 | C37: 1000 | D37: 1200 | E37: 80
B38: =IF(AND($C$6>C38,$C$6<=D38),1,0) -> 0 | C38: 1200 | D38: 2000 | E38: 95
B39: =IF(AND($C$6>C39,$C$6<=D39),1,0) -> 0 | C39: 2000 | D39: 9999 | E39: 110
B41: Minimale hoogte | E41: =VLOOKUP(1,B28:E39,4,FALSE) -> 37
AG44: Beveiliging | AO44: Beveiliging
B45: 2 | C45: 3 | D45: 4 | E45: 5 | F45: 6 | G45: 7 | H45: 8 | I45: 9 | J45: 10 | K45: 11 | L45: 12 | M45: 13 | N45: 14 | O45: 15 | P45: 16 | Q45: 17 | R45: 18 | S45: 19 | T45: 20 | U45: 21 | V45: 22 | W45: 23 | X45: 24 | Y45: 25 | Z45: 26 | AA45: 27 | AB45: 28 | AC45: 29 | AD45: 30 | AE45: 31 | AF45: 32 | AG45: 33 | AH45: 34 | AI45: 35 | AJ45: 36 | AK45: 37 | AL45: 38 | AM45: 39 | AN45: 40 | AO45: 41 | AP45: 42 | AQ45: 43 | AR45: 44 | AS45: 45 | AT45: 46 | AU45: 47 | AV45: 48 | AW45: 49 | AX45: 50 | AY45: 51 | AZ45: 52
C46: =C6 -> 300 | D46: =C7 -> 250 | E46: =C8 -> 100 | F46: =C13 -> 3 | I46: =C12 -> 2 | K46: =C6 -> 300 | L46: =C7 -> 250 | M46: =C8 -> 100 | N46: =C13 -> 3 | Q46: =C12 -> 2 | T46: =VLOOKUP(1,50:70,T45,FALSE) -> 1 | U46: =VLOOKUP(1,50:70,U45,FALSE) -> 1 | V46: =VLOOKUP(1,50:70,V45,FALSE) -> 0 | W46: =VLOOKUP(1,50:70,W45,FALSE) -> 0 | X46: =VLOOKUP(1,50:70,X45,FALSE) -> 0 | AA46: =VLOOKUP(1,50:70,AA45,FALSE) -> 1 | AB46: =VLOOKUP(1,50:70,AB45,FALSE) -> 1 | AC46: =VLOOKUP(1,50:70,AC45,FALSE) -> 0 | AD46: =VLOOKUP(1,50:70,AD45,FALSE) -> 127 | AE46: =VLOOKUP(1,50:70,AE45,FALSE) -> 127 | AF46: =VLOOKUP(1,50:70,AF45,FALSE) -> 107 | AG46: =VLOOKUP(1,50:70,AG45,FALSE) -> 100 | AH46: =VLOOKUP(1,50:70,AH45,FALSE) -> 2000 | ... AZ46: =VLOOKUP(1,50:70,AZ45,FALSE) -> 1
C47: Breedte plaat | K47: Lengte plaat | S47: Bewerkingen | T47: Machinegroep mogelijk | AA47: Sluiting | AB47: Lijmlip | AC47: Zijafval mini | AD47: Slitmaten | AF47: Ongeslit Emba | AG47: Lengte | AI47: Breedte | AK47: Hoogte | AM47: Lengte > Breedte | AN47: Max. boven elkaar | AO47: H < L | AP47: L > 2xB | AQ47: Handgreep | AR47: Stapel/bundel | AS47: Factoren | AT47: Stanssuport | AU47: Extra marge | AX47: H min 10% van L
B48: Fefco | C48: Lengte | D48: Breedte | E48: Hoogte | F48: Wanddikte | G48: Extra | H48: Extra waarde | I48: Toeslag | J48: Totaal (golfrichting) | K48: Lengte | L48: Breedte | M48: Hoogte | N48: Wanddikte | O48: Extra | P48: Extra waarde | Q48: Toeslag | R48: Totaal (lengte) | T48: Boxmaker | U48: Emba | V48: Stans | W48: Roda | X48: Plaat op maat | Y48: m2 / st | Z48: m2 tot | AA48: Nodig | AB48: Nodig | AC48: Nodig | AD48: Onder | AE48: Boven | AG48: minimaal | AH48: maximaal | AI48: Minimaal | AJ48: Maximaal | AK48: Minimaal | AL48: Maximaal | AM48: verplicht | AN48: Mini | AQ48: Mogelijk | AR48: Berekenen | AS48: Emba | AT48: Boxmaker | AU48: Fefco | AV48: Pallet berekenen | AW48: Afval boxm / product | AY48: Efficientie/ fefco | AZ48: Bedrukking mogelijk
A50: =IF($C$2=B50,1," ") | B50: 0110 | C50: 1 | J50: =(C50*$C$46)+(D50*$D$46)+(E50*$E$46)+(F50*$F$46)+(I50*$I$46)+(G50*H50) -> 300 | L50: 1 | R50: =(K50*$K$46)+(L50*$L$46)+(M50*$M$46)+(N50*$N$46)+(Q50*$Q$46)+(O50*P50) -> 250 | S50: 1 | T50: 1 | U50: 1 | W50: 1 | X50: 1 | Y50: =(J50/1000)*(R50/1000) -> 0.075 | Z50: =Y50*$C$3 -> 135 | AA50: 0 | AB50: 0 | AC50: 0 | AG50: 65 | AH50: 2000 | AI50: 65 | AJ50: 5000 | AK50: 0 | AL50: 0 | AM50: 0 | AN50: 4 | AO50: 0 | AP50: 0 | AQ50: 0 | AR50: 0 | AS50: 0 | AT50: 0 | AU50: 0 | AV50: 1 | AW50: 0,2 | AX50: 0 | AY50: 0.9 | AZ50: 0 | BD50: 0110
A51: =IF($C$2=B51,1," ") | B51: 0200 | D51: 0.5 | E51: 1 | F51: 1 | I51: 2 | J51: =(C51*$C$46)+(D51*$D$46)+(E51*$E$46)+(F51*$F$46)+(I51*$I$46)+(G51*H51) -> 232 | K51: 2 | L51: 2 | Q51: 7 | R51: =(K51*$K$46)+(L51*$L$46)+(M51*$M$46)+(N51*$N$46)+(Q51*$Q$46)+(O51*P51) -> 1114 | S51: 3 | T51: 1 | U51: 1 | Y51: =(J51/1000)*(R51/1000) -> 0.258448 | Z51: =Y51*$C$3 -> 465.2064 | AA51: 1 | AB51: 1 | AC51: 0 | AD51: =(0.5*D46)+I46 -> 127 | AE51: 0 | AF51: =J51-AD51-AE51 -> 105 | AG51: 100 | AH51: 2000 | AI51: =M23 -> 70 | AJ51: 1000 | AK51: =E41 -> 37 | AL51: 1200 | AM51: 1 | AN51: 4 | AO51: 0 | AP51: 0 | AQ51: 1 | AR51: 1 | AS51: 1 | AT51: 0 | AU51: 0 | AV51: 1 | AW51: 0,2 | AX51: 1 | AY51: 0.9 | AZ51: 1 | BD51: 0200
A52: =IF($C$2=B52,1," ") -> 1 | B52: 0201 | D52: 1 | E52: 1 | F52: 1 | I52: 4 | J52: =(C52*$C$46)+(D52*$D$46)+(E52*$E$46)+(F52*$F$46)+(I52*$I$46)+(G52*H52) -> 361 | K52: 2 | L52: 2 | Q52: 7 | R52: =(K52*$K$46)+(L52*$L$46)+(M52*$M$46)+(N52*$N$46)+(Q52*$Q$46)+(O52*P52) -> 1114 | S52: 3 | T52: 1 | U52: 1 | Y52: =(J52/1000)*(R52/1000) -> 0.402154 | Z52: =Y52*$C$3 -> 723.8772 | AA52: 1 | AB52: 1 | AC52: 0 | AD52: =(0.5*D46)+I46 -> 127 | AE52: =(0.5*D46)+I46 -> 127 | AF52: =J52-AD52-AE52 -> 107 | AG52: 100 | AH52: 2000 | AI52: =M23 -> 70 | AJ52: 1000 | AK52: =E41 -> 37 | AL52: 1200 | AM52: 1 | AN52: 4 | AO52: 0 | AP52: 0 | AQ52: 1 | AR52: 1 | AS52: 1 | AT52: 0 | AU52: 0 | AV52: 1 | AW52: 0,2 | AX52: 1 | AY52: 0.9 | AZ52: 1 | BD52: 0201
A53: =IF($C$2=B53,1," ") | B53: 0203 | D53: 2 | E53: 1 | F53: 2 | I53: 4 | J53: =(C53*$C$46)+(D53*$D$46)+(E53*$E$46)+(F53*$F$46)+(I53*$I$46)+(G53*H53) -> 614 | K53: 2 | L53: 2 | Q53: 7 | R53: =(K53*$K$46)+(L53*$L$46)+(M53*$M$46)+(N53*$N$46)+(Q53*$Q$46)+(O53*P53) -> 1114 | S53: 3 | T53: 1 | U53: 1 | Y53: =(J53/1000)*(R53/1000) -> 0.683996 | Z53: =Y53*$C$3 -> 1231.1928 | AA53: 1 | AB53: 1 | AC53: 0 | AD53: =D46+I46 -> 252 | AE53: =D46+I46 -> 252 | AF53: =J53-AD53-AE53 -> 110 | AG53: 100 | AH53: 2000 | AI53: =M24 -> 40 | AJ53: 1000 | AK53: =E41 -> 37 | AL53: 1200 | AM53: 1 | AN53: 4 | AO53: 0 | AP53: 1 | AQ53: 1 | AR53: 1 | AS53: 1 | AT53: 0 | AU53: 0 | AV53: 1 | AW53: 0,2 | AX53: 1 | AY53: 0.9 | AZ53: 1 | BD53: 0203
A54: =IF($C$2=B54,1," ") | B54: 0409 | C54: 1 | E54: 2 | F54: 2 | I54: 4 | J54: =(C54*$C$46)+(D54*$D$46)+(E54*$E$46)+(F54*$F$46)+(I54*$I$46)+(G54*H54) -> 514 | L54: 2 | M54: 3 | N54: 1 | Q54: 8 | R54: =(K54*$K$46)+(L54*$L$46)+(M54*$M$46)+(N54*$N$46)+(Q54*$Q$46)+(O54*P54) -> 819 | S54: 4 | T54: 1 | Y54: =(J54/1000)*(R54/1000) -> 0.420966 | Z54: =Y54*$C$3 -> 757.7388 | AA54: 0 | AB54: 0 | AC54: 0 | AD54: =E46+I46 -> 102 | AE54: =E46+I46 -> 102 | AG54: 200 | AH54: 2000 | AI54: 100 | AJ54: 1200 | AK54: 40 | AL54: 200 | AM54: 1 | AN54: 4 | AO54: 0 | AP54: 0 | AQ54: 0 | AR54: 0 | AS54: 0 | AT54: 0 | AU54: 0 | AV54: 1 | AW54: 0,2 | AX54: 0 | AY54: 0.9 | AZ54: 0 | BD54: 0409
A55: =IF($C$2=B55,1," ") | B55: 0410 | C55: 1 | E55: 2 | F55: 2 | I55: 4 | J55: =(C55*$C$46)+(D55*$D$46)+(E55*$E$46)+(F55*$F$46)+(I55*$I$46)+(G55*H55) -> 514 | L55: 2 | M55: 3 | N55: 1 | Q55: 8 | R55: =(K55*$K$46)+(L55*$L$46)+(M55*$M$46)+(N55*$N$46)+(Q55*$Q$46)+(O55*P55) -> 819 | S55: 4 | T55: 1 | Y55: =(J55/1000)*(R55/1000) -> 0.420966 | Z55: =Y55*$C$3 -> 757.7388 | AA55: 0 | AB55: 0 | AC55: 0 | AD55: =E46+I46 -> 102 | AE55: =E46+I46 -> 102 | AG55: 200 | AH55: 2000 | AI55: 100 | AJ55: 1200 | AK55: 40 | AL55: 200 | AM55: 1 | AN55: 4 | AO55: 0 | AP55: 0 | AQ55: 0 | AR55: 0 | AS55: 0 | AT55: =C8+C12 -> 102 | AU55: 0.04 | AV55: 1 | AW55: 0,5 | AX55: 0 | AY55: 0.85 | AZ55: 0 | BD55: 0410
A56: =IF($C$2=B56,1," ") | B56: 0412 | D56: 3 | E56: 2 | F56: 4 | I56: 8 | J56: =(C56*$C$46)+(D56*$D$46)+(E56*$E$46)+(F56*$F$46)+(I56*$I$46)+(G56*H56) -> 978 | K56: 1 | M56: 2 | O56: 2 | P56: 50 | Q56: 8 | R56: =(K56*$K$46)+(L56*$L$46)+(M56*$M$46)+(N56*$N$46)+(Q56*$Q$46)+(O56*P56) -> 616 | S56: 4 | T56: 1 | Y56: =(J56/1000)*(R56/1000) -> 0.602448 | Z56: =Y56*$C$3 -> 1084.4064 | AA56: 0 | AB56: 0 | AC56: 1 | AG56: 300 | AH56: 2000 | AI56: 100 | AJ56: 500 | AK56: 80 | AL56: 200 | AM56: 1 | AN56: 2 | AO56: 0 | AP56: 0 | AQ56: 0 | AR56: 0 | AS56: 0 | AT56: =(P56+C12) -> 52 | AU56: 0.04 | AV56: 1 | AW56: 0,4 | AX56: 0 | AY56: 0.82 | AZ56: 0 | BD56: 0412
A57: =IF($C$2=B57,1," ") | B57: 0427 | C57: 1 | E57: 4 | F57: 12 | I57: 12 | J57: =(C57*$C$46)+(D57*$D$46)+(E57*$E$46)+(F57*$F$46)+(I57*$I$46)+(G57*H57) -> 760 | L57: 2 | M57: 3 | N57: 1 | Q57: 8 | R57: =(K57*$K$46)+(L57*$L$46)+(M57*$M$46)+(N57*$N$46)+(Q57*$Q$46)+(O57*P57) -> 819 | V57: 0 | Y57: =(J57/1000)*(R57/1000) -> 0.62244 | Z57: =Y57*$C$3 -> 1120.392 | AA57: 0 | AB57: 0 | AC57: 0 | AG57: 80 | AH57: 1400 | AI57: 50 | AJ57: 550 | AK57: 23 | AL57: 200 | AM57: 0 | AN57: 0 | AO57: 1 | AP57: 0 | AQ57: 0 | AR57: 0 | AS57: 0 | AT57: 0 | AU57: 0.02 | AV57: 1 | AW57: 0 | AX57: 0 | AY57: 0.9 | BD57: 0427
A58: =IF($C$2=B58,1," ") | B58: 0421 | C58: 1 | E58: 4 | F58: 8 | I58: 12 | J58: =(C58*$C$46)+(D58*$D$46)+(E58*$E$46)+(F58*$F$46)+(I58*$I$46)+(G58*H58) -> 748 | L58: 2 | M58: 2 | N58: 1 | O58: 1 | P58: 30 | Q58: 4 | R58: =(K58*$K$46)+(L58*$L$46)+(M58*$M$46)+(N58*$N$46)+(Q58*$Q$46)+(O58*P58) -> 741 | V58: 0 | Y58: =(J58/1000)*(R58/1000) -> 0.554268 | Z58: =Y58*$C$3 -> 997.6824 | AA58: 0 | AB58: 0 | AC58: 0 | AG58: 80 | AH58: 1400 | AI58: 50 | AJ58: 550 | AK58: 23 | AL58: 200 | AM58: 0 | AN58: 0 | AO58: 1 | AP58: 0 | AQ58: 0 | AR58: 0 | AS58: 0 | AT58: 0 | AU58: 0.02 | AV58: 1 | AW58: 0 | AX58: 0 | AY58: 0.9 | BD58: 0421
A59: =IF($C$2=B59,1," ") | B59: 0422 | C59: 1 | E59: 4 | F59: 8 | I59: 12 | J59: =(C59*$C$46)+(D59*$D$46)+(E59*$E$46)+(F59*$F$46)+(I59*$I$46)+(G59*H59) -> 748 | L59: 1 | M59: 2 | Q59: 4 | R59: =(K59*$K$46)+(L59*$L$46)+(M59*$M$46)+(N59*$N$46)+(Q59*$Q$46)+(O59*P59) -> 458 | V59: 0 | Y59: =(J59/1000)*(R59/1000) -> 0.342584 | Z59: =Y59*$C$3 -> 616.6512 | AA59: 0 | AB59: 0 | AC59: 0 | AG59: 100 | AH59: 1400 | AI59: 50 | AJ59: 800 | AK59: 30 | AL59: 200 | AM59: 0 | AN59: 0 | AO59: 1 | AP59: 0 | AQ59: 0 | AR59: 0 | AS59: 0 | AT59: 0 | AU59: 0.02 | AV59: 1 | AW59: 0 | AX59: 0 | AY59: 0.9 | BD59: 0422
A60: =IF($C$2=B60,1," ") | B60: 0452 | D60: 1 | E60: 2 | F60: 2 | I60: 4 | J60: =(C60*$C$46)+(D60*$D$46)+(E60*$E$46)+(F60*$F$46)+(I60*$I$46)+(G60*H60) -> 464 | K60: 1 | M60: 2 | Q60: 4 | R60: =(K60*$K$46)+(L60*$L$46)+(M60*$M$46)+(N60*$N$46)+(Q60*$Q$46)+(O60*P60) -> 508 | S60: 2 | T60: 1 | Y60: =(J60/1000)*(R60/1000) -> 0.235712 | Z60: =Y60*$C$3 -> 424.2816 | AA60: 0 | AB60: 0 | AC60: 0 | AD60: =E46+I46 -> 102 | AE60: =E46+I46 -> 102 | AG60: 150 | AH60: 2000 | AI60: 100 | AJ60: 1200 | AK60: 45 | AL60: 400 | AM60: 1 | AN60: 4 | AO60: 0 | AP60: 0 | AQ60: 0 | AR60: 0 | AS60: 0 | AT60: 0 | AU60: 0 | AV60: 1 | AW60: 0,2 | AX60: 0 | AY60: 0.9 | BD60: 0452
A61: =IF($C$2=B61,1," ") | B61: 0501 | E61: 1 | I61: 0 | J61: =(C61*$C$46)+(D61*$D$46)+(E61*$E$46)+(F61*$F$46)+(I61*$I$46)+(G61*H61) -> 100 | K61: 2 | L61: 2 | Q61: 7 | R61: =(K61*$K$46)+(L61*$L$46)+(M61*$M$46)+(N61*$N$46)+(Q61*$Q$46)+(O61*P61) -> 1114 | S61: 4 | T61: 1 | U61: 1 | Y61: =(J61/1000)*(R61/1000) -> 0.1114 | Z61: =Y61*$C$3 -> 200.52 | AA61: 1 | AB61: 1 | AC61: 0 | AG61: 100 | AH61: 2000 | AI61: =M24 -> 40 | AJ61: 1000 | AK61: 100 | AL61: 1200 | AM61: 1 | AN61: 4 | AO61: 0 | AP61: 0 | AQ61: 1 | AR61: 1 | AS61: 1 | AT61: 0 | AU61: 0 | AV61: 1 | AW61: 0 | AX61: 1 | AY61: 0.9 | AZ61: 1 | BD61: 0501
A62: =IF($C$2=B62,1," ") | B62: 0401 | D62: 2 | E62: 2 | F62: 2 | I62: 8 | J62: =(C62*$C$46)+(D62*$D$46)+(E62*$E$46)+(F62*$F$46)+(I62*$I$46)+(G62*H62) -> 722 | K62: 1 | M62: 2 | O62: 2 | P62: 50 | Q62: 8 | R62: =(K62*$K$46)+(L62*$L$46)+(M62*$M$46)+(N62*$N$46)+(Q62*$Q$46)+(O62*P62) -> 616 | S62: 4 | T62: 1 | Y62: =(J62/1000)*(R62/1000) -> 0.444752 | Z62: =Y62*$C$3 -> 800.5536 | AA62: 0 | AB62: 0 | AC62: 1 | AD62: =(0.5*D46)+E46+(3*I46)+F46 -> 234 | AE62: =(0.5*D46)+E46+(3*I46)+F46 -> 234 | AG62: 200 | AH62: 2000 | AI62: 100 | AJ62: 800 | AK62: 20 | AL62: 80 | AM62: 1 | AN62: =IF(J62+C166>=I183,1,2) -> 1 | AO62: 0 | AP62: 0 | AQ62: 0 | AR62: 0 | AS62: 0 | AT62: =(P62+(C12*3)+C8) -> 156 | AU62: 0.04 | AV62: 1 | AW62: 2 | AX62: 0 | AY62: 0.82 | BD62: 0401
A63: =IF($C$2=B63,1," ") | B63: 0471 | D63: 2 | E63: 3 | F63: 2 | I63: 8 | J63: =(C63*$C$46)+(D63*$D$46)+(E63*$E$46)+(F63*$F$46)+(I63*$I$46)+(G63*H63) -> 822 | K63: 1 | L63: 2 | N63: 6 | Q63: 4 | R63: =(K63*$K$46)+(L63*$L$46)+(M63*$M$46)+(N63*$N$46)+(Q63*$Q$46)+(O63*P63) -> 826 | V63: 0 | Y63: =(J63/1000)*(R63/1000) -> 0.678972 | Z63: =Y63*$C$3 -> 1222.1496 | AA63: 0 | AB63: 0 | AC63: 0 | AG63: 180 | AH63: 1400 | AI63: 80 | AJ63: 600 | AK63: 60 | AL63: 400 | AM63: 1 | AN63: 0 | AO63: 1 | AP63: 0 | AQ63: 0 | AR63: 0 | AS63: 0 | AT63: 0 | AU63: 0.02 | AV63: 1 | AW63: 0 | AX63: 0 | AY63: 0.9 | BD63: 0471
A64: =IF($C$2=B64,1," ") | B64: 0933 | C64: 1 | D64: 1 | E64: 1 | F64: 1 | J64: =(C64*$C$46)+(D64*$D$46)+(E64*$E$46)+(F64*$F$46)+(I64*$I$46)+(G64*H64) -> 653 | K64: 1 | L64: 1 | M64: 1 | N64: 1 | O64: 1 | R64: =(K64*$K$46)+(L64*$L$46)+(M64*$M$46)+(N64*$N$46)+(Q64*$Q$46)+(O64*P64) -> 653 | T64: 0 | U64: 0 | V64: 0 | W64: 0 | X64: 0 | Y64: =(J64/1000)*(R64/1000) -> 0.426409 | Z64: =Y64*$C$3 -> 767.5362 | AA64: 0 | AB64: 0 | AC64: 0 | AG64: 99 | AH64: 9999 | AI64: 99 | AJ64: 9999 | AK64: 99 | AL64: 9999 | AM64: 0 | AN64: 0 | AO64: 0 | AP64: 0 | AQ64: 0 | AR64: 0 | AS64: 0 | AT64: 0 | AU64: 0 | AV64: 0 | AW64: 0 | AX64: 0 | AY64: 0.9 | BA64: Wordt niet berekend | BD64: 0933
A65: =IF($C$2=B65,1," ") | B65: 0701 | C65: 1 | D65: 1 | E65: 1 | F65: 1 | J65: =(C65*$C$46)+(D65*$D$46)+(E65*$E$46)+(F65*$F$46)+(I65*$I$46)+(G65*H65) -> 653 | K65: 1 | L65: 1 | M65: 1 | N65: 1 | O65: 1 | R65: =(K65*$K$46)+(L65*$L$46)+(M65*$M$46)+(N65*$N$46)+(Q65*$Q$46)+(O65*P65) -> 653 | T65: 0 | U65: 0 | V65: 0 | W65: 0 | X65: 0 | Y65: =(J65/1000)*(R65/1000) -> 0.426409 | Z65: =Y65*$C$3 -> 767.5362 | AA65: 0 | AB65: 0 | AC65: 0 | AG65: 99 | AH65: 9999 | AI65: 99 | AJ65: 9999 | AK65: 99 | AL65: 9999 | AM65: 0 | AN65: 0 | AO65: 0 | AP65: 0 | AQ65: 0 | AR65: 0 | AS65: 0 | AT65: 0 | AU65: 0 | AV65: 0 | AW65: 0 | AX65: 0 | AY65: 0.9 | BA65: Wordt niet berekend | BD65: 0711
A66: =IF($C$2=B66,1," ") | J66: =(C66*$C$46)+(D66*$D$46)+(E66*$E$46)+(F66*$F$46)+(I66*$I$46)+(G66*H66) -> 0 | R66: =(K66*$K$46)+(L66*$L$46)+(M66*$M$46)+(N66*$N$46)+(Q66*$Q$46)+(O66*P66) -> 0 | Y66: =(J66/1000)*(R66/1000) -> 0 | Z66: =Y66*$C$3 -> 0
A67: =IF($C$2=B67,1," ") | J67: =(C67*$C$46)+(D67*$D$46)+(E67*$E$46)+(F67*$F$46)+(I67*$I$46)+(G67*H67) -> 0 | R67: =(K67*$K$46)+(L67*$L$46)+(M67*$M$46)+(N67*$N$46)+(Q67*$Q$46)+(O67*P67) -> 0 | Y67: =(J67/1000)*(R67/1000) -> 0 | Z67: =Y67*$C$3 -> 0
A68: =IF($C$2=B68,1," ") | J68: =(C68*$C$46)+(D68*$D$46)+(E68*$E$46)+(F68*$F$46)+(I68*$I$46)+(G68*H68) -> 0 | R68: =(K68*$K$46)+(L68*$L$46)+(M68*$M$46)+(N68*$N$46)+(Q68*$Q$46)+(O68*P68) -> 0 | Y68: =(J68/1000)*(R68/1000) -> 0 | Z68: =Y68*$C$3 -> 0
A69: =IF($C$2=B69,1," ") | J69: =(C69*$C$46)+(D69*$D$46)+(E69*$E$46)+(F69*$F$46)+(I69*$I$46)+(G69*H69) -> 0 | R69: =(K69*$K$46)+(L69*$L$46)+(M69*$M$46)+(N69*$N$46)+(Q69*$Q$46)+(O69*P69) -> 0 | Y69: =(J69/1000)*(R69/1000) -> 0 | Z69: =Y69*$C$3 -> 0
